Workbook

Sheet Scholar
A1: Title | B1: Link | C1: Pubblication Class | D1: Q1 | E1: Q2 | F1: Q3 | G1: Q4 | H1: Q5 | I1: Q6 | J1: Q7 | K1: Exc.Crit | L1: Inc.Crit | M1: Pubblication Venue | N1: Vanue Name | O1: IDQ | P1: CDQ | Q1: FDQ | R1: Selected
A2: A New Smart Contract Anomaly Detection Method by Fusing Opcode and Source Code Features for Blockchain Services | B2: https://ieeexplore.ieee.org/abstract/document/10130487 | C2: PS | D2: =Info!$B$51 -> 0 | E2: =Info!$B$53 -> 1 | L2: 2 | M2: Journal Article | N2: IEEE Transactions on Network and Service Management | O2: 1 | P2: =(D2+E2)/2 -> 0.5 | Q2: =(O2+P2)/2 -> 0.75 | R2: =IF(_xlfn.BITAND(P2>0.4999, Q2>0.4999)=1,1,0) -> 1
A3: A Novel Smart Contract Vulnerability Detection Method Based on Information Graph and Ensemble Learning | B3: https://www.mdpi.com/1424-8220/22/9/3581 | C3: PS | D3: =Info!$B$16 -> 1 | E3: =Info!$B$53 -> 1 | L3: 1 | M3: Journal Article | N3: Sensors | O3: 0.8 | P3: =(D3+E3)/2 -> 1 | Q3: =(O3+P3)/2 -> 0.9 | R3: =IF(_xlfn.BITAND(P3>0.4999, Q3>0.4999)=1,1,0) -> 1
A4: A survey on smart contract vulnerabilities: Data sources, detection and repair | B4: https://www.sciencedirect.com/science/article/pii/S0950584923000757 | C4: Survey | D4: =Info!$B$16 -> 1 | E4: =Info!$B$19 -> 1 | F4: =Info!$B$25 -> 0.6 | G4: =Info!$B$31 -> 0.3 | H4: =Info!$B$37 -> 0 | I4: =Info!$B$40 -> 0 | J4: =Info!$B$42 -> 1 | L4: 1 | M4: Journal Article | N4: Information and Software Technology | O4: 1 | P4: =(D4+E4+F4+G4+H4+I4+J4)/6 -> 0.65 | Q4: =(O4+P4)/2 -> 0.825 | R4: =IF(_xlfn.BITAND(P4>0.4999, Q4>0.4999)=1,1,0) -> 1
A5: A systematic literature review of undiscovered vulnerabilities and tools in smart contract technology | B5: https://www.degruyter.com/document/doi/10.1515/jisys-2023-0038/html | C5: SLR | D5: =Info!$B$16 -> 1 | E5: =Info!$B$19 -> 1 | F5: =Info!$B$24 -> 1 | G5: =Info!$B$29 -> 1 | H5: =Info!$B$35 -> 0.6 | I5: =Info!$B$40 -> 0 | J5: =Info!$B$42 -> 1 | L5: 1,2,3 | M5: Journal Article | N5: Journal of Intelligent Systems | O5: 0.8 | P5: =(D5+E5+F5+G5+H5+I5+J5)/6 -> 0.93333333 | Q5: =(O5+P5)/2 -> 0.86666667 | R5: =IF(_xlfn.BITAND(P5>0.4999, Q5>0.4999)=1,1,0) -> 1
A6: ASSBert: Active and semi-supervised bert for smart contract vulnerability detection | B6: https://www.sciencedirect.com/science/article/pii/S221421262300008X?casa_token=L17-2HJTgKsAAAAA:23B-zr-DrCcMyTvK3pFKbj39IVgciQFPTp_DaQSmLk8oOziBxuzZ7HZ2uvb-4gb_A9oGJQHW | C6: PS | D6: =Info!$B$49 -> 0.6 | E6: =Info!$B$53 -> 1 | L6: 2,3 | M6: Journal Article | N6: Journal of Information Security and Applications | O6: 1 | P6: =(D6+E6)/2 -> 0.8 | Q6: =(O6+P6)/2 -> 0.9 | R6: =IF(_xlfn.BITAND(P6>0.4999, Q6>0.4999)=1,1,0) -> 1
A7: AUTOMATED MUTATION ANALYSIS FOR SMART CONTRACT USING AMA TOOL WITH ENHANCED GA AND MACHINE LEARNING APPROACH | B7: https://www.jatit.org/volumes/Vol101No21/22Vol101No21.pdf | C7: PS | D7: =Info!$B$51 -> 0 | E7: =Info!$B$53 -> 1 | L7: 2 | M7: Journal Article | N7: Journal of Theoretical and Applied Information Technology | O7: 0.5 | P7: =(D7+E7)/2 -> 0.5 | Q7: =(O7+P7)/2 -> 0.5 | R7: =IF(_xlfn.BITAND(P7>0.4999, Q7>0.4999)=1,1,0) -> 1
A8: Automation and smart materials in detecting smart contracts vulnerabilities in Blockchain using deep learning | B8: https://www.sciencedirect.com/science/article/pii/S2214785321030273?casa_token=iI8eqBHd0dAAAAAA:IsrBBuibA8NSlZ2kPSsIOCioFA4YnsqFasV7Uz0FasX4NaFgid2wbeF7pHvjC-05SulB-Rii | C8: PS | D8: =Info!$B$48 -> 1 | E8: =Info!$B$54 -> 0 | L8: 2,3 | M8: Journal Article | N8: Materials Today: Proceedings | O8: 0.8 | P8: =(D8+E8)/2 -> 0.5 | Q8: =(O8+P8)/2 -> 0.65 | R8: =IF(_xlfn.BITAND(P8>0.4999, Q8>0.4999)=1,1,0) -> 1
A9: AutoMESC: Automatic Framework for Mining and Classifying Ethereum Smart Contract Vulnerabilities and Their Fixes | B9: https://ieeexplore.ieee.org/abstract/document/10371421?casa_token=mSO-2-SQH6wAAAAA:TxW1DRrUmpfyKVVIY9sJfnUq6o24yaXucDPJ7Q-RuH778THgkvPEOJ9lbptgqemmDqQ1M-s | C9: PS | D9: =Info!$B$51 -> 0 | E9: =Info!$B$53 -> 1 | L9: 2 | M9: Conference Proceeding or Workshop | N9: Euromicro Conference on Software Engineering and Advanced Applications | O9: 0.5 | P9: =(D9+E9)/2 -> 0.5 | Q9: =(O9+P9)/2 -> 0.5 | R9: =IF(_xlfn.BITAND(P9>0.4999, Q9>0.4999)=1,1,0) -> 1
A10: Data Flow-driven and Attention Mechanism-enabled Smart Contract Vulnerability Detection for Secure and Green Blockchain-based Service Networks | B10: https://ieeexplore.ieee.org/abstract/document/10279381 | C10: PS | D10: =Info!$B$51 -> 0 | E10: =Info!$B$53 -> 1 | L10: 2 | M10: Conference Proceeding or Workshop | N10: IEEE International Conference on Communications (ICC) | O10: 1 | P10: =(D10+E10)/2 -> 0.5 | Q10: =(O10+P10)/2 -> 0.75 | R10: =IF(_xlfn.BITAND(P10>0.4999, Q10>0.4999)=1,1,0) -> 1
A11: Demystifying Random Number in Ethereum Smart Contract: Taxonomy, Vulnerability Identification, and Attack Detection | B11: https://ieeexplore.ieee.org/abstract/document/10111037?casa_token=QEdDIblGokYAAAAA:0B4lB52irnYXlCYtNceVkNaGiA5hElARm1S8YLbzMMQtbyF5ZRpIQp76i-3VF9gQPwTO31g | C11: PS | D11: =Info!$B$50 -> 0.3 | E11: =Info!$B$53 -> 1 | L11: 1 | M11: Journal Article | N11: IEEE Transactions on Software Engineering | O11: 1 | P11: =(D11+E11)/2 -> 0.65 | Q11: =(O11+P11)/2 -> 0.825 | R11: =IF(_xlfn.BITAND(P11>0.4999, Q11>0.4999)=1,1,0) -> 1
A12: Design and evaluation of highly accurate smart contract code vulnerability detection framework | B12: https://link.springer.com/article/10.1007/s10618-023-00981-1 | C12: PS | D12: =Info!$B$51 -> 0 | E12: =Info!$B$53 -> 1 | L12: 1.2 | M12: Journal Article | N12: Data Mining and Knowledge Discovery | O12: 1 | P12: =(D12+E12)/2 -> 0.5 | Q12: =(O12+P12)/2 -> 0.75 | R12: =IF(_xlfn.BITAND(P12>0.4999, Q12>0.4999)=1,1,0) -> 1
A13: Detecting functional and security-related issues in smartcontracts: A systematic literature review | B13: https://onlinelibrary.wiley.com/doi/epdf/10.1002/spe.3156 | C13: SLR | D13: =Info!$B$16 -> 1 | E13: =Info!$B$21 -> 0.3 | F13: =Info!$B$26 -> 0.3 | G13: =Info!$B$29 -> 1 | H13: =Info!$B$34 -> 1 | I13: =Info!$B$39 -> 1 | J13: =Info!$B$43 -> 0.5 | L13: 1.2 | M13: Journal Article | N13: Software - Practice and Experience | O13: 0.8 | P13: =(D13+E13+F13+G13+H13+I13+J13)/7 -> 0.72857143 | Q13: =(O13+P13)/2 -> 0.76428571 | R13: =IF(_xlfn.BITAND(P13>0.4999, Q13>0.4999)=1,1,0) -> 1
A14: EDIT: A data inspection tool for smart contracts temporal behavior modeling and prediction | B14: https://www.sciencedirect.com/science/article/pii/S0167739X24000013 | C14: PS | D14: =Info!$B$51 -> 0 | E14: =Info!$B$53 -> 1 | L14: 2,3 | M14: Journal Article | N14: Future Generation Computer Systems | O14: 1 | P14: =(D14+E14)/2 -> 0.5 | Q14: =(O14+P14)/2 -> 0.75 | R14: =IF(_xlfn.BITAND(P14>0.4999, Q14>0.4999)=1,1,0) -> 1
A15: Empirical Review of Smart Contract and DeFi Security: Vulnerability Detection and Automated Repair | B15: https://arxiv.org/abs/2309.02391 | C15: Survey | D15: =Info!$B$17 -> 0 | E15: =Info!$B$19 -> 1 | F15: =Info!$B$25 -> 0.6 | G15: =Info!$B$29 -> 1 | H15: =Info!$B$34 -> 1 | I15: =Info!$B$39 -> 1 | J15: =Info!$B$42 -> 1 | L15: 1.3 | M15: Arxiv Paper or Preprint | O15: 0.2 | P15: =(D15+E15+F15+G15+H15+I15+J15)/7 -> 0.8 | Q15: =(O15+P15)/2 -> 0.5 | R15: =IF(_xlfn.BITAND(P15>0.4999, Q15>0.4999)=1,1,0) -> 1
A16: Enhancing Smart-Contract Security through Machine Learning: A Survey of Approaches and Techniques | B16: https://www.mdpi.com/2079-9292/12/9/2046 | C16: Survey | D16: =Info!$B$17 -> 0 | E16: =Info!$B$20 -> 0.6 | F16: =Info!$B$26 -> 0.3 | G16: =Info!$B$30 -> 0.6 | H16: =Info!$B$35 -> 0.6 | I16: =Info!$B$40 -> 0 | J16: =Info!$B$42 -> 1 | L16: 1 | M16: Journal Article | N16: Electronics | O16: 0.8 | P16: =(D16+E16+F16+G16+H16+I16+J16)/6 -> 0.51666667 | Q16: =(O16+P16)/2 -> 0.65833333 | R16: =IF(_xlfn.BITAND(P16>0.4999, Q16>0.4999)=1,1,0) -> 1
A17: ESCORT: Ethereum Smart COntRacTs Vulnerability Detection using Deep Neural Network and Transfer Learning | B17: https://arxiv.org/abs/2103.12607 | C17: PS | D17: 1 | E17: 1 | L17: 2 | M17: Arxiv Paper or Preprint | O17: 0.2 | P17: =(D17+E17)/2 -> 1 | Q17: =(O17+P17)/2 -> 0.6 | R17: =IF(_xlfn.BITAND(P17>0.4999, Q17>0.4999)=1,1,0) -> 1
A18: EtherProv: Provenance-Aware Detection, Analysis, and Mitigation of Ethereum Smart Contract Security Issues | B18: https://ieeexplore.ieee.org/abstract/document/9680507?casa_token=EvobFcapGO8AAAAA:77f_1k1cz7PPbn_R-F_IJdxxZf7jSADmcjNxkRh-oNewQmKb3GQK9IwdCv1A8Ikm6fWqoRE | C18: PS | D18: =Info!$B$49 -> 0.6 | E18: =Info!$B$53 -> 1 | L18: 1 | M18: Conference Proceeding or Workshop | N18: IEEE International Conference on Blockchain | O18: 0.2 | P18: =(D18+E18)/2 -> 0.8 | Q18: =(O18+P18)/2 -> 0.5 | R18: =IF(_xlfn.BITAND(P18>0.4999, Q18>0.4999)=1,1,0) -> 1
A19: GraphSA: Smart Contract Vulnerability Detection Combining Graph Neural Networks and Static Analysis | B19: https://ebooks.iospress.nl/doi/10.3233/FAIA230374 | C19: PS | D19: =Info!$B$17 -> 0 | E19: =Info!$B$53 -> 1 | L19: 2,3 | M19: Book Section | N19: IOS Press | O19: 1 | P19: =(D19+E19)/2 -> 0.5 | Q19: =(O19+P19)/2 -> 0.75 | R19: =IF(_xlfn.BITAND(P19>0.4999, Q19>0.4999)=1,1,0) -> 1
A20: GRATDet: Smart Contract Vulnerability Detector Based on Graph Representation and Transformer | B20: https://cdn.techscience.cn/files/cmc/2023/TSP_CMC-76-2/TSP_CMC_38878/TSP_CMC_38878.pdf | C20: PS | D20: =Info!$B$51 -> 0 | E20: =Info!$B$53 -> 1 | L20: 2 | M20: Journal Article | N20: Computers, Materials & Continua | O20: 0.8 | P20: =(D20+E20)/2 -> 0.5 | Q20: =(O20+P20)/2 -> 0.65 | R20: =IF(_xlfn.BITAND(P20>0.4999, Q20>0.4999)=1,1,0) -> 1
A21: Improvement and Optimization of Vulnerability Detection Methods for Ethernet Smart Contracts | B21: https://ieeexplore.ieee.org/abstract/document/10192903 | C21: PS | D21: =Info!$B$17 -> 0 | E21: =Info!$B$20 -> 0.6 | F21: =Info!$B$26 -> 0.3 | G21: =Info!$B$30 -> 0.6 | H21: =Info!$B$35 -> 0.6 | I21: =Info!$B$40 -> 0 | J21: =Info!$B$42 -> 1 | L21: 2 | M21: Journal Article | N21: IEEE Access | O21: 1 | P21: =(D21+E21+F21+G21+H21+I21+J21)/6 -> 0.51666667 | Q21: =(O21+P21)/2 -> 0.75833333 | R21: =IF(_xlfn.BITAND(P21>0.4999, Q21>0.4999)=1,1,0) -> 1
A22: MSmart: Smart Contract Vulnerability Analysis and Improved Strategies Based on Smartcheck | B22: https://www.mdpi.com/2076-3417/13/3/1733 | C22: PS | D22: =Info!$B$51 -> 0 | E22: =Info!$B$53 -> 1 | L22: 2 | M22: Journal Article | N22: Applied Science | O22: 0.5 | P22: =(D22+E22)/2 -> 0.5 | Q22: =(O22+P22)/2 -> 0.5 | R22: =IF(_xlfn.BITAND(P22>0.4999, Q22>0.4999)=1,1,0) -> 1
A23: ReSuMo: a regression strategy and tool for mutation testing of solidity smart contracts | B23: https://link.springer.com/article/10.1007/s11219-023-09637-1 | C23: PS | D23: =Info!$B$17 -> 0 | E23: =Info!$B$53 -> 1 | L23: 2,3 | M23: Journal Article | N23: Software Quality Journal | O23: 0.5 | P23: =(D23+E23)/2 -> 0.5 | Q23: =(O23+P23)/2 -> 0.5 | R23: =IF(_xlfn.BITAND(P23>0.4999, Q23>0.4999)=1,1,0) -> 1
A24: SCGRU: A Model for Ethereum Smart Contract Vulnerability Detection Combining CNN and BiGRU-Attention | B24: https://ieeexplore.ieee.org/abstract/document/10270857 | C24: PS | D24: =Info!$B$17 -> 0 | E24: =Info!$B$53 -> 1 | L24: 2,3 | M24: Conference Proceeding or Workshop | N24: IEEE International Conference on Signal and Image Processing (ICSIP) | O24: 0.5 | P24: =(D24+E24)/2 -> 0.5 | Q24: =(O24+P24)/2 -> 0.5 | R24: =IF(_xlfn.BITAND(P24>0.4999, Q24>0.4999)=1,1,0) -> 1
A25: Security Risks and Best Practices for Blockchain and Smart Contracts: A Systematic Literature Review | B25: https://ieeexplore.ieee.org/abstract/document/10278055 | C25: SLR | D25: =Info!$B$16 -> 1 | E25: =Info!$B$20 -> 0.6 | F25: =Info!$B$25 -> 0.6 | G25: =Info!$B$32 -> 0 | H25: =Info!$B$37 -> 0 | I25: =Info!$B$40 -> 0 | J25: =Info!$B$42 -> 1 | L25: 1 | M25: Conference Proceeding or Workshop | N25: International Conference on Information Management and Technology (ICIMTech) | O25: 1 | P25: =(D25+E25+F25+G25+H25+I25+J25)/6 -> 0.53333333 | Q25: =(O25+P25)/2 -> 0.76666667 | R25: =IF(_xlfn.BITAND(P25>0.4999, Q25>0.4999)=1,1,0) -> 1
A26: Smart Contract and DeFi Security Tools: Do They Meet the Needs of Practitioners? | B26: https://synthical.com/article/ed404388-ffad-11ed-9b54-72eb57fa10b3 | C26: Survey | D26: 1 | E26: 1 | F26: 0.6 | G26: 0.3 | H26: 0.6 | I26: 0 | J26: 1 | L26: 1 | M26: Conference Proceeding or Workshop | N26: IEEE/ACM International Conference on Software Engineering | O26: 1 | P26: =(D26+E26+F26+G26+H26+I26+J26)/7 -> 0.64285714 | Q26: =(O26+P26)/2 -> 0.82142857 | R26: =IF(_xlfn.BITAND(P26>0.4999, Q26>0.4999)=1,1,0) -> 1
A27: Smart Contracts Security Threats and Solutions | B27: https://www.igi-global.com/gateway/article/full-text-pdf/304048&riu=true | C27: SLR | D27: =Info!$B$16 -> 1 | E27: =Info!$B$20 -> 0.6 | F27: =Info!$B$24 -> 1 | G27: =Info!$B$32 -> 0 | H27: =Info!$B$37 -> 0 | I27: =Info!$B$40 -> 0 | J27: =Info!$B$43 -> 0.5 | L27: 1 | M27: Journal Article | N27: International Journal of Information Technology and Web Engineering | O27: 0.5 | P27: =(D27+E27+F27+G27+H27+I27+J27)/6 -> 0.51666667 | Q27: =(O27+P27)/2 -> 0.50833333 | R27: =IF(_xlfn.BITAND(P27>0.4999, Q27>0.4999)=1,1,0) -> 1
A28: SmartFast: an accurate and robust formal analysis tool for Ethereum smart contracts | B28: https://link.springer.com/article/10.1007/s10664-022-10218-2 | C28: PS | D28: =Info!$B$50 -> 0.3 | E28: =Info!$B$53 -> 1 | L28: 2,3 | M28: Journal Article | N28: Empirical Software Engineering | O28: 1 | P28: =(D28+E28)/2 -> 0.65 | Q28: =(O28+P28)/2 -> 0.825 | R28: =IF(_xlfn.BITAND(P28>0.4999, Q28>0.4999)=1,1,0) -> 1
A29: SuMo: A mutation testing approach and tool for the Ethereum blockchain | B29: https://www.sciencedirect.com/science/article/pii/S0164121222001418 | C29: PS | D29: =Info!$B$49 -> 0.6 | E29: =Info!$B$53 -> 1 | L29: 2,3 | M29: Journal Article | N29: Journal of Systems and Software | O29: 1 | P29: =(D29+E29)/2 -> 0.8 | Q29: =(O29+P29)/2 -> 0.9 | R29: =IF(_xlfn.BITAND(P29>0.4999, Q29>0.4999)=1,1,0) -> 1
A30: Systematic Review of Ethereum Smart Contract Security Vulnerabilities, Analysis Methods and Tools | B30: https://web.archive.org/web/20210909005434id_/https://repositum.tuwien.at/bitstream/20.500.12708/18323/1/Rameder%20Heidelinde%20-%202021%20-%20Systematic%20Review%20of%20Ethereum%20Smart%20Contract...pdf | C30: SLR | D30: =Info!$B$16 -> 1 | E30: =Info!$B$16 -> 1 | F30: =Info!$B$24 -> 1 | G30: =Info!$B$29 -> 1 | H30: =Info!$B$34 -> 1 | I30: =Info!$B$39 -> 1 | J30: =Info!$B$44 -> 0 | L30: 1,2,3 | M30: Thesis or Seminar Paper | N30: PhD Thesis | O30: 0.2 | P30: =(D30+E30+F30+G30+H30+I30+J30)/7 -> 0.85714286 | Q30: =(O30+P30)/2 -> 0.52857143 | R30: =IF(_xlfn.BITAND(P30>0.4999, Q30>0.4999)=1,1,0) -> 1
A31: The State of Ethereum Smart Contracts Security: Vulnerabilities, Countermeasures, and Tool Support | B31: https://www.mdpi.com/2624-800X/2/2/19 | C31: Survey | D31: =Info!$B$17 -> 0 | E31: =Info!$B$19 -> 1 | F31: =Info!$B$24 -> 1 | G31: =Info!$B$30 -> 0.6 | H31: =Info!$B$35 -> 0.6 | I31: =Info!$B$39 -> 1 | J31: =Info!$B$43 -> 0.5 | L31: 1 | M31: Journal Article | N31: Journal of Cybersecurity and Privacy | O31: 0.5 | P31: =(D31+E31+F31+G31+H31+I31+J31)/7 -> 0.67142857 | Q31: =(O31+P31)/2 -> 0.58571429 | R31: =IF(_xlfn.BITAND(P31>0.4999, Q31>0.4999)=1,1,0) -> 1
A32: Towards the Assessment and the Improvement of Smart Contract Security | B32: https://flore.unifi.it/handle/2158/1272428 | C32: Survey | D32: =Info!$B$16 -> 1 | E32: =Info!$B$19 -> 1 | F32: =Info!$B$24 -> 1 | G32: =Info!$B$29 -> 1 | H32: =Info!$B$34 -> 1 | I32: =Info!$B$40 -> 0 | J32: =Info!$B$43 -> 0.5 | L32: 1 | M32: Thesis or Seminar Paper | N32: Thesis | O32: 0.2 | P32: =(D32+E32+F32+G32+H32+I32+J32)/6 -> 0.91666667 | Q32: =(O32+P32)/2 -> 0.55833333 | R32: =IF(_xlfn.BITAND(P32>0.4999, Q32>0.4999)=1,1,0) -> 1
A33: Unveiling the Landscape of Smart Contract Vulnerabilities: A Detailed Examination and Codification of Vulnerabilities in Prominent Blockchains | B33: https://papers.ssrn.com/sol3/papers.cfm?abstract_id=4650383 | C33: Survey | D33: =Info!$B$17 -> 0 | E33: =Info!$B$19 -> 1 | F33: =Info!$B$24 -> 1 | G33: =Info!$B$32 -> 0 | H33: =Info!$B$37 -> 0 | I33: =Info!$B$39 -> 1 | J33: =Info!$B$42 -> 1 | L33: 1 | M33: Journal Article | N33: International Journal of Computer Networks & Communications (IJCNC) | O33: 0.5 | P33: =(D33+E33+F33+G33+H33+I33+J33)/7 -> 0.57142857 | Q33: =(O33+P33)/2 -> 0.53571429 | R33: =IF(_xlfn.BITAND(P33>0.4999, Q33>0.4999)=1,1,0) -> 1
A34: Vulnerability and Transaction Behavior Based Detection of Malicious Smart Contracts | B34: https://link.springer.com/chapter/10.1007/978-3-030-94029-4_6 | C34: Survey | D34: =Info!$B$16 -> 1 | E34: =Info!$B$19 -> 1 | F34: =Info!$B$24 -> 1 | G34: =Info!$B$30 -> 0.6 | H34: =Info!$B$36 -> 0.3 | I34: =Info!$B$40 -> 0 | J34: =Info!$B$43 -> 0.5 | L34: 2 | M34: Conference Proceeding or Workshop | N34: Cyberspace Safety and Security | O34: 0.4 | P34: =(D34+E34+F34+G34+H34+I34+J34)/6 -> 0.73333333 | Q34: =(O34+P34)/2 -> 0.56666667 | R34: =IF(_xlfn.BITAND(P34>0.4999, Q34>0.4999)=1,1,0) -> 1
A35: ConvMHSA-SCVD: Enhancing Smart Contract Vulnerability Detection through a Knowledge-Driven and Data-Driven Framework | B35: https://ieeexplore.ieee.org/abstract/document/10301256 | C35: PS | D35: =Info!$B$51 -> 0 | E35: =Info!$B$53 -> 1 | L35: 2 | M35: Conference Proceeding or Workshop | N35: International Symposium on Software Reliability Engineering (ISSRE) | O35: 0.4 | P35: =(D35+E35)/2 -> 0.5 | Q35: =(O35+P35)/2 -> 0.45 | R35: =IF(_xlfn.BITAND(P35>0.4999, Q35>0.4999)=1,1,0) -> 0
A36: Contextual Language Model and Transfer Learning for Reentrancy Vulnerability Detection in Smart Contracts | B36: https://dl.acm.org/doi/abs/10.1145/3628797.3628945 | C36: PS | D36: =Info!$B$51 -> 0 | E36: =Info!$B$54 -> 0 | L36: 2 | M36: Conference Proceeding or Workshop | N36: SOICT '23: Proceedings of the 12th International Symposium on Information and Communication Technology | O36: 0.4 | P36: =(D36+E36)/2 -> 0 | Q36: =(O36+P36)/2 -> 0.2 | R36: =IF(_xlfn.BITAND(P36>0.4999, Q36>0.4999)=1,1,0) -> 0
A37: A Smart Contract Vulnerability Detection Model Based on Syntactic and Semantic Fusion Learning | B37: https://www.hindawi.com/journals/wcmc/2023/9212269/ | C37: PS | D37: =Info!$B$51 -> 0 | E37: =Info!$B$54 -> 0 | L37: 2 | M37: Journal Article | N37: Wireless Communications and Mobile Computing | O37: 0.8 | P37: =(D37+E37)/2 -> 0 | Q37: =(O37+P37)/2 -> 0.4 | R37: =IF(_xlfn.BITAND(P37>0.4999, Q37>0.4999)=1,1,0) -> 0
A38: Smart contract vulnerability detection based on a semantic code structure and a self-designed neural network | B38: https://www.sciencedirect.com/science/article/pii/S0045790623001908 | C38: PS | D38: =Info!$B$51 -> 0 | E38: =Info!$B$54 -> 0 | L38: 2 | M38: Journal Article | N38: Computers and Electrical Engineering | O38: 1 | P38: =(D38+E38)/2 -> 0 | Q38: =(O38+P38)/2 -> 0.5 | R38: =IF(_xlfn.BITAND(P38>0.4999, Q38>0.4999)=1,1,0) -> 0
A39: A Smart Contract Vulnerability Detection Method Based on Multimodal Feature Fusion and Deep Learning | B39: https://www.mdpi.com/2227-7390/11/23/4823 | C39: PS | D39: =Info!$B$51 -> 0 | E39: =Info!$B$54 -> 0 | L39: 2 | M39: Journal Article | N39: Mathematics | O39: 1 | P39: =(D39+E39)/2 -> 0 | Q39: =(O39+P39)/2 -> 0.5 | R39: =IF(_xlfn.BITAND(P39>0.4999, Q39>0.4999)=1,1,0) -> 0
A40: Detecting Smart Contract Vulnerabilities with Combined Binary and Multiclass Classification | B40: https://www.mdpi.com/2410-387X/7/3/34 | C40: PS | D40: =Info!$B$51 -> 0 | E40: =Info!$B$54 -> 0 | L40: 2 | M40: Journal Article | N40: Cryptography | O40: 0.8 | P40: =(D40+E40)/2 -> 0 | Q40: =(O40+P40)/2 -> 0.4 | R40: =IF(_xlfn.BITAND(P40>0.4999, Q40>0.4999)=1,1,0) -> 0
A41: Fine-grained smart contract vulnerability detection by heterogeneous code feature learning and automated dataset construction | B41: https://www.sciencedirect.com/science/article/pii/S016412122300314X?casa_token=ya4gUTqe5o8AAAAA:IT9sZYUq2FC5Po8TLXJ7PoTcvnGVSfU1w0AAnKmtwnkGWehJmtrSvcaYCMgWlk25ROquMz2U | C41: PS | D41: =Info!$B$51 -> 0 | E41: =Info!$B$54 -> 0 | L41: 2 | M41: Journal Article | N41: Journal of Systems and Software | O41: 1 | P41: =(D41+E41)/2 -> 0 | Q41: =(O41+P41)/2 -> 0.5 | R41: =IF(_xlfn.BITAND(P41>0.4999, Q41>0.4999)=1,1,0) -> 0
A42: Smart contract vulnerability detection based on semantic graph and residual graph convolutional networks with edge attention | B42: https://www.sciencedirect.com/science/article/pii/S0164121223001000 | C42: PS | D42: =Info!$B$51 -> 0 | E42: =Info!$B$54 -> 0 | L42: 2 | M42: Journal Article | N42: Journal of Systems and Software | O42: 1 | P42: =(D42+E42)/2 -> 0 | Q42: =(O42+P42)/2 -> 0.5 | R42: =IF(_xlfn.BITAND(P42>0.4999, Q42>0.4999)=1,1,0) -> 0
A43: SCGformer: Smart contract vulnerability detection based on control flow graph and transformer | B43: https://ietresearch.onlinelibrary.wiley.com/doi/full/10.1049/blc2.12046 | C43: PS | D43: =Info!$B$51 -> 0 | E43: =Info!$B$53 -> 1 | L43: 2 | M43: Journal Article | N43: The Institution of Engineering and Technology | O43: 0.2 | P43: =(D43+E43)/2 -> 0.5 | Q43: =(O43+P43)/2 -> 0.35 | R43: =IF(_xlfn.BITAND(P43>0.4999, Q43>0.4999)=1,1,0) -> 0
A44: Smart Contract Vulnerability Detection Based on Deep Learning and Multimodal Decision Fusion | B44: https://www.mdpi.com/1424-8220/23/16/7246 | C44: PS | D44: =Info!$B$51 -> 0 | E44: =Info!$B$54 -> 0 | L44: 2 | M44: Journal Article | N44: Sensors | O44: 0.8 | P44: =(D44+E44)/2 -> 0 | Q44: =(O44+P44)/2 -> 0.4 | R44: =IF(_xlfn.BITAND(P44>0.4999, Q44>0.4999)=1,1,0) -> 0
A45: Improving Robustness and Accuracy of Ponzi Scheme Detection on Ethereum Using Time-Dependent Features | B45: https://arxiv.org/abs/2308.16391 | C45: PS | D45: =Info!$B$51 -> 0 | E45: =Info!$B$54 -> 0 | L45: 2 | M45: Arxiv Paper or Preprint | O45: 0.2 | P45: =(D45+E45)/2 -> 0 | Q45: =(O45+P45)/2 -> 0.1 | R45: =IF(_xlfn.BITAND(P45>0.4999, Q45>0.4999)=1,1,0) -> 0
A46: Vulnerability Detection of Smart Contracts Based on Bidirectional GRU and Attention Mechanism | B46: https://link.springer.com/chapter/10.1007/978-3-031-48325-7_21 | C46: PS | D46: =Info!$B$51 -> 0 | E46: =Info!$B$53 -> 1 | L46: 2 | M46: Book Section | O46: 0.2 | P46: =(D46+E46)/2 -> 0.5 | Q46: =(O46+P46)/2 -> 0.35 | R46: =IF(_xlfn.BITAND(P46>0.4999, Q46>0.4999)=1,1,0) -> 0
A47: Smart Contract Vulnerability Detection Based on Automated Feature Extraction and Feature Interaction | B47: https://ieeexplore.ieee.org/abstract/document/10319764 | C47: PS | D47: =Info!$B$51 -> 0 | E47: =Info!$B$54 -> 0 | L47: 2 | M47: Journal Article | N47: IEEE Transactions on Knowledge and Data Engineering | O47: 1 | P47: =(D47+E47)/2 -> 0 | Q47: =(O47+P47)/2 -> 0.5 | R47: =IF(_xlfn.BITAND(P47>0.4999, Q47>0.4999)=1,1,0) -> 0
A48: Optimizing smart contract vulnerability detection via multi-modality code and entropy embedding | B48: https://www.sciencedirect.com/science/article/pii/S0164121223000948 | C48: PS | D48: =Info!$B$51 -> 0 | E48: =Info!$B$54 -> 0 | L48: 2 | M48: Journal Article | N48: Journal of Systems and Software | O48: 1 | P48: =(D48+E48)/2 -> 0 | Q48: =(O48+P48)/2 -> 0.5 | R48: =IF(_xlfn.BITAND(P48>0.4999, Q48>0.4999)=1,1,0) -> 0
A49: Vulnerability Detection of Smart Contracts Based on Bidirectional GRU and Attention Mechanism | B49: https://books.google.com/books?hl=it&lr=&id=4x3nEAAAQBAJ&oi=fnd&pg=PA276&dq=+(%E2%80%9Csmart+contract%E2%80%9D+OR+%E2%80%9Csmart+contracts%E2%80%9D+OR+Ethereum)+AND+(vulnerability+OR+vulnerabilities+OR+bug+OR+bugs+OR+security+OR+analysis+OR+detection+OR+tool+OR+verification)&ots=QS1SRii5yW&sig=ab-mjqZulvTgEXTwBKQRY-m47d4 | C49: PS | D49: =Info!$B$51 -> 0 | E49: =Info!$B$53 -> 1 | M49: Book Section | O49: 0.2 | P49: =(D49+E49)/2 -> 0.5 | Q49: =(O49+P49)/2 -> 0.35 | R49: =IF(_xlfn.BITAND(P49>0.4999, Q49>0.4999)=1,1,0) -> 0
A50: Modelling And Simulation For Detecting Vulnerabilities And Security Threats Of Smart Contracts Using Machine Learning | B50: https://ieeexplore.ieee.org/abstract/document/10305867 | C50: PS | D50: =Info!$B$51 -> 0 | E50: =Info!$B$54 -> 0 | L50: 2 | M50: Conference Proceeding or Workshop | N50: International Conference on Fog and Mobile Edge Computing (FMEC) | O50: 0.2 | P50: =(D50+E50)/2 -> 0 | Q50: =(O50+P50)/2 -> 0.1 | R50: =IF(_xlfn.BITAND(P50>0.4999, Q50>0.4999)=1,1,0) -> 0
A51: Smart Contract Vulnerability Detection Based on Critical Combination Path and Deep Learning | B51: https://dl.acm.org/doi/abs/10.1145/3586102.3586135 | C51: PS | D51: =Info!$B$51 -> 0 | E51: =Info!$B$20 -> 0.6 | L51: 2 | M51: Conference Proceeding or Workshop | N51: ICCNS '22: Proceedings of the 2022 12th International Conference on Communication and Network Security | O51: 0.2 | P51: =(D51+E51)/2 -> 0.3 | Q51: =(O51+P51)/2 -> 0.25 | R51: =IF(_xlfn.BITAND(P51>0.4999, Q51>0.4999)=1,1,0) -> 0
A52: Ethereum Phishing Detection Based on Graph Structure and Transaction Sequence Features Fusion | B52: https://link.springer.com/chapter/10.1007/978-981-99-4402-6_18 | C52: PS | D52: =Info!$B$51 -> 0 | E52: =Info!$B$53 -> 1 | L52: 2 | M52: Conference Proceeding or Workshop | N52: International Conference on Service Science | O52: 0.2 | P52: =(D52+E52)/2 -> 0.5 | Q52: =(O52+P52)/2 -> 0.35 | R52: =IF(_xlfn.BITAND(P52>0.4999, Q52>0.4999)=1,1,0) -> 0
A53: VulnSense: Efficient Vulnerability Detection in Ethereum Smart Contracts by Multimodal Learning with Graph Neural Network and Language Model | B53: https://arxiv.org/abs/2309.08474 | C53: PS | D53: =Info!$B$51 -> 0 | E53: =Info!$B$53 -> 1 | M53: Arxiv Paper or Preprint | N53: Cryptography and Security | O53: 0.2 | P53: =(D53+E53)/2 -> 0.5 | Q53: =(O53+P53)/2 -> 0.35 | R53: =IF(_xlfn.BITAND(P53>0.4999, Q53>0.4999)=1,1,0) -> 0
A54: VulnSense: Efficient Vulnerability Detection in Ethereum Smart Contracts by Multimodal Learning with Graph Neural Network and Language Model | B54: https://ui.adsabs.harvard.edu/abs/2023arXiv230908474D/abstract | C54: PS | D54: =Info!$B$51 -> 0 | E54: =Info!$B$53 -> 1 | L54: 2 | M54: Arxiv Paper or Preprint | N54: Cryptography and Security | O54: 0.2 | P54: =(D54+E54)/2 -> 0.5 | Q54: =(O54+P54)/2 -> 0.35 | R54: =IF(_xlfn.BITAND(P54>0.4999, Q54>0.4999)=1,1,0) -> 0
A55: Strengthening Smart Contracts: An Investigation into Vulnerability Detection and Mitigation in Smart Contracts with a Web Application Based Tool | B55: https://www.proquest.com/docview/2896757878?pq-origsite=gscholar&fromopenview=true&sourcetype=Scholarly%20Journals | C55: PS | D55: =Info!$B$17 -> 0 | E55: =Info!$B$53 -> 1 | L55: 2 | M55: Journal Article | N55: International Research Journal of Innovations in Engineering and Technology | O55: 0.2 | P55: =(D55+E55)/2 -> 0.5 | Q55: =(O55+P55)/2 -> 0.35 | R55: =IF(_xlfn.BITAND(P55>0.4999, Q55>0.4999)=1,1,0) -> 0
A56: Detection and Analysis of Ethereum Energy Smart Contracts | B56: https://www.mdpi.com/2076-3417/13/10/6027 | C56: PS | D56: =Info!$B$51 -> 0 | E56: =Info!$B$54 -> 0 | L56: 2 | M56: Journal Article | N56: Applied Sciences | O56: 0.5 | P56: =(D56+E56)/2 -> 0 | Q56: =(O56+P56)/2 -> 0.25 | R56: =IF(_xlfn.BITAND(P56>0.4999, Q56>0.4999)=1,1,0) -> 0
A57: Highsimb: A Concrete Blockchain High Simulation with Contract Vulnerability Detection for Ethereum and Hyperledger Fabric | B57: https://link.springer.com/chapter/10.1007/978-3-031-20099-1_39 | C57: PS | D57: =Info!$B$51 -> 0 | E57: =Info!$B$53 -> 1 | L57: 2 | M57: Conference Proceeding or Workshop | N57: Machine Learning for Cyber Security | O57: 0.2 | P57: =(D57+E57)/2 -> 0.5 | Q57: =(O57+P57)/2 -> 0.35 | R57: =IF(_xlfn.BITAND(P57>0.4999, Q57>0.4999)=1,1,0) -> 0
A58: EF-CF Fuzzer and Extorsionware: Uncovering and Exploiting Smart Contract Vulnerabilities | B58: https://thesis.unipd.it/handle/20.500.12608/53846 | C58: PS | D58: =Info!$B$51 -> 0 | E58: =Info!$B$54 -> 0 | L58: 2 | M58: Thesis or Seminar Paper | N58: PhD Thesis | O58: 0.2 | P58: =(D58+E58)/2 -> 0 | Q58: =(O58+P58)/2 -> 0.1 | R58: =IF(_xlfn.BITAND(P58>0.4999, Q58>0.4999)=1,1,0) -> 0
A59: Smart Contracts Classification and Vulnerabilities Detection | B59: https://www.informatics-europe.org/images/ECSS/ECSS2022/members-spotlight/Proceedings-Early-Career-Researchers-Workshop-ECSS2021.pdf#page=43 | C59: PS | D59: =Info!$B$17 -> 0 | E59: =Info!$B$53 -> 1 | L59: 2 | M59: Conference Proceeding or Workshop | N59: Proceedings-Early-Career-Researchers-Workshop-ECSS | O59: 0.2 | P59: =(D59+E59)/2 -> 0.5 | Q59: =(O59+P59)/2 -> 0.35 | R59: =IF(_xlfn.BITAND(P59>0.4999, Q59>0.4999)=1,1,0) -> 0
A60: Fraud Detection in Ethereum Using Web-scraping and Natural Language Processing Techniques | B60: https://www.research-collection.ethz.ch/handle/20.500.11850/523134 | C60: PS | D60: =Info!$B$51 -> 0 | E60: =Info!$B$54 -> 0 | L60: 2 | M60: Thesis or Seminar Paper | N60: Master Thesis | O60: 0.2 | P60: =(D60+E60)/2 -> 0 | Q60: =(O60+P60)/2 -> 0.1 | R60: =IF(_xlfn.BITAND(P60>0.4999, Q60>0.4999)=1,1,0) -> 0
A61: Detection of Re-Entrancy, Timestamp Dependence and Infinite Loop Attack in Smart Contracts Using Graph Convolution Network | B61: https://ijisae.org/index.php/IJISAE/article/view/3471 | C61: PS | D61: =Info!$B$51 -> 0 | E61: =Info!$B$54 -> 0 | L61: 1.2 | M61: Journal Article | N61: International Journal of INTELLIGENT SYSTEMS AND APPLICATIONS IN ENGINEERING | O61: 0.5 | P61: =(D61+E61)/2 -> 0 | Q61: =(O61+P61)/2 -> 0.25 | R61: =IF(_xlfn.BITAND(P61>0.4999, Q61>0.4999)=1,1,0) -> 0
A62: Deep Learning-Based Malicious Smart Contract and Intrusion Detection System for IoT Environment | B62: https://www.mdpi.com/2227-7390/11/2/418 | C62: PS | D62: =Info!$B$51 -> 0 | E62: =Info!$B$54 -> 0 | L62: 1.2 | M62: Journal Article | N62: Mathematics | O62: 1 | P62: =(D62+E62)/2 -> 0 | Q62: =(O62+P62)/2 -> 0.5 | R62: =IF(_xlfn.BITAND(P62>0.4999, Q62>0.4999)=1,1,0) -> 0
A63: Extorsionware: Exploiting Smart Contract Vulnerabilities for Fun and Profit | B63: https://arxiv.org/abs/2203.09843 | C63: PS | D63: =Info!$B$51 -> 0 | E63: =Info!$B$54 -> 0 | L63: 1 | M63: Arxiv Paper or Preprint | N63: Cryptography and Security | O63: 0.2 | P63: =(D63+E63)/2 -> 0 | Q63: =(O63+P63)/2 -> 0.1 | R63: =IF(_xlfn.BITAND(P63>0.4999, Q63>0.4999)=1,1,0) -> 0
A64: A bytecode-based integrated detection and repair method for reentrancy vulnerabilities in smart contracts | B64: https://ietresearch.onlinelibrary.wiley.com/doi/full/10.1049/blc2.12043 | C64: PS | D64: =Info!$B$51 -> 0 | E64: =Info!$B$54 -> 0 | L64: 1 | M64: Journal Article | N64: The Institution of Engineering and Technology | O64: 0.2 | P64: =(D64+E64)/2 -> 0 | Q64: =(O64+P64)/2 -> 0.1 | R64: =IF(_xlfn.BITAND(P64>0.4999, Q64>0.4999)=1,1,0) -> 0
A65: Hybrid analysis of smart contracts and malicious behaviors in ethereum | B65: https://theses.lib.polyu.edu.hk/handle/200/11411 | C65: PS | D65: =Info!$B$51 -> 0 | E65: =Info!$B$54 -> 0 | L65: 1 | M65: Thesis or Seminar Paper | N65: PhD Thesis | O65: 0.2 | P65: =(D65+E65)/2 -> 0 | Q65: =(O65+P65)/2 -> 0.1 | R65: =IF(_xlfn.BITAND(P65>0.4999, Q65>0.4999)=1,1,0) -> 0
A66: Smart Contract Vulnerability Detection Based on Deep and Cross Network | B66: https://ieeexplore.ieee.org/abstract/document/9824581 | C66: PS | D66: =Info!$B$50 -> 0.3 | E66: =Info!$B$54 -> 0 | L66: 1 | M66: Conference Proceeding or Workshop | N66: International Conference on Computer Engineering and Applications | O66: 0.2 | P66: =(D66+E66)/2 -> 0.15 | Q66: =(O66+P66)/2 -> 0.175 | R66: =IF(_xlfn.BITAND(P66>0.4999, Q66>0.4999)=1,1,0) -> 0
A67: PrAIoritize: Learning to Prioritize Smart Contract Bugs and Vulnerabilities | B67: https://arxiv.org/abs/2308.11082 | C67: PS | D67: =Info!$B$51 -> 0 | E67: =Info!$B$53 -> 1 | L67: 1 | M67: Conference Proceeding or Workshop | N67: Software Engineering | O67: 0.4 | P67: =(D67+E67)/2 -> 0.5 | Q67: =(O67+P67)/2 -> 0.45 | R67: =IF(_xlfn.BITAND(P67>0.4999, Q67>0.4999)=1,1,0) -> 0
A68: A study on gas cost of ethereum smart contracts and performance of blockchain on simulation tool | B68: https://link.springer.com/article/10.1007/s12083-023-01598-3 | C68: PS | D68: =Info!$B$51 -> 0 | E68: =Info!$B$54 -> 0 | L68: 1 | M68: Journal Article | N68: Peer-to-Peer Networking and Applications | O68: 0.8 | P68: =(D68+E68)/2 -> 0 | Q68: =(O68+P68)/2 -> 0.4 | R68: =IF(_xlfn.BITAND(P68>0.4999, Q68>0.4999)=1,1,0) -> 0
A69: Ponzi scheme detection in smart contracts using the integration of deep learning and formal verification | B69: https://ietresearch.onlinelibrary.wiley.com/doi/full/10.1049/blc2.12056 | C69: PS | D69: =Info!$B$51 -> 0 | E69: =Info!$B$54 -> 0 | L69: 1 | M69: Journal Article | N69: The Institution of Engineering and Technology | O69: 0.2 | P69: =(D69+E69)/2 -> 0 | Q69: =(O69+P69)/2 -> 0.1 | R69: =IF(_xlfn.BITAND(P69>0.4999, Q69>0.4999)=1,1,0) -> 0
A70: The Detection of Fraudulent Smart Contracts Based on ECA-EfficientNet and Data Enhancement | B70: https://cdn.techscience.cn/files/cmc/2023/TSP_CMC-77-3/TSP_CMC_40253/TSP_CMC_40253.pdf | C70: PS | D70: =Info!$B$51 -> 0 | E70: =Info!$B$54 -> 0 | L70: 1 | M70: Journal Article | N70: Computers, Materials & Continua | O70: 0.8 | P70: =(D70+E70)/2 -> 0 | Q70: =(O70+P70)/2 -> 0.4 | R70: =IF(_xlfn.BITAND(P70>0.4999, Q70>0.4999)=1,1,0) -> 0
A71: Peculiar: Smart Contract Vulnerability Detection Based on Crucial Data Flow Graph and Pre-training Techniques | B71: https://ieeexplore.ieee.org/abstract/document/9700296?casa_token=lmrU2K8lxAMAAAAA:w85DTIFlG9-ewMjMMCbw2QTfMA03uOAtCuwtATVBOeHYRImk5ezYIv2ZHSimPwUGi4puGMw | C71: PS | D71: =Info!$B$16 -> 1 | E71: =Info!$B$54 -> 0 | L71: 1 | M71: Conference Proceeding or Workshop | N71: International Symposium on Software Reliability Engineering (ISSRE) | O71: 0.4 | P71: =(D71+E71)/2 -> 0.5 | Q71: =(O71+P71)/2 -> 0.45 | R71: =IF(_xlfn.BITAND(P71>0.4999, Q71>0.4999)=1,1,0) -> 0
A72: A Practical Detection and Defense Scheme Against Smart Contract Attacks Based on Transaction Features | B72: https://link.springer.com/chapter/10.1007/978-981-99-4430-9_21 | C72: PS | D72: =Info!$B$51 -> 0 | E72: =Info!$B$54 -> 0 | L72: 1 | M72: Conference Proceeding or Workshop | N72: International Symposium on Mobile Internet Security | O72: 0.2 | P72: =(D72+E72)/2 -> 0 | Q72: =(O72+P72)/2 -> 0.1 | R72: =IF(_xlfn.BITAND(P72>0.4999, Q72>0.4999)=1,1,0) -> 0
A73: A lightweight approach to smart contracts supporting safety, security, and privacy | B73: https://www.sciencedirect.com/science/article/pii/S2352220822000256 | C73: PS | D73: =Info!$B$50 -> 0.3 | E73: =Info!$B$54 -> 0 | L73: 1 | M73: Journal Article | N73: Journal of Logical and Algebraic Methods in Programming | O73: 0.5 | P73: =(D73+E73)/2 -> 0.15 | Q73: =(O73+P73)/2 -> 0.325 | R73: =IF(_xlfn.BITAND(P73>0.4999, Q73>0.4999)=1,1,0) -> 0
A74: STUDY ON SMART CONTRACT HONEYPOT COMBINED WITH MACHINE LEARNING TECHNIQUES AND DATA ANALYSIS | B74: https://jmcms.s3.amazonaws.com/wp-content/uploads/2022/08/24093022/jmcms-2208001-STUDY-ON-SMART-CONTRACT-HONEYPOT-Swapna-Siddamsetti.pdf | C74: PS | D74: =Info!$B$51 -> 0 | E74: =Info!$B$54 -> 0 | L74: 1 | M74: Journal Article | N74: JOURNAL OF MECHANICS OF CONTINUA AND MATHEMATICAL SCIENCES | O74: 0.2 | P74: =(D74+E74)/2 -> 0 | Q74: =(O74+P74)/2 -> 0.1 | R74: =IF(_xlfn.BITAND(P74>0.4999, Q74>0.4999)=1,1,0) -> 0
A75: Vulnerabilities and Open Issues of Smart Contracts: A Systematic Mapping | B75: https://arxiv.org/abs/2104.12295 | C75: SLR | D75: =Info!$B$16 -> 1 | E75: =Info!$B$22 -> 0 | F75: =Info!$B$27 -> 0 | G75: =Info!$B$31 -> 0.3 | H75: =Info!$B$36 -> 0.3 | I75: =Info!$B$40 -> 0 | J75: =Info!$B$44 -> 0 | M75: Conference Proceeding or Workshop | N75: Computational Science and Its Applications – ICCSA 2021 | O75: 0.5 | P75: =(D75+E75+F75+G75+H75+I75+J75)/6 -> 0.26666667 | Q75: =(O75+P75)/2 -> 0.38333333 | R75: =IF(_xlfn.BITAND(P75>0.4999, Q75>0.4999)=1,1,0) -> 0
A76: Vulnerabilities and Open Issues of Smart Contracts: A Systematic Mapping | B76: https://link.springer.com/chapter/10.1007/978-3-030-86973-1_1#Tab3 | C76: SLR | D76: =Info!$B$16 -> 1 | E76: =Info!$B$22 -> 0 | F76: =Info!$B$27 -> 0 | G76: =Info!$B$31 -> 0.3 | H76: =Info!$B$36 -> 0.3 | I76: =Info!$B$40 -> 0 | J76: =Info!$B$44 -> 0 | L76: 1 | M76: Conference Proceeding or Workshop | N76: Computational Science and Its Applications – ICCSA 2021 | O76: 0.5 | P76: =(D76+E76+F76+G76+H76+I76+J76)/6 -> 0.26666667 | Q76: =(O76+P76)/2 -> 0.38333333 | R76: =IF(_xlfn.BITAND(P76>0.4999, Q76>0.4999)=1,1,0) -> 0
A77: From Smart to Secure Contracts: Automated Security Assessment and Improvement of Ethereum Smart Contracts | B77: https://orbilu.uni.lu/handle/10993/51118 | C77: Survey | D77: =Info!$B$17 -> 0 | E77: =Info!$B$19 -> 1 | F77: =Info!$B$25 -> 0.6 | G77: =Info!$B$31 -> 0.3 | H77: =Info!$B$35 -> 0.6 | I77: =Info!$B$40 -> 0 | J77: =Info!$B$43 -> 0.5 | L77: 3 | M77: Thesis or Seminar Paper | N77: PhD Thesis | O77: 0.2 | P77: =(D77+E77+F77+G77+H77+I77+J77)/6 -> 0.5 | Q77: =(O77+P77)/2 -> 0.35 | R77: =IF(_xlfn.BITAND(P77>0.4999, Q77>0.4999)=1,1,0) -> 0
A78: From Smart to Secure Contracts: Automated Security Assessment and Improvement of Ethereum Smart Contracts | B78: https://mediatum.ub.tum.de/doc/1641114/jmaww4489686mnp3sw290kuf3.Christof%20Ferreira%20Torres.pdf | C78: Survey | D78: =Info!$B$17 -> 0 | E78: =Info!$B$19 -> 1 | F78: =Info!$B$25 -> 0.6 | G78: =Info!$B$31 -> 0.3 | H78: =Info!$B$35 -> 0.6 | I78: =Info!$B$40 -> 0 | J78: =Info!$B$43 -> 0.5 | M78: Thesis or Seminar Paper | N78: PhD Thesis | O78: 0.2 | P78: =(D78+E78+F78+G78+H78+I78+J78)/6 -> 0.5 | Q78: =(O78+P78)/2 -> 0.35 | R78: =IF(_xlfn.BITAND(P78>0.4999, Q78>0.4999)=1,1,0) -> 0
A79: Research on smart contract vulnerability detection method based on domain features of solidity contracts and attention mechanism | B79: https://www.researchgate.net/publication/370644368_Research_on_smart_contract_vulnerability_detection_method_based_on_domain_features_of_solidity_contracts_and_attention_mechanism | C79: Survey | D79: =Info!$B$17 -> 0 | E79: =Info!$B$20 -> 0.6 | F79: =Info!$B$26 -> 0.3 | G79: =Info!$B$31 -> 0.3 | H79: =Info!$B$36 -> 0.3 | I79: =Info!$B$40 -> 0 | J79: =Info!$B$42 -> 1 | L79: 3 | M79: Journal Article | N79: Journal of Intelligent & Fuzzy Systems | O79: 0.8 | P79: =(D79+E79+F79+G79+H79+I79+J79)/6 -> 0.41666667 | Q79: =(O79+P79)/2 -> 0.60833333 | R79: =IF(_xlfn.BITAND(P79>0.4999, Q79>0.4999)=1,1,0) -> 0
A80: Smart contract: a survey towards extortionate vulnerability detection and security enhancement | B80: https://link.springer.com/article/10.1007/s11276-023-03587-z | C80: Survey | D80: =Info!$B$17 -> 0 | E80: =Info!$B$20 -> 0.6 | F80: =Info!$B$26 -> 0.3 | G80: =Info!$B$31 -> 0.3 | H80: =Info!$B$36 -> 0.3 | I80: =Info!$B$40 -> 0 | J80: =Info!$B$42 -> 1 | L80: 2 | M80: Journal Article | N80: Wireless Networks | O80: 0.8 | P80: =(D80+E80+F80+G80+H80+I80+J80)/6 -> 0.41666667 | Q80: =(O80+P80)/2 -> 0.60833333 | R80: =IF(_xlfn.BITAND(P80>0.4999, Q80>0.4999)=1,1,0) -> 0
A81: Combatting Front-Running in Smart Contracts: Attack Mining, Benchmark Construction and Vulnerability Detector Evaluation | B81: https://ieeexplore.ieee.org/abstract/document/10108045 | C81: Survey | D81: =Info!$B$17 -> 0 | E81: =Info!$B$20 -> 0.6 | F81: =Info!$B$26 -> 0.3 | G81: =Info!$B$31 -> 0.3 | H81: =Info!$B$36 -> 0.3 | I81: =Info!$B$40 -> 0 | J81: =Info!$B$42 -> 1 | L81: 2 | M81: Journal Article | N81: IEEE Transactions on Software Engineering | O81: 1 | P81: =(D81+E81+F81+G81+H81+I81+J81)/6 -> 0.41666667 | Q81: =(O81+P81)/2 -> 0.70833333 | R81: =IF(_xlfn.BITAND(P81>0.4999, Q81>0.4999)=1,1,0) -> 0
A82: Security analysis of smart contract based rating and review systems: the perilous state of blockchain-based recommendation practices | B82: https://www.tandfonline.com/doi/full/10.1080/09540091.2022.2066065 | C82: Survey | D82: =Info!$B$17 -> 0 | E82: =Info!$B$20 -> 0.6 | F82: =Info!$B$26 -> 0.3 | G82: =Info!$B$31 -> 0.3 | H82: =Info!$B$36 -> 0.3 | I82: =Info!$B$40 -> 0 | J82: =Info!$B$43 -> 0.5 | L82: 2 | M82: Journal Article | N82: CONNECTION SCIENCE | O82: 0.8 | P82: =(D82+E82+F82+G82+H82+I82+J82)/6 -> 0.33333333 | Q82: =(O82+P82)/2 -> 0.56666667 | R82: =IF(_xlfn.BITAND(P82>0.4999, Q82>0.4999)=1,1,0) -> 0
A83: Detecting Vulnerabilities in Smart Contract within Blockchain: A Review and Comparative Analysis of Key Approaches | B83: https://ieeexplore.ieee.org/abstract/document/9932169 | C83: Survey | D83: =Info!$B$17 -> 0 | E83: =Info!$B$20 -> 0.6 | F83: =Info!$B$26 -> 0.3 | G83: =Info!$B$31 -> 0.3 | H83: =Info!$B$37 -> 0 | I83: =Info!$B$40 -> 0 | J83: =Info!$B$43 -> 0.5 | L83: 2 | M83: Conference Proceeding or Workshop | N83: International Conference on Next Generation Computing Applications | O83: 0.2 | P83: =(D83+E83+F83+G83+H83+I83+J83)/6 -> 0.28333333 | Q83: =(O83+P83)/2 -> 0.24166667 | R83: =IF(_xlfn.BITAND(P83>0.4999, Q83>0.4999)=1,1,0) -> 0
A84: DESIGNING AND EVALUATING DL-MODEL FOR VULNERABILITY DETECTION IN SMART CONTRACTS | B84: http://ais.khpi.edu.ua/article/view/292286 | C84: Survey | D84: =Info!$B$17 -> 0 | E84: =Info!$B$21 -> 0.3 | F84: =Info!$B$27 -> 0 | G84: =Info!$B$32 -> 0 | H84: =Info!$B$37 -> 0 | I84: =Info!$B$40 -> 0 | J84: =Info!$B$42 -> 1 | L84: 2 | M84: Conference Proceeding or Workshop | N84: International Conference on Advanced Information Systems Engineering | O84: 1 | P84: =(D84+E84+F84+G84+H84+I84+J84)/6 -> 0.21666667 | Q84: =(O84+P84)/2 -> 0.60833333 | R84: =IF(_xlfn.BITAND(P84>0.4999, Q84>0.4999)=1,1,0) -> 0
A85: Model Checking and Gas Optimization of Move Smart Contracts, and Transaction Order Dependency Detection and Rectification | B85: https://www.proquest.com/openview/3fb3dbefede8061f461635b5fc687ab3/1?cbl=18750&diss=y&pq-origsite=gscholar&parentSessionId=fy9LcjO8oXi1gTWKyV9svvgCHyN76salsyg2t8oIF%2Fs%3D | C85: Survey | D85: =Info!$B$17 -> 0 | E85: =Info!$B$21 -> 0.3 | F85: =Info!$B$27 -> 0 | G85: =Info!$B$32 -> 0 | H85: =Info!$B$37 -> 0 | I85: =Info!$B$40 -> 0 | J85: =Info!$B$42 -> 1 | L85: 2 | M85: Thesis or Seminar Paper | N85: PhD Thesis | O85: 0.2 | P85: =(D85+E85+F85+G85+H85+I85+J85)/6 -> 0.21666667 | Q85: =(O85+P85)/2 -> 0.20833333 | R85: =IF(_xlfn.BITAND(P85>0.4999, Q85>0.4999)=1,1,0) -> 0
A86: Detecting Security Breaches on Smart Contracts Through Techniques and Tools a Brief Review: Applications and Challenges | B86: https://link.springer.com/chapter/10.1007/978-981-99-2742-5_38 | C86: Survey | D86: =Info!$B$17 -> 0 | E86: =Info!$B$22 -> 0 | F86: =Info!$B$27 -> 0 | G86: =Info!$B$32 -> 0 | H86: =Info!$B$37 -> 0 | I86: =Info!$B$40 -> 0 | J86: =Info!$B$42 -> 1 | L86: 2 | M86: Conference Proceeding or Workshop | N86: International Conference on Cognitive and Intelligent Computing | O86: 0.2 | P86: =(D86+E86+F86+G86+H86+I86+J86)/6 -> 0.16666667 | Q86: =(O86+P86)/2 -> 0.18333333 | R86: =IF(_xlfn.BITAND(P86>0.4999, Q86>0.4999)=1,1,0) -> 0
A87: A Survey of Security Vulnerabilities and Detection Methods for Smart Contracts | B87: https://link.springer.com/chapter/10.1007/978-981-99-9247-8_43 | C87: Survey | D87: =Info!$B$17 -> 0 | E87: =Info!$B$20 -> 0.6 | F87: =Info!$B$26 -> 0.3 | G87: =Info!$B$31 -> 0.3 | H87: =Info!$B$36 -> 0.3 | I87: =Info!$B$40 -> 0 | J87: =Info!$B$42 -> 1 | L87: 1.2 | M87: Conference Proceeding or Workshop | N87: Proceedings of the 13th International Conference on Computer Engineering and Networks | O87: 0.2 | P87: =(D87+E87+F87+G87+H87+I87+J87)/6 -> 0.41666667 | Q87: =(O87+P87)/2 -> 0.30833333 | R87: =IF(_xlfn.BITAND(P87>0.4999, Q87>0.4999)=1,1,0) -> 0
A88: Requirements for the development of smart contracts and an overview of smart contract vulnerabilities at the Solidity code level on the Ethereum platform | B88: http://dspace.op.edu.ua/jspui/bitstream/123456789/13894/1/157-%d0%a2%d0%b5%d0%ba%d1%81%d1%82%20%d1%81%d1%82%d0%b0%d1%82%d1%82%d1%96-199-2-10-20230420.pdf | C88: Survey | D88: =Info!$B$17 -> 0 | E88: =Info!$B$19 -> 1 | F88: =Info!$B$25 -> 0.6 | G88: =Info!$B$32 -> 0 | H88: =Info!$B$37 -> 0 | I88: =Info!$B$40 -> 0 | J88: =Info!$B$42 -> 1 | L88: 1 | M88: Journal Article | N88: Herald of Advanced Information Technology | O88: 0.8 | P88: =(D88+E88+F88+G88+H88+I88+J88)/6 -> 0.43333333 | Q88: =(O88+P88)/2 -> 0.61666667 | R88: =IF(_xlfn.BITAND(P88>0.4999, Q88>0.4999)=1,1,0) -> 0
A89: Security Strengths and Weaknesses of Blockchain Smart Contract System: A Survey | B89: https://www.researchgate.net/profile/Malaw-Ndiaye/publication/360624196_Security_Strengths_and_Weaknesses_of_Blockchain_Smart_Contract_System_A_Survey/links/62824c3590841d5155d7dbb7/Security-Strengths-and-Weaknesses-of-Blockchain-Smart-Contract-System-A-Survey.pdf | C89: Survey | D89: =Info!$B$17 -> 0 | E89: =Info!$B$20 -> 0.6 | F89: =Info!$B$25 -> 0.6 | G89: =Info!$B$30 -> 0.6 | H89: =Info!$B$36 -> 0.3 | I89: =Info!$B$40 -> 0 | J89: =Info!$B$43 -> 0.5 | L89: 1 | M89: Journal Article | N89: World Academy of Science, Engineering and Technology International Journal of Information and Communication Engineering | O89: 0.5 | P89: =(D89+E89+F89+G89+H89+I89+J89)/6 -> 0.43333333 | Q89: =(O89+P89)/2 -> 0.46666667 | R89: =IF(_xlfn.BITAND(P89>0.4999, Q89>0.4999)=1,1,0) -> 0
A90: Investigating Security Vulnerabilities and Tools of Blockchain Smart Contract: A Review | B90: https://dl.acm.org/doi/abs/10.1145/3607947.3608069 | C90: Survey | D90: =Info!$B$17 -> 0 | E90: =Info!$B$20 -> 0.6 | F90: =Info!$B$25 -> 0.6 | G90: =Info!$B$31 -> 0.3 | H90: =Info!$B$37 -> 0 | I90: =Info!$B$40 -> 0 | J90: =Info!$B$42 -> 1 | L90: 1 | M90: Conference Proceeding or Workshop | N90: IC3-2023: Proceedings of the 2023 Fifteenth International Conference on Contemporary Computing | O90: 1 | P90: =(D90+E90+F90+G90+H90+I90+J90)/6 -> 0.41666667 | Q90: =(O90+P90)/2 -> 0.70833333 | R90: =IF(_xlfn.BITAND(P90>0.4999, Q90>0.4999)=1,1,0) -> 0
A91: A Survey on Smart Contract Vulnerabilities and Safeguards in Blockchain | B91: https://ijisae.org/index.php/IJISAE/article/view/2405 | C91: Survey | D91: =Info!$B$17 -> 0 | E91: =Info!$B$20 -> 0.6 | F91: =Info!$B$26 -> 0.3 | G91: =Info!$B$30 -> 0.6 | H91: =Info!$B$36 -> 0.3 | I91: =Info!$B$40 -> 0 | J91: =Info!$B$43 -> 0.5 | L91: 1 | M91: Journal Article | N91: International Journal of INTELLIGENT SYSTEMS AND APPLICATIONS IN ENGINEERING | O91: 0.5 | P91: =(D91+E91+F91+G91+H91+I91+J91)/6 -> 0.38333333 | Q91: =(O91+P91)/2 -> 0.44166667 | R91: =IF(_xlfn.BITAND(P91>0.4999, Q91>0.4999)=1,1,0) -> 0
A92: A Survey of Smart Contract Formal Specification and Verification | B92: https://dl.acm.org/doi/abs/10.1145/3464421 | C92: Survey | D92: =Info!$B$17 -> 0 | E92: =Info!$B$20 -> 0.6 | F92: =Info!$B$25 -> 0.6 | G92: =Info!$B$29 -> 1 | H92: =Info!$B$36 -> 0.3 | I92: =Info!$B$40 -> 0 | J92: =Info!$B$44 -> 0 | L92: 1 | M92: Journal Article | N92: ACM Computing Surveys | O92: 1 | P92: =(D92+E92+F92+G92+H92+I92+J92)/6 -> 0.41666667 | Q92: =(O92+P92)/2 -> 0.70833333 | R92: =IF(_xlfn.BITAND(P92>0.4999, Q92>0.4999)=1,1,0) -> 0
A93: A Survey of Verification, Validation and Testing Solutions for Smart Contracts | B93: https://ieeexplore.ieee.org/abstract/document/9657040?casa_token=sxjoBMYV0BoAAAAA:fbZVMqj7ERWlHa1l9k2ULcgTb0sZ0T9F4VWN2sW8DgFQgf6Om35GWgjT_oPlkZm9QCoVeDY | C93: Survey | D93: =Info!$B$17 -> 0 | E93: =Info!$B$20 -> 0.6 | F93: =Info!$B$26 -> 0.3 | G93: =Info!$B$30 -> 0.6 | H93: =Info!$B$36 -> 0.3 | I93: =Info!$B$40 -> 0 | J93: =Info!$B$44 -> 0 | L93: 1 | M93: Conference Proceeding or Workshop | N93: International Conference on Blockchain Computing and Applications (BCCA) | O93: 0.2 | P93: =(D93+E93+F93+G93+H93+I93+J93)/6 -> 0.3 | Q93: =(O93+P93)/2 -> 0.25 | R93: =IF(_xlfn.BITAND(P93>0.4999, Q93>0.4999)=1,1,0) -> 0
A94: Cybersecurity and Ethereum Security Vulnerabilities Analysis | B94: https://drpress.org/ojs/index.php/HSET/article/view/5498/5317 | C94: Survey | D94: =Info!$B$17 -> 0 | E94: =Info!$B$21 -> 0.3 | F94: =Info!$B$26 -> 0.3 | G94: =Info!$B$32 -> 0 | H94: =Info!$B$37 -> 0 | I94: =Info!$B$40 -> 0 | J94: =Info!$B$42 -> 1 | L94: 1 | M94: Conference Proceeding or Workshop | N94: highlights in science engineering and technology | O94: 0.2 | P94: =(D94+E94+F94+G94+H94+I94+J94)/6 -> 0.26666667 | Q94: =(O94+P94)/2 -> 0.23333333 | R94: =IF(_xlfn.BITAND(P94>0.4999, Q94>0.4999)=1,1,0) -> 0
A95: Definition and Detection of Defects in NFT Smart Contracts | B95: https://arxiv.org/abs/2305.15829 | C95: Survey | D95: =Info!$B$17 -> 0 | E95: =Info!$B$21 -> 0.3 | F95: =Info!$B$26 -> 0.3 | G95: =Info!$B$32 -> 0 | H95: =Info!$B$37 -> 0 | I95: =Info!$B$40 -> 0 | J95: =Info!$B$42 -> 1 | L95: 1 | M95: Conference Proceeding or Workshop | N95: Software Engineering | O95: 0.4 | P95: =(D95+E95+F95+G95+H95+I95+J95)/6 -> 0.26666667 | Q95: =(O95+P95)/2 -> 0.33333333 | R95: =IF(_xlfn.BITAND(P95>0.4999, Q95>0.4999)=1,1,0) -> 0
A96: OpenAI ChatGPT for Smart Contract Security Testing: Discussion and Future Directions | B96: https://papers.ssrn.com/sol3/papers.cfm?abstract_id=4412215 | C96: Survey | D96: =Info!$B$17 -> 0 | E96: =Info!$B$21 -> 0.3 | F96: =Info!$B$26 -> 0.3 | G96: =Info!$B$32 -> 0 | H96: =Info!$B$37 -> 0 | I96: =Info!$B$40 -> 0 | J96: =Info!$B$42 -> 1 | L96: 1 | M96: Journal Article | O96: 0.2 | P96: =(D96+E96+F96+G96+H96+I96+J96)/6 -> 0.26666667 | Q96: =(O96+P96)/2 -> 0.23333333 | R96: =IF(_xlfn.BITAND(P96>0.4999, Q96>0.4999)=1,1,0) -> 0
A97: Smart Contract Vulnerabilities: Vulnerable Does Not Imply Exploited | B97: https://www.usenix.org/conference/usenixsecurity21/presentation/perez | C97: Survey | D97: =Info!$B$17 -> 0 | E97: =Info!$B$20 -> 0.6 | F97: =Info!$B$26 -> 0.3 | G97: =Info!$B$31 -> 0.3 | H97: =Info!$B$36 -> 0.3 | I97: =Info!$B$40 -> 0 | J97: =Info!$B$44 -> 0 | L97: 1 | M97: Conference Proceeding or Workshop | N97: 30th USENIX Security Symposium | O97: 0.2 | P97: =(D97+E97+F97+G97+H97+I97+J97)/6 -> 0.25 | Q97: =(O97+P97)/2 -> 0.225 | R97: =IF(_xlfn.BITAND(P97>0.4999, Q97>0.4999)=1,1,0) -> 0
A98: An empirical study on the complexity, security and maintainability of Ethereum-based decentralized applications (DApps) | B98: https://www.sciencedirect.com/science/article/pii/S2096720922000616 | C98: Survey | D98: =Info!$B$17 -> 0 | E98: =Info!$B$20 -> 0.6 | F98: =Info!$B$26 -> 0.3 | G98: =Info!$B$32 -> 0 | H98: =Info!$B$37 -> 0 | I98: =Info!$B$40 -> 0 | J98: =Info!$B$43 -> 0.5 | L98: 1 | M98: Journal Article | N98: Blockchain: Research and Applications | O98: 1 | P98: =(D98+E98+F98+G98+H98+I98+J98)/6 -> 0.23333333 | Q98: =(O98+P98)/2 -> 0.61666667 | R98: =IF(_xlfn.BITAND(P98>0.4999, Q98>0.4999)=1,1,0) -> 0
A99: Management of blockchain-based data provenance and addressing smart contract security issues | B99: https://unbscholar.lib.unb.ca/items/a16c685b-381d-4f5c-89f4-008b338dd114 | C99: Survey | D99: =Info!$B$17 -> 0 | E99: =Info!$B$21 -> 0.3 | F99: =Info!$B$27 -> 0 | G99: =Info!$B$32 -> 0 | H99: =Info!$B$37 -> 0 | I99: =Info!$B$40 -> 0 | J99: =Info!$B$42 -> 1 | L99: 1 | M99: Thesis or Seminar Paper | N99: PhD Thesis | O99: 0.2 | P99: =(D99+E99+F99+G99+H99+I99+J99)/6 -> 0.21666667 | Q99: =(O99+P99)/2 -> 0.20833333 | R99: =IF(_xlfn.BITAND(P99>0.4999, Q99>0.4999)=1,1,0) -> 0
A100: Security Analysis Methods for Detection and Repair of DoS Vulnerabilities in Smart Contracts | B100: https://uwspace.uwaterloo.ca/handle/10012/16885 | C100: Survey | D100: =Info!$B$17 -> 0 | E100: =Info!$B$22 -> 0 | F100: =Info!$B$26 -> 0.3 | G100: =Info!$B$31 -> 0.3 | H100: =Info!$B$35 -> 0.6 | I100: =Info!$B$40 -> 0 | J100: =Info!$B$44 -> 0 | L100: 1 | M100: Conference Proceeding or Workshop | N100: Electrical and Computer Engineering | O100: 0.2 | P100: =(D100+E100+F100+G100+H100+I100+J100)/6 -> 0.2 | Q100: =(O100+P100)/2 -> 0.2 | R100: =IF(_xlfn.BITAND(P100>0.4999, Q100>0.4999)=1,1,0) -> 0
...

Sheet ACM_DL
A1: Title | B1: Link | C1: Pubblication Class | D1: Q1 | E1: Q2 | F1: Q3 | G1: Q4 | H1: Q5 | I1: Q6 | J1: Q7 | K1: Exc.Crit | L1: Inc.Crit | M1: Pubblication Venue | N1: Vanue Name | O1: IDQ | P1: CDQ | Q1: FDQ | R1: Selected
A2: A Solicitous Approach to Smart Contract Verification | B2: https://dl.acm.org/doi/10.1145/3564699 | C2: PS | D2: =Info!$B$50 -> 0.3 | E2: =Info!$B$53 -> 1 | L2: 2,3 | M2: Journal Article | N2: ACM Transactions on Privacy and Security | O2: 1 | P2: =(D2+E2)/2 -> 0.65 | Q2: =(O2+P2)/2 -> 0.825 | R2: =IF(_xlfn.BITAND(P2>0.4999, Q2>0.4999)=1,1,0) -> 1
A3: AChecker: Statically Detecting Smart Contract Access Control Vulnerabilities | B3: https://dl.acm.org/doi/10.1109/ICSE48619.2023.00087 | C3: PS | D3: =Info!$B$50 -> 0.3 | E3: =Info!$B$53 -> 1 | L3: 2,3 | M3: Conference Proceeding or Workshop | N3: ICSE '23: Proceedings of the 45th International Conference on Software Engineering | O3: 1 | P3: =(D3+E3)/2 -> 0.65 | Q3: =(O3+P3)/2 -> 0.825 | R3: =IF(_xlfn.BITAND(P3>0.4999, Q3>0.4999)=1,1,0) -> 1
A4: Cross-Modality Mutual Learning for Enhancing Smart Contract Vulnerability Detection on Bytecode | B4: https://dl.acm.org/doi/10.1145/3543507.3583367 | C4: PS | D4: =Info!$B$51 -> 0 | E4: =Info!$B$53 -> 1 | L4: 2 | M4: Conference Proceeding or Workshop | N4: WWW '23: Proceedings of the ACM Web Conference 2023 | O4: 1 | P4: =(D4+E4)/2 -> 0.5 | Q4: =(O4+P4)/2 -> 0.75 | R4: =IF(_xlfn.BITAND(P4>0.4999, Q4>0.4999)=1,1,0) -> 1
A5: Turn the Rudder: A Beacon of Reentrancy Detection for Smart Contracts on Ethereum | B5: https://dl.acm.org/doi/10.1109/ICSE48619.2023.00036 | C5: Survey | D5: =Info!$B$17 -> 0 | E5: =Info!$B$20 -> 0.6 | F5: =Info!$B$25 -> 0.6 | G5: =Info!$B$30 -> 0.6 | H5: =Info!$B$36 -> 0.3 | I5: =Info!$B$40 -> 0 | J5: =Info!$B$42 -> 1 | L5: 2 | M5: Conference Proceeding or Workshop | N5: ICSE '23: Proceedings of the 45th International Conference on Software Engineering | O5: 1 | P5: =(D5+E5+F5+G5+H5+I5+J5)/6 -> 0.51666667 | Q5: =(O5+P5)/2 -> 0.75833333 | R5: =IF(_xlfn.BITAND(P5>0.4999, Q5>0.4999)=1,1,0) -> 1
A6: Demystifying Exploitable Bugs in Smart Contracts | B6: https://dl.acm.org/doi/10.1109/ICSE48619.2023.00061 | C6: Survey | D6: =Info!$B$17 -> 0 | E6: =Info!$B$19 -> 1 | F6: =Info!$B$25 -> 0.6 | G6: =Info!$B$29 -> 1 | H6: =Info!$B$35 -> 0.6 | I6: =Info!$B$40 -> 0 | J6: =Info!$B$42 -> 1 | L6: 1 | M6: Conference Proceeding or Workshop | N6: International Conference on Software Engineering | O6: 1 | P6: =(D6+E6+F6+G6+H6+I6+J6)/6 -> 0.7 | Q6: =(O6+P6)/2 -> 0.85 | R6: =IF(_xlfn.BITAND(P6>0.4999, Q6>0.4999)=1,1,0) -> 1
A7: Dynamic Vulnerability Detection on Smart Contracts Using Machine Learning | C7: PS | D7: =Info!$B$48 -> 1 | E7: =Info!$B$52 -> 0 | L7: 2 | M7: Conference Proceeding or Workshop | N7: EASE | O7: 1 | P7: =(D7+E7)/2 -> 0.5 | Q7: =(O7+P7)/2 -> 0.75 | R7: =IF(_xlfn.BITAND(P7>0.4999, Q7>0.4999)=1,1,0) -> 1
A8: Effectively Generating Vulnerable Transaction Sequences in Smart Contracts with Reinforcement Learning-guided Fuzzing | B8: https://dl.acm.org/doi/10.1145/3551349.3560429 | C8: PS | D8: 1 | E8: 1 | L8: 2,3 | M8: Conference Proceeding or Workshop | N8: ASE | O8: 1 | P8: =(D8+E8)/2 -> 1 | Q8: =(O8+P8)/2 -> 1 | R8: =IF(_xlfn.BITAND(P8>0.4999, Q8>0.4999)=1,1,0) -> 1
A9: Elysium: Context-Aware Bytecode-Level Patching to Automatically Heal Vulnerable Smart Contracts | B9: https://dl.acm.org/doi/10.1145/3545948.3545975 | C9: PS | D9: =Info!$B$48 -> 1 | E9: =Info!$B$53 -> 1 | L9: 2,3 | M9: Conference Proceeding or Workshop | N9: RAID '22: Proceedings of the 25th International Symposium on Research in Attacks, Intrusions and Defenses | O9: 0.8 | P9: =(D9+E9)/2 -> 1 | Q9: =(O9+P9)/2 -> 0.9 | R9: =IF(_xlfn.BITAND(P9>0.4999, Q9>0.4999)=1,1,0) -> 1
A10: eTainter: detecting gas-related vulnerabilities in smart contracts | B10: https://dl.acm.org/doi/10.1145/3533767.3534378 | C10: PS | D10: =Info!$B$48 -> 1 | E10: =Info!$B$53 -> 1 | L10: 2 | M10: Conference Proceeding or Workshop | N10: ISSTA 2022: Proceedings of the 31st ACM SIGSOFT International Symposium on Software Testing and Analysis | O10: 1 | P10: =(D10+E10)/2 -> 1 | Q10: =(O10+P10)/2 -> 1 | R10: =IF(_xlfn.BITAND(P10>0.4999, Q10>0.4999)=1,1,0) -> 1
A11: Eth2Vec: Learning Contract-Wide Code Representations for Vulnerability Detection on Ethereum Smart Contracts | C11: PS | D11: =Info!$B$48 -> 1 | E11: =Info!$B$53 -> 1 | L11: 2 | M11: Conference Proceeding or Workshop | N11: International Symposium on Blockchain and Secure Critical Infrastructure | O11: 0.4 | P11: =(D11+E11)/2 -> 1 | Q11: =(O11+P11)/2 -> 0.7 | R11: =IF(_xlfn.BITAND(P11>0.4999, Q11>0.4999)=1,1,0) -> 1
A12: Park: accelerating smart contract vulnerability detection via parallel-fork symbolic execution | B12: https://dl.acm.org/doi/10.1145/3533767.3534395 | C12: PS | D12: =Info!$B$51 -> 0 | E12: =Info!$B$53 -> 1 | L12: 2 | M12: Conference Proceeding or Workshop | N12: ISSTA 2022: Proceedings of the 31st ACM SIGSOFT International Symposium on Software Testing and Analysis | O12: 1 | P12: =(D12+E12)/2 -> 0.5 | Q12: =(O12+P12)/2 -> 0.75 | R12: =IF(_xlfn.BITAND(P12>0.4999, Q12>0.4999)=1,1,0) -> 1
A13: Finding permission bugs in smart contracts with role mining | B13: https://dl.acm.org/doi/10.1145/3533767.3534372 | C13: PS | D13: 1 | E13: 1 | L13: 2,3 | M13: Conference Proceeding or Workshop | N13: ISSTA 2022 | O13: 1 | P13: =(D13+E13)/2 -> 1 | Q13: =(O13+P13)/2 -> 1 | R13: =IF(_xlfn.BITAND(P13>0.4999, Q13>0.4999)=1,1,0) -> 1
A14: Siguard: Detecting Signature-Related Vulnerabilities in Smart Contracts | B14: https://dl.acm.org/doi/10.1109/ICSE-Companion58688.2023.00019 | C14: PS | D14: =Info!$B$51 -> 0 | E14: =Info!$B$53 -> 1 | L14: 2,3 | M14: Conference Proceeding or Workshop | N14: ICSE '23: Proceedings of the 45th International Conference on Software Engineering: Companion Proceedings | O14: 1 | P14: =(D14+E14)/2 -> 0.5 | Q14: =(O14+P14)/2 -> 0.75 | R14: =IF(_xlfn.BITAND(P14>0.4999, Q14>0.4999)=1,1,0) -> 1
A15: Gas estimation and optimization for smart contracts on ethereum | B15: https://dl.acm.org/doi/10.1109/ASE51524.2021.9678932 | C15: PS | D15: 1 | E15: 1 | L15: 3 | M15: Conference Proceeding or Workshop | N15: ASE21 | O15: 1 | P15: =(D15+E15)/2 -> 1 | Q15: =(O15+P15)/2 -> 1 | R15: =IF(_xlfn.BITAND(P15>0.4999, Q15>0.4999)=1,1,0) -> 1
A16: ESBMC-solidity: an SMT-based model checker for solidity smart contracts | B16: https://dl.acm.org/doi/10.1145/3510454.3516855 | C16: PS | D16: 1 | E16: 1 | M16: Conference Proceeding or Workshop | N16: ICSE22 | O16: 1 | P16: =(D16+E16)/2 -> 1 | Q16: =(O16+P16)/2 -> 1 | R16: =IF(_xlfn.BITAND(P16>0.4999, Q16>0.4999)=1,1,0) -> 1
A17: SmartState: Detecting State-Reverting Vulnerabilities in Smart Contracts via Fine-Grained State-Dependency Analysis | B17: https://dl.acm.org/doi/10.1145/3597926.3598111 | C17: PS | D17: =Info!$B$51 -> 0 | E17: =Info!$B$53 -> 1 | L17: 2,3 | M17: Conference Proceeding or Workshop | N17: ISSTA 2023: Proceedings of the 32nd ACM SIGSOFT International Symposium on Software Testing and Analysis | O17: 1 | P17: =(D17+E17)/2 -> 0.5 | Q17: =(O17+P17)/2 -> 0.75 | R17: =IF(_xlfn.BITAND(P17>0.4999, Q17>0.4999)=1,1,0) -> 1
A18: SynTest-solidity: automated test case generation and fuzzing for smart contracts | B18: https://dl.acm.org/doi/10.1145/3510454.3516869 | C18: PS | D18: =Info!$B$49 -> 0.6 | E18: =Info!$B$53 -> 1 | L18: 2.3 | M18: Conference Proceeding or Workshop | N18: ICSE '22: Proceedings of the ACM/IEEE 44th International Conference on Software Engineering: Companion Proceedings | O18: 1 | P18: =(D18+E18)/2 -> 0.8 | Q18: =(O18+P18)/2 -> 0.9 | R18: =IF(_xlfn.BITAND(P18>0.4999, Q18>0.4999)=1,1,0) -> 1
A19: Beyond “Protected” and “Private”: An Empirical Security Analysis of Custom Function Modifiers in Smart Contracts | B19: https://dl.acm.org/doi/abs/10.1145/3597926.3598125 | D19: 1 | E19: 1 | L19: 2.3 | M19: Conference Proceeding or Workshop | N19: ISSTA23 | O19: 1 | P19: =(D19+E19)/2 -> 1 | Q19: =(O19+P19)/2 -> 1 | R19: =IF(_xlfn.BITAND(P19>0.4999, Q19>0.4999)=1,1,0) -> 1
A20: When ChatGPT Meets Smart Contract Vulnerability Detection: How Far Are We? | B20: https://doi.org/10.1145/3702973 | C20: PS | D20: 1 | E20: 0 | L20: 3 | M20: Journal Article | N20: TOSEM24 | O20: 1 | P20: =(D20+E20)/2 -> 0.5 | Q20: =(O20+P20)/2 -> 0.75 | R20: =IF(_xlfn.BITAND(P20>0.4999, Q20>0.4999)=1,1,0) -> 1
A21: Improving Smart Contract Security with Contrastive Learning-based Vulnerability Detection | B21: https://doi.org/10.1145/3597503.3639173 | C21: PS | D21: 1 | E21: 1 | L21: 3 | M21: Conference Proceeding or Workshop | N21: ICSE24 | O21: 1 | P21: =(D21+E21)/2 -> 1 | Q21: =(O21+P21)/2 -> 1 | R21: =IF(_xlfn.BITAND(P21>0.4999, Q21>0.4999)=1,1,0) -> 1
A22: COBRA: Interaction-Aware Bytecode-Level Vulnerability Detector for Smart Contracts | B22: https://doi.org/10.1145/3691620.3695601 | C22: PS | D22: 0 | E22: 1 | L22: 3 | M22: Conference Proceeding or Workshop | N22: ICSE24 | O22: 1 | P22: =(D22+E22)/2 -> 0.5 | Q22: =(O22+P22)/2 -> 0.75 | R22: =IF(_xlfn.BITAND(P22>0.4999, Q22>0.4999)=1,1,0) -> 1
A23: ContractTinker: LLM-Empowered Vulnerability Repair for Real-World Smart Contracts | B23: https://doi.org/10.1145/3691620.3695349 | C23: PS | D23: 0 | E23: 1 | L23: 3 | M23: Conference Proceeding or Workshop | N23: ICSE24 | O23: 1 | P23: =(D23+E23)/2 -> 0.5 | Q23: =(O23+P23)/2 -> 0.75 | R23: =IF(_xlfn.BITAND(P23>0.4999, Q23>0.4999)=1,1,0) -> 1
A24: AdvSCanner: Generating Adversarial Smart Contracts to Exploit Reentrancy Vulnerabilities Using LLM and Static Analysis | B24: https://doi.org/10.1145/3691620.3695482 | C24: PS | D24: 0 | E24: 1 | L24: 3 | M24: Conference Proceeding or Workshop | N24: ICSE24 | O24: 1 | P24: =(D24+E24)/2 -> 0.5 | Q24: =(O24+P24)/2 -> 0.75 | R24: =IF(_xlfn.BITAND(P24>0.4999, Q24>0.4999)=1,1,0) -> 1
A25: Verifying Declarative Smart Contracts | B25: https://doi.org/10.1145/3597503.3639203 | C25: PS | D25: 0 | E25: 1 | M25: Conference Proceeding or Workshop | N25: ICSE24 | O25: 1 | P25: 0.5 | Q25: 0.75 | R25: =IF(_xlfn.BITAND(P25>0.4999, Q25>0.4999)=1,1,0) -> 1
A26: GPTScan: Detecting Logic Vulnerabilities in Smart Contracts by Combining GPT with Program Analysis | B26: https://doi.org/10.1145/3597503.3639117 | C26: PS | D26: 1 | E26: 1 | L26: 3 | M26: Conference Proceeding or Workshop | N26: ICSE24 | O26: 1 | P26: =(D26+E26)/2 -> 1 | Q26: =(O26+P26)/2 -> 1 | R26: =IF(_xlfn.BITAND(P26>0.4999, Q26>0.4999)=1,1,0) -> 1
A27: Oracle-Guided Vulnerability Diversity and Exploit Synthesis of Smart Contracts Using LLMs | B27: https://doi.org/10.1145/3691620.3695292 | C27: PS | D27: 0 | E27: 1 | L27: 3 | M27: Conference Proceeding or Workshop | N27: ICSE24 | O27: 1 | P27: =(D27+E27)/2 -> 0.5 | Q27: =(O27+P27)/2 -> 0.75 | R27: =IF(_xlfn.BITAND(P27>0.4999, Q27>0.4999)=1,1,0) -> 1
A28: FunFuzz: A Function-Oriented Fuzzer for Smart Contract Vulnerability Detection with High Effectiveness and Efficiency | B28: https://doi.org/10.1145/3674725 | C28: PS | D28: 0 | E28: 1 | L28: 3 | M28: Journal Article | N28: TOSEM24 | O28: 1 | P28: =(D28+E28)/2 -> 0.5 | Q28: =(O28+P28)/2 -> 0.75 | R28: =IF(_xlfn.BITAND(P28>0.4999, Q28>0.4999)=1,1,0) -> 1
A29: Skyeye: Detecting Imminent Attacks via Analyzing Adversarial Smart Contracts | B29: https://doi.org/10.1145/3691620.3695526 | C29: PS | D29: 0 | E29: 1 | L29: 3 | M29: Conference Proceeding or Workshop | N29: ICSE24 | O29: 1 | P29: 0.5 | Q29: 0.75 | R29: =IF(_xlfn.BITAND(P29>0.4999, Q29>0.4999)=1,1,0) -> 1
A30: Demystifying Invariant Effectiveness for Securing Smart Contracts | B30: https://doi.org/10.1145/3660786 | C30: PS | D30: 0.3 | E30: 1 | L30: 3 | M30: Conference Proceeding or Workshop | N30: ICSE24 | O30: 1 | P30: =(D30+E30)/2 -> 0.65 | Q30: =(O30+P30)/2 -> 0.825 | R30: =IF(_xlfn.BITAND(P30>0.4999, Q30>0.4999)=1,1,0) -> 1
A31: Identifying Smart Contract Security Issues in Code Snippets from Stack Overflow | B31: https://doi.org/10.1145/3650212.3680353 | C31: PS | D31: 0.3 | E31: 1 | L31: 3 | M31: Conference Proceeding or Workshop | N31: ICSE24 | O31: 1 | P31: =(D31+E31)/2 -> 0.65 | Q31: =(O31+P31)/2 -> 0.825 | R31: =IF(_xlfn.BITAND(P31>0.4999, Q31>0.4999)=1,1,0) -> 1
A32: HighGuard: Cross-Chain Business Logic Monitoring of Smart Contracts | B32: https://doi.org/10.1145/3691620.3695356 | C32: PS | E32: 1 | M32: Conference Proceeding or Workshop | N32: Proceedings of the 39th IEEE/ACM International Conference on Automated Software Engineering | O32: 1 | P32: =(D32+E32)/2 -> 0.5 | Q32: =(O32+P32)/2 -> 0.75 | R32: =IF(_xlfn.BITAND(P32>0.4999, Q32>0.4999)=1,1,0) -> 1
A33: Static Application Security Testing (SAST) Tools for Smart Contracts: How Far Are We? | B33: https://doi.org/10.1145/3660772 | C33: Survey | D33: 0 | E33: 1 | F33: 1 | G33: 0 | H33: 0 | I33: 1 | J33: 1 | L33: 2.3 | M33: Conference Proceeding or Workshop | N33: ICSE24 | O33: 1 | P33: =(D33+E33+F33+G33+H33+I33+J33)/6 -> 0.66666667 | Q33: =(O33+P33)/2 -> 0.83333333 | R33: =IF(_xlfn.BITAND(P33>0.4999, Q33>0.4999)=1,1,0) -> 1
A34: Safeguarding DeFi Smart Contracts against Oracle Deviations | B34: https://doi.org/10.1145/3597503.3639225 | C34: PS | D34: 0.6 | E34: 1 | M34: Conference Proceeding or Workshop | N34: ICSE24 | O34: 1 | P34: =(D34+E34)/2 -> 0.8 | Q34: =(O34+P34)/2 -> 0.9 | R34: =IF(_xlfn.BITAND(P34>0.4999, Q34>0.4999)=1,1,0) -> 1
A35: Midas: Mining Profitable Exploits in On-Chain Smart Contracts via Feedback-Driven Fuzzing and Differential Analysis | B35: https://doi.org/10.1145/3650212.3680321 | C35: PS | E35: 1 | M35: Conference Proceeding or Workshop | N35: Proceedings of the 33rd ACM SIGSOFT International Symposium on Software Testing and Analysis | O35: 1 | P35: =(D35+E35+F35+G35+H35+I35+J35)/2 -> 0.5 | Q35: =(O35+P35)/2 -> 0.75 | R35: =IF(_xlfn.BITAND(P35>0.4999, Q35>0.4999)=1,1,0) -> 1
A36: SmartBugs 2.0: An Execution Framework for Weakness Detection in Ethereum Smart Contracts | B36: https://doi.org/10.1109/ASE56229.2023.00060 | C36: PS | E36: 1 | M36: Conference Proceeding or Workshop | N36: Proceedings of the 38th IEEE/ACM International Conference on Automated Software Engineering | O36: 1 | P36: =(D36+E36+F36+G36+H36+I36+J36)/2 -> 0.5 | Q36: =(O36+P36)/2 -> 0.75 | R36: =IF(_xlfn.BITAND(P36>0.4999, Q36>0.4999)=1,1,0) -> 1
A37: OpenTracer: A Dynamic Transaction Trace Analyzer for Smart Contract Invariant Generation and Beyond | B37: https://doi.org/10.1145/3691620.3695361 | C37: PS | D37: 0 | E37: 1 | L37: 3 | M37: Conference Proceeding or Workshop | N37: ICSE24 | O37: 1 | P37: =(D37+E37)/2 -> 0.5 | Q37: =(O37+P37)/2 -> 0.75 | R37: =IF(_xlfn.BITAND(P37>0.4999, Q37>0.4999)=1,1,0) -> 1
A38: FunRedisp: A Function Redispatch Tool to Reduce Invocation Gas Fees in Solidity Smart Contracts | B38: https://doi.org/10.1145/3650212.3685312 | C38: PS | D38: 0 | E38: 1 | L38: 3 | M38: Conference Proceeding or Workshop | N38: ICSE24 | O38: 1 | P38: =(D38+E38)/2 -> 0.5 | Q38: =(O38+P38)/2 -> 0.75 | R38: =IF(_xlfn.BITAND(P38>0.4999, Q38>0.4999)=1,1,0) -> 1
A39: FunRedisp: Reordering Function Dispatch in Smart Contract to Reduce Invocation Gas Fees | B39: https://doi.org/10.1145/3650212.3652146 | C39: PS | D39: 0 | E39: 1 | L39: 3 | M39: Conference Proceeding or Workshop | N39: ICSE24 | O39: 1 | P39: =(D39+E39)/2 -> 0.5 | Q39: =(O39+P39)/2 -> 0.75 | R39: =IF(_xlfn.BITAND(P39>0.4999, Q39>0.4999)=1,1,0) -> 1
A40: Smart Contract Code Repair Recommendation based on Reinforcement Learning and Multi-metric Optimization | B40: https://doi.org/10.1145/3637229 | C40: PS | D40: 0.6 | E40: 1 | L40: 3 | M40: Journal Article | N40: TOSEM24 | O40: 1 | P40: =(D40+E40)/2 -> 0.8 | Q40: =(O40+P40)/2 -> 0.9 | R40: =IF(_xlfn.BITAND(P40>0.4999, Q40>0.4999)=1,1,0) -> 1
A41: LENT-SSE: Leveraging Executed and Near Transactions for Speculative Symbolic Execution of Smart Contracts | B41: https://doi.org/10.1145/3650212.3680303 | C41: PS | D41: 0 | E41: 1 | L41: 3 | M41: Conference Proceeding or Workshop | N41: ISSTA24 | O41: 1 | P41: =(D41+E41)/2 -> 0.5 | Q41: =(O41+P41)/2 -> 0.75 | R41: =IF(_xlfn.BITAND(P41>0.4999, Q41>0.4999)=1,1,0) -> 1
A42: Are We There Yet? Unraveling the State-of-the-Art Smart Contract Fuzzers | B42: https://doi.org/10.1145/3597503.3639152 | C42: Survey | D42: 0 | E42: =Info!$B$20 -> 0.6 | F42: =Info!$B$25 -> 0.6 | G42: =Info!$B$30 -> 0.6 | H42: 1 | I42: 1 | J42: 1 | L42: 2 | M42: Conference Proceeding or Workshop | N42: ICSE24 | O42: 1 | P42: =(D42+E42+F42+G42+H42+I42+J42)/6 -> 0.8 | Q42: =(O42+P42)/2 -> 0.9 | R42: =IF(_xlfn.BITAND(P42>0.4999, Q42>0.4999)=1,1,0) -> 1
A43: Revealing Hidden Threats: An Empirical Study of Library Misuse in Smart Contracts | B43: https://doi.org/10.1145/3597503.3623335 | C43: Survey | D43: =Info!$B$17 -> 0 | E43: =Info!$B$20 -> 0.6 | F43: =Info!$B$25 -> 0.6 | G43: =Info!$B$27 -> 0 | H43: 0 | I43: 1 | J43: =Info!$B$42 -> 1 | L43: 2 | M43: Conference Proceeding or Workshop | N43: ICSE24 | O43: 1 | P43: =(D43+E43+F43+G43+H43+I43+J43)/6 -> 0.53333333 | Q43: =(O43+P43)/2 -> 0.76666667 | R43: =IF(_xlfn.BITAND(P43>0.4999, Q43>0.4999)=1,1,0) -> 1
A44: Modelling a Blockchain for Smart Contract Verification using DeepSEA | B44: https://dl.acm.org/doi/10.1145/3563822.3568011 | C44: PS | D44: =Info!$B$51 -> 0 | E44: =Info!$B$52 -> 0 | L44: 2,3 | M44: Conference Proceeding or Workshop | N44: FTSCS 2022: Proceedings of the 8th ACM SIGPLAN International Workshop on Formal Techniques for Safety-Critical Systems | O44: 0.5 | P44: =(D44+E44)/2 -> 0 | Q44: =(O44+P44)/2 -> 0.25 | R44: =IF(_xlfn.BITAND(P44>0.4999, Q44>0.4999)=1,1,0) -> 0
A45: Predicate abstractions for smart contract validation | B45: https://dl.acm.org/doi/10.1145/3550355.3552462 | C45: PS | D45: =Info!$B$51 -> 0 | E45: =Info!$B$52 -> 0 | L45: 3 | M45: Conference Proceeding or Workshop | N45: MODELS '22: Proceedings of the 25th International Conference on Model Driven Engineering Languages and Systems | O45: 0.2 | P45: =(D45+E45)/2 -> 0 | Q45: =(O45+P45)/2 -> 0.1 | R45: =IF(_xlfn.BITAND(P45>0.4999, Q45>0.4999)=1,1,0) -> 0
A46: An Analysis of Important Factors Affecting the Success of Blockchain Smart Contract Security Vulnerability Scanning Tools | B46: https://dl.acm.org/doi/10.1145/3594556.3594615 | C46: Survey | D46: =Info!$B$17 -> 0 | E46: =Info!$B$20 -> 0.6 | F46: =Info!$B$26 -> 0.3 | G46: =Info!$B$30 -> 0.6 | H46: =Info!$B$34 -> 1 | I46: =Info!$B$40 -> 0 | J46: =Info!$B$42 -> 1 | L46: 2 | M46: Conference Proceeding or Workshop | N46: BSCI '23: Proceedings of the 5th ACM International Symposium on Blockchain and Secure Critical Infrastructure | O46: 0.2 | P46: =(D46+E46+F46+G46+H46+I46+J46)/6 -> 0.58333333 | Q46: =(O46+P46)/2 -> 0.39166667 | R46: =IF(_xlfn.BITAND(P46>0.4999, Q46>0.4999)=1,1,0) -> 0
A47: Testing Smart Contracts: Which Technique Performs Best? | B47: https://dl.acm.org/doi/10.1145/3475716.3475779 | C47: Survey | D47: =Info!$B$17 -> 0 | E47: =Info!$B$21 -> 0.3 | F47: =Info!$B$27 -> 0 | G47: =Info!$B$30 -> 0.6 | H47: =Info!$B$36 -> 0.3 | I47: =Info!$B$40 -> 0 | J47: =Info!$B$44 -> 0 | L47: 2 | M47: Conference Proceeding or Workshop | N47: ESEM '21: Proceedings of the 15th ACM / IEEE International Symposium on Empirical Software Engineering and Measurement | O47: 1 | P47: =(D47+E47+F47+G47+H47+I47+J47)/6 -> 0.2 | Q47: =(O47+P47)/2 -> 0.6 | R47: =IF(_xlfn.BITAND(P47>0.4999, Q47>0.4999)=1,1,0) -> 0
A48: Smart contract vulnerability detection based on variant LSTM | B48: https://dl.acm.org/doi/10.1145/3588340.3588369 | C48: Survey | D48: =Info!$B$17 -> 0 | E48: =Info!$B$22 -> 0 | F48: =Info!$B$27 -> 0 | G48: =Info!$B$32 -> 0 | H48: =Info!$B$37 -> 0 | I48: =Info!$B$40 -> 0 | J48: =Info!$B$43 -> 0.5 | L48: 2 | M48: Conference Proceeding or Workshop | N48: ICBICC '22: Proceedings of the 2022 International Conference on Big Data, IoT, and Cloud Computing | O48: 0.2 | P48: =(D48+E48+F48+G48+H48+I48+J48)/6 -> 0.083333333 | Q48: =(O48+P48)/2 -> 0.14166667 | R48: =IF(_xlfn.BITAND(P48>0.4999, Q48>0.4999)=1,1,0) -> 0
A49: Vulnerable Smart Contract Detection by Means of Model Checking | B49: https://dl.acm.org/doi/10.1145/3494106.3528672 | C49: PS | D49: =Info!$B$50 -> 0.3 | E49: =Info!$B$52 -> 0 | L49: 2 | M49: Conference Proceeding or Workshop | N49: BSCI '22: Proceedings of the Fourth ACM International Symposium on Blockchain and Secure Critical Infrastructure | O49: 0.2 | P49: =(D49+E49)/2 -> 0.15 | Q49: =(O49+P49)/2 -> 0.175 | R49: =IF(_xlfn.BITAND(P49>0.4999, Q49>0.4999)=1,1,0) -> 0
A50: Smart Contract Symbol Execution Vulnerability Detection Method Based on CFG Path Pruning | B50: https://dl.acm.org/doi/10.1145/3594556.3594618 | C50: PS | D50: =Info!$B$51 -> 0 | E50: =Info!$B$52 -> 0 | L50: 2 | M50: Conference Proceeding or Workshop | N50: BSCI '23: Proceedings of the 5th ACM International Symposium on Blockchain and Secure Critical Infrastructure | O50: 0.2 | P50: =(D50+E50)/2 -> 0 | Q50: =(O50+P50)/2 -> 0.1 | R50: =IF(_xlfn.BITAND(P50>0.4999, Q50>0.4999)=1,1,0) -> 0
A51: Cross-contract static analysis for detecting practical reentrancy vulnerabilities in smart contracts | B51: https://dl.acm.org/doi/10.1145/3324884.3416553 | C51: PS | D51: =Info!$B$51 -> 0 | E51: =Info!$B$52 -> 0 | L51: 2 | M51: Conference Proceeding or Workshop | N51: ASE '20: Proceedings of the 35th IEEE/ACM International Conference on Automated Software Engineering | O51: 0.2 | P51: =(D51+E51)/2 -> 0 | Q51: =(O51+P51)/2 -> 0.1 | R51: =IF(_xlfn.BITAND(P51>0.4999, Q51>0.4999)=1,1,0) -> 0
A52: SmartFix: Fixing Vulnerable Smart Contracts by Accelerating Generate-and-Verify Repair using Statistical Models | B52: https://dl.acm.org/doi/10.1145/3611643.3616341 | C52: PS | D52: =Info!$B$51 -> 0 | E52: =Info!$B$52 -> 0 | L52: 2 | M52: Conference Proceeding or Workshop | N52: ESEC/FSE 2023: Proceedings of the 31st ACM Joint European Software Engineering Conference and Symposium on the Foundations of Software Engineering | O52: 1 | P52: =(D52+E52)/2 -> 0 | Q52: =(O52+P52)/2 -> 0.5 | R52: =IF(_xlfn.BITAND(P52>0.4999, Q52>0.4999)=1,1,0) -> 0
A53: Uncovering Smart Contract VM Bugs Via Differential Fuzzing | B53: https://dl.acm.org/doi/10.1145/3503921.3503923 | C53: PS | D53: =Info!$B$50 -> 0.3 | E53: =Info!$B$53 -> 1 | L53: 2 | M53: Conference Proceeding or Workshop | N53: ROOTS'21: Reversing and Offensive-oriented Trends Symposium | O53: 0.2 | P53: =(D53+E53)/2 -> 0.65 | Q53: =(O53+P53)/2 -> 0.425 | R53: =IF(_xlfn.BITAND(P53>0.4999, Q53>0.4999)=1,1,0) -> 0
A54: EOSFuzzer: Fuzzing EOSIO Smart Contracts for Vulnerability Detection | B54: https://dl.acm.org/doi/10.1145/3457913.3457920 | C54: PS | K54: 1 | M54: Conference Proceeding or Workshop | N54: Internetware '20: Proceedings of the 12th Asia-Pacific Symposium on Internetware | O54: 0.2 | P54: =(D54+E54)/2 -> 0 | Q54: =(O54+P54)/2 -> 0.1 | R54: =IF(_xlfn.BITAND(P54>0.4999, Q54>0.4999)=1,1,0) -> 0
A55: Investigating Security Vulnerabilities and Tools of Blockchain Smart Contract: A Review | B55: https://dl.acm.org/doi/10.1145/3607947.3608069 | P55: =(D55+E55+F55+G55+H55+I55+J55)/6 -> 0 | Q55: =(O55+P55)/2 -> 0 | R55: =IF(_xlfn.BITAND(P55>0.4999, Q55>0.4999)=1,1,0) -> 0
A56: Towards Effective Static Analysis Approaches for Security Vulnerabilities in Smart Contracts | B56: https://dl.acm.org/doi/10.1145/3551349.3559567 | C56: Survey | D56: =Info!$B$17 -> 0 | E56: =Info!$B$20 -> 0.6 | F56: =Info!$B$26 -> 0.3 | G56: =Info!$B$32 -> 0 | H56: =Info!$B$37 -> 0 | I56: =Info!$B$40 -> 0 | J56: =Info!$B$43 -> 0.5 | L56: 1 | M56: Conference Proceeding or Workshop | N56: ASE '22: Proceedings of the 37th IEEE/ACM International Conference on Automated Software Engineering | O56: 1 | P56: =(D56+E56+F56+G56+H56+I56+J56)/6 -> 0.23333333 | Q56: =(O56+P56)/2 -> 0.61666667 | R56: =IF(_xlfn.BITAND(P56>0.4999, Q56>0.4999)=1,1,0) -> 0
A57: Research on Blockchain Smart Contracts Vulnerability and A Code Audit Tool based on Matching Rules | B57: https://dl.acm.org/doi/10.1145/3444370.3444617 | C57: Survey | D57: =Info!$B$17 -> 0 | E57: =Info!$B$21 -> 0.3 | F57: =Info!$B$26 -> 0.3 | G57: =Info!$B$32 -> 0 | H57: =Info!$B$37 -> 0 | I57: =Info!$B$40 -> 0 | J57: =Info!$B$44 -> 0 | L57: 1 | M57: Conference Proceeding or Workshop | N57: CIAT 2020: Proceedings of the 2020 International Conference on Cyberspace Innovation of Advanced Technologies | O57: 0.2 | P57: =(D57+E57+F57+G57+H57+I57+J57)/6 -> 0.1 | Q57: =(O57+P57)/2 -> 0.15 | R57: =IF(_xlfn.BITAND(P57>0.4999, Q57>0.4999)=1,1,0) -> 0
A58: Model checking of vulnerabilities in smart contracts: a solidity-to-CPN approach | B58: https://dl.acm.org/doi/10.1145/3477314.3507309 | C58: PS | D58: =Info!$B$50 -> 0.3 | E58: =Info!$B$52 -> 0 | L58: 1 | M58: Conference Proceeding or Workshop | N58: SAC '22: Proceedings of the 37th ACM/SIGAPP Symposium on Applied Computing | O58: 0.8 | P58: =(D58+E58)/2 -> 0.15 | Q58: =(O58+P58)/2 -> 0.475 | R58: =IF(_xlfn.BITAND(P58>0.4999, Q58>0.4999)=1,1,0) -> 0
A59: Smart Contracts Vulnerability Classification through Deep Learning | B59: https://dl.acm.org/doi/10.1145/3560905.3568175 | C59: PS | D59: =Info!$B$51 -> 0 | E59: =Info!$B$52 -> 0 | L59: 1 | M59: Conference Proceeding or Workshop | N59: SenSys '22: Proceedings of the 20th ACM Conference on Embedded Networked Sensor Systems | O59: 1 | P59: =(D59+E59)/2 -> 0 | Q59: =(O59+P59)/2 -> 0.5 | R59: =IF(_xlfn.BITAND(P59>0.4999, Q59>0.4999)=1,1,0) -> 0
A60: Poster: A Privacy-Preserving Smart Contract Vulnerability Detection Framework for Permissioned Blockchain | B60: https://dl.acm.org/doi/10.1145/3576915.3624366 | C60: PS | K60: 1 | M60: Conference Proceeding or Workshop | N60: CCS '23: Proceedings of the 2023 ACM SIGSAC Conference on Computer and Communications Security | O60: 1 | P60: =(D60+E60)/2 -> 0 | Q60: =(O60+P60)/2 -> 0.5 | R60: =IF(_xlfn.BITAND(P60>0.4999, Q60>0.4999)=1,1,0) -> 0
A61: WASAI: uncovering vulnerabilities in Wasm smart contracts | B61: https://dl.acm.org/doi/10.1145/3533767.3534218 | C61: PS | K61: 1 | M61: Conference Proceeding or Workshop | N61: ISSTA 2022: Proceedings of the 31st ACM SIGSOFT International Symposium on Software Testing and Analysis | O61: 1 | P61: =(D61+E61)/2 -> 0 | Q61: =(O61+P61)/2 -> 0.5 | R61: =IF(_xlfn.BITAND(P61>0.4999, Q61>0.4999)=1,1,0) -> 0
A62: SmartMark: Software Watermarking Scheme for Smart Contracts | B62: https://dl.acm.org/doi/10.1109/ICSE48619.2023.00035 | D62: =Info!$B$17 -> 0 | E62: =Info!$B$20 -> 0.6 | F62: =Info!$B$26 -> 0.3 | G62: =Info!$B$31 -> 0.3 | H62: =Info!$B$37 -> 0 | I62: =Info!$B$40 -> 0 | J62: =Info!$B$42 -> 1 | P62: =(D62+E62+F62+G62+H62+I62+J62)/7 -> 0.31428571 | Q62: =(O62+P62)/2 -> 0.15714286 | R62: =IF(_xlfn.BITAND(P62>0.4999, Q62>0.4999)=1,1,0) -> 0
A63: Smart Contract based Skill Verification System for Recruitment | B63: https://dl.acm.org/doi/10.1145/3607947.3607973 | D63: =Info!$B$17 -> 0 | E63: =Info!$B$21 -> 0.3 | F63: =Info!$B$26 -> 0.3 | G63: =Info!$B$32 -> 0 | H63: =Info!$B$37 -> 0 | I63: =Info!$B$40 -> 0 | J63: =Info!$B$42 -> 1 | P63: =(D63+E63+F63+G63+H63+I63+J63)/7 -> 0.22857143 | Q63: =(O63+P63)/2 -> 0.11428571 | R63: =IF(_xlfn.BITAND(P63>0.4999, Q63>0.4999)=1,1,0) -> 0
A64: Toward Automated Detecting Unanticipated Price Feed in Smart Contract | B64: https://dl.acm.org/doi/10.1145/3597926.3598133 | D64: =Info!$B$17 -> 0 | E64: =Info!$B$21 -> 0.3 | F64: =Info!$B$27 -> 0 | G64: =Info!$B$32 -> 0 | H64: =Info!$B$37 -> 0 | I64: =Info!$B$40 -> 0 | J64: =Info!$B$42 -> 1 | P64: =(D64+E64+F64+G64+H64+I64+J64)/7 -> 0.18571429 | Q64: =(O64+P64)/2 -> 0.092857143 | R64: =IF(_xlfn.BITAND(P64>0.4999, Q64>0.4999)=1,1,0) -> 0
A65: Lanturn: Measuring Economic Security of Smart Contracts Through Adaptive Learning | B65: https://dl.acm.org/doi/10.1145/3576915.3623204 | D65: =Info!$B$17 -> 0 | E65: =Info!$B$21 -> 0.3 | F65: =Info!$B$27 -> 0 | G65: =Info!$B$32 -> 0 | H65: =Info!$B$37 -> 0 | I65: =Info!$B$40 -> 0 | J65: =Info!$B$42 -> 1 | P65: =(D65+E65+F65+G65+H65+I65+J65)/7 -> 0.18571429 | Q65: =(O65+P65)/2 -> 0.092857143 | R65: =IF(_xlfn.BITAND(P65>0.4999, Q65>0.4999)=1,1,0) -> 0
A66: Identifying Solidity Smart Contract API Documentation Errors | B66: https://dl.acm.org/doi/10.1145/3551349.3556963 | D66: =Info!$B$17 -> 0 | E66: =Info!$B$21 -> 0.3 | F66: =Info!$B$27 -> 0 | G66: =Info!$B$32 -> 0 | H66: =Info!$B$37 -> 0 | I66: =Info!$B$40 -> 0 | J66: =Info!$B$42 -> 1 | P66: =(D66+E66+F66+G66+H66+I66+J66)/7 -> 0.18571429 | Q66: =(O66+P66)/2 -> 0.092857143 | R66: =IF(_xlfn.BITAND(P66>0.4999, Q66>0.4999)=1,1,0) -> 0
A67: Towards Assessing the Real-World Impact of Defects in Blockchain-Based Smart Contracts | B67: https://dl.acm.org/doi/10.1145/3617572.3617880 | D67: =Info!$B$17 -> 0 | E67: =Info!$B$21 -> 0.3 | F67: =Info!$B$27 -> 0 | G67: =Info!$B$32 -> 0 | H67: =Info!$B$37 -> 0 | I67: =Info!$B$40 -> 0 | J67: =Info!$B$42 -> 1 | P67: =(D67+E67+F67+G67+H67+I67+J67)/7 -> 0.18571429 | Q67: =(O67+P67)/2 -> 0.092857143 | R67: =IF(_xlfn.BITAND(P67>0.4999, Q67>0.4999)=1,1,0) -> 0
A68: Smart contract testing: challenges and opportunities | B68: https://dl.acm.org/doi/10.1145/3528226.3528370 | D68: =Info!$B$17 -> 0 | E68: =Info!$B$22 -> 0 | F68: =Info!$B$27 -> 0 | G68: =Info!$B$32 -> 0 | H68: =Info!$B$37 -> 0 | I68: =Info!$B$40 -> 0 | J68: =Info!$B$42 -> 1 | P68: =(D68+E68+F68+G68+H68+I68+J68)/7 -> 0.14285714 | Q68: =(O68+P68)/2 -> 0.071428571 | R68: =IF(_xlfn.BITAND(P68>0.4999, Q68>0.4999)=1,1,0) -> 0
A69: SmartFuzzDriverGen: Smart Contract Fuzzing Automation for Golang | B69: https://dl.acm.org/doi/10.1145/3578527.3578538 | D69: =Info!$B$17 -> 0 | E69: =Info!$B$22 -> 0 | F69: =Info!$B$27 -> 0 | G69: =Info!$B$32 -> 0 | H69: =Info!$B$37 -> 0 | I69: =Info!$B$40 -> 0 | J69: =Info!$B$42 -> 1 | K69: 1 | P69: =(D69+E69+F69+G69+H69+I69+J69)/7 -> 0.14285714 | Q69: =(O69+P69)/2 -> 0.071428571 | R69: =IF(_xlfn.BITAND(P69>0.4999, Q69>0.4999)=1,1,0) -> 0
A70: ItyFuzz: Snapshot-Based Fuzzer for Smart Contract | B70: https://dl.acm.org/doi/10.1145/3597926.3598059 | D70: =Info!$B$17 -> 0 | E70: =Info!$B$22 -> 0 | F70: =Info!$B$27 -> 0 | G70: =Info!$B$32 -> 0 | H70: =Info!$B$37 -> 0 | I70: =Info!$B$40 -> 0 | J70: =Info!$B$42 -> 1 | P70: =(D70+E70+F70+G70+H70+I70+J70)/7 -> 0.14285714 | Q70: =(O70+P70)/2 -> 0.071428571 | R70: =IF(_xlfn.BITAND(P70>0.4999, Q70>0.4999)=1,1,0) -> 0
A71: Automated Generation of Security-Centric Descriptions for Smart Contract Bytecode | B71: https://dl.acm.org/doi/10.1145/3597926.3598132 | D71: =Info!$B$17 -> 0 | E71: =Info!$B$22 -> 0 | F71: =Info!$B$27 -> 0 | G71: =Info!$B$32 -> 0 | H71: =Info!$B$37 -> 0 | I71: =Info!$B$40 -> 0 | J71: =Info!$B$42 -> 1 | P71: =(D71+E71+F71+G71+H71+I71+J71)/7 -> 0.14285714 | Q71: =(O71+P71)/2 -> 0.071428571 | R71: =IF(_xlfn.BITAND(P71>0.4999, Q71>0.4999)=1,1,0) -> 0
A72: Preserving Privacy of Vulnerable Users across Heterogeneous Sensitive Sensor Data Streams using Smart Contracts | B72: https://dl.acm.org/doi/10.1145/3628354.3629532 | D72: =Info!$B$17 -> 0 | E72: =Info!$B$22 -> 0 | F72: =Info!$B$27 -> 0 | G72: =Info!$B$32 -> 0 | H72: =Info!$B$37 -> 0 | I72: =Info!$B$40 -> 0 | J72: =Info!$B$42 -> 1 | P72: =(D72+E72+F72+G72+H72+I72+J72)/7 -> 0.14285714 | Q72: =(O72+P72)/2 -> 0.071428571 | R72: =IF(_xlfn.BITAND(P72>0.4999, Q72>0.4999)=1,1,0) -> 0
A73: TransRacer: Function Dependence-Guided Transaction Race Detection for Smart Contracts | B73: https://dl.acm.org/doi/10.1145/3611643.3616281 | D73: =Info!$B$17 -> 0 | E73: =Info!$B$22 -> 0 | F73: =Info!$B$27 -> 0 | G73: =Info!$B$32 -> 0 | H73: =Info!$B$37 -> 0 | I73: =Info!$B$40 -> 0 | J73: =Info!$B$42 -> 1 | P73: =(D73+E73+F73+G73+H73+I73+J73)/7 -> 0.14285714 | Q73: =(O73+P73)/2 -> 0.071428571 | R73: =IF(_xlfn.BITAND(P73>0.4999, Q73>0.4999)=1,1,0) -> 0
A74: Can Neural Networks Help Smart Contract Testing? An Empirical Study | B74: https://dl.acm.org/doi/10.1145/3609437.3609455 | D74: =Info!$B$17 -> 0 | E74: =Info!$B$22 -> 0 | F74: =Info!$B$27 -> 0 | G74: =Info!$B$32 -> 0 | H74: =Info!$B$37 -> 0 | I74: =Info!$B$40 -> 0 | J74: =Info!$B$42 -> 1 | P74: =(D74+E74+F74+G74+H74+I74+J74)/7 -> 0.14285714 | Q74: =(O74+P74)/2 -> 0.071428571 | R74: =IF(_xlfn.BITAND(P74>0.4999, Q74>0.4999)=1,1,0) -> 0
A75: Transactional Cross-Chain Smart Contract Invocations | B75: https://dl.acm.org/doi/10.1145/3616023 | D75: =Info!$B$17 -> 0 | E75: =Info!$B$22 -> 0 | F75: =Info!$B$27 -> 0 | G75: =Info!$B$32 -> 0 | H75: =Info!$B$37 -> 0 | I75: =Info!$B$40 -> 0 | J75: =Info!$B$42 -> 1 | P75: =(D75+E75+F75+G75+H75+I75+J75)/7 -> 0.14285714 | Q75: =(O75+P75)/2 -> 0.071428571 | R75: =IF(_xlfn.BITAND(P75>0.4999, Q75>0.4999)=1,1,0) -> 0
A76: Formal Verification of Smart Contract Based on Timed Colored Petri Net | B76: https://dl.acm.org/doi/10.1145/3579895.3579943 | D76: =Info!$B$17 -> 0 | E76: =Info!$B$22 -> 0 | F76: =Info!$B$27 -> 0 | G76: =Info!$B$32 -> 0 | H76: =Info!$B$37 -> 0 | I76: =Info!$B$40 -> 0 | J76: =Info!$B$42 -> 1 | P76: =(D76+E76+F76+G76+H76+I76+J76)/7 -> 0.14285714 | Q76: =(O76+P76)/2 -> 0.071428571 | R76: =IF(_xlfn.BITAND(P76>0.4999, Q76>0.4999)=1,1,0) -> 0
A77: Smart Contract Based Honey Production Supply Chain | B77: https://dl.acm.org/doi/10.1145/3581971.3581981 | D77: =Info!$B$17 -> 0 | E77: =Info!$B$22 -> 0 | F77: =Info!$B$27 -> 0 | G77: =Info!$B$32 -> 0 | H77: =Info!$B$37 -> 0 | I77: =Info!$B$40 -> 0 | J77: =Info!$B$42 -> 1 | P77: =(D77+E77+F77+G77+H77+I77+J77)/7 -> 0.14285714 | Q77: =(O77+P77)/2 -> 0.071428571 | R77: =IF(_xlfn.BITAND(P77>0.4999, Q77>0.4999)=1,1,0) -> 0
A78: Asparagus: Automated Synthesis of Parametric Gas Upper-Bounds for Smart Contracts | B78: https://dl.acm.org/doi/10.1145/3622829 | D78: =Info!$B$17 -> 0 | E78: =Info!$B$22 -> 0 | F78: =Info!$B$27 -> 0 | G78: =Info!$B$32 -> 0 | H78: =Info!$B$37 -> 0 | I78: =Info!$B$40 -> 0 | J78: =Info!$B$42 -> 1 | P78: =(D78+E78+F78+G78+H78+I78+J78)/7 -> 0.14285714 | Q78: =(O78+P78)/2 -> 0.071428571 | R78: =IF(_xlfn.BITAND(P78>0.4999, Q78>0.4999)=1,1,0) -> 0
A79: A Unified Specification Mining Framework for Smart Contracts | B79: https://dl.acm.org/doi/10.1145/3551349.3559512 | D79: =Info!$B$17 -> 0 | E79: =Info!$B$22 -> 0 | F79: =Info!$B$27 -> 0 | G79: =Info!$B$32 -> 0 | H79: =Info!$B$37 -> 0 | I79: =Info!$B$40 -> 0 | J79: =Info!$B$42 -> 1 | P79: =(D79+E79+F79+G79+H79+I79+J79)/7 -> 0.14285714 | Q79: =(O79+P79)/2 -> 0.071428571 | R79: =IF(_xlfn.BITAND(P79>0.4999, Q79>0.4999)=1,1,0) -> 0
A80: Can Smart Contracts Become Smart?: An Overview of Transaction Impact on Ethereum DApp Engineering | B80: https://dl.acm.org/doi/10.1145/3631310.3633492 | D80: =Info!$B$17 -> 0 | E80: =Info!$B$22 -> 0 | F80: =Info!$B$27 -> 0 | G80: =Info!$B$32 -> 0 | H80: =Info!$B$37 -> 0 | I80: =Info!$B$40 -> 0 | J80: =Info!$B$42 -> 1 | P80: =(D80+E80+F80+G80+H80+I80+J80)/7 -> 0.14285714 | Q80: =(O80+P80)/2 -> 0.071428571 | R80: =IF(_xlfn.BITAND(P80>0.4999, Q80>0.4999)=1,1,0) -> 0
A81: DCSS: A Smart Contract-based Data Continuous Storage Scheme | B81: https://dl.acm.org/doi/10.1145/3594556.3594610 | D81: =Info!$B$17 -> 0 | E81: =Info!$B$22 -> 0 | F81: =Info!$B$27 -> 0 | G81: =Info!$B$32 -> 0 | H81: =Info!$B$37 -> 0 | I81: =Info!$B$40 -> 0 | J81: =Info!$B$42 -> 1 | P81: =(D81+E81+F81+G81+H81+I81+J81)/7 -> 0.14285714 | Q81: =(O81+P81)/2 -> 0.071428571 | R81: =IF(_xlfn.BITAND(P81>0.4999, Q81>0.4999)=1,1,0) -> 0
... A114: Simulating Prosumer Data Trading: Testing a Blockchain Smart Contract Based Control | B114: https://dl.acm.org/doi/10.5555/3586210.3586307 | D114: =Info!$B$17 -> 0 | E114: =Info!$B$22 -> 0 | F114: =Info!$B$27 -> 0 | G114: =Info!$B$32 -> 0 | H114: =Info!$B$37 -> 0 | I114: =Info!$B$40 -> 0 | J114: =Info!$B$42 -> 1 | P114: =(D114+E114+F114+G114+H114+I114+J114)/7 -> 0.14285714 | Q114: =(O114+P114)/2 -> 0.071428571 | R114: =IF(_xlfn.BITAND(P114>0.4999, Q114>0.4999)=1,1,0) -> 0
A115: Smart Contract Languages: A Multivocal Mapping Study | B115: https://dl.acm.org/doi/10.1145/3423166 | D115: =Info!$B$17 -> 0 | E115: =Info!$B$21 -> 0.3 | F115: =Info!$B$26 -> 0.3 | G115: =Info!$B$32 -> 0 | H115: =Info!$B$37 -> 0 | I115: =Info!$B$40 -> 0 | J115: =Info!$B$44 -> 0 | P115: =(D115+E115+F115+G115+H115+I115+J115)/7 -> 0.085714286 | Q115: =(O115+P115)/2 -> 0.042857143 | R115: =IF(_xlfn.BITAND(P115>0.4999, Q115>0.4999)=1,1,0) -> 0
A116: Demystifying loops in smart contracts | B116: https://dl.acm.org/doi/10.1145/3324884.3416626 | D116: =Info!$B$17 -> 0 | E116: =Info!$B$21 -> 0.3 | F116: =Info!$B$26 -> 0.3 | G116: =Info!$B$32 -> 0 | H116: =Info!$B$37 -> 0 | I116: =Info!$B$40 -> 0 | J116: =Info!$B$44 -> 0 | P116: =(D116+E116+F116+G116+H116+I116+J116)/7 -> 0.085714286 | Q116: =(O116+P116)/2 -> 0.042857143 | R116: =IF(_xlfn.BITAND(P116>0.4999, Q116>0.4999)=1,1,0) -> 0
A117: Extracting smart contracts tested and verified in Coq | B117: https://dl.acm.org/doi/10.1145/3437992.3439934 | D117: =Info!$B$17 -> 0 | E117: =Info!$B$21 -> 0.3 | F117: =Info!$B$26 -> 0.3 | G117: =Info!$B$32 -> 0 | H117: =Info!$B$37 -> 0 | I117: =Info!$B$40 -> 0 | J117: =Info!$B$44 -> 0 | P117: =(D117+E117+F117+G117+H117+I117+J117)/7 -> 0.085714286 | Q117: =(O117+P117)/2 -> 0.042857143 | R117: =IF(_xlfn.BITAND(P117>0.4999, Q117>0.4999)=1,1,0) -> 0
A118: Making smart contract development more secure and easier | B118: https://dl.acm.org/doi/10.1145/3468264.3473929 | D118: =Info!$B$17 -> 0 | E118: =Info!$B$21 -> 0.3 | F118: =Info!$B$26 -> 0.3 | G118: =Info!$B$32 -> 0 | H118: =Info!$B$37 -> 0 | I118: =Info!$B$40 -> 0 | J118: =Info!$B$44 -> 0 | P118: =(D118+E118+F118+G118+H118+I118+J118)/7 -> 0.085714286 | Q118: =(O118+P118)/2 -> 0.042857143 | R118: =IF(_xlfn.BITAND(P118>0.4999, Q118>0.4999)=1,1,0) -> 0
A119: SolSaviour: A Defending Framework for Deployed Defective Smart Contracts | B119: https://dl.acm.org/doi/10.1145/3485832.3488015 | D119: =Info!$B$17 -> 0 | E119: =Info!$B$21 -> 0.3 | F119: =Info!$B$26 -> 0.3 | G119: =Info!$B$32 -> 0 | H119: =Info!$B$37 -> 0 | I119: =Info!$B$40 -> 0 | J119: =Info!$B$44 -> 0 | P119: =(D119+E119+F119+G119+H119+I119+J119)/7 -> 0.085714286 | Q119: =(O119+P119)/2 -> 0.042857143 | R119: =IF(_xlfn.BITAND(P119>0.4999, Q119>0.4999)=1,1,0) -> 0
A120: Declarative smart contracts | B120: https://dl.acm.org/doi/10.1145/3540250.3549121 | D120: =Info!$B$17 -> 0 | E120: =Info!$B$22 -> 0 | F120: =Info!$B$27 -> 0 | G120: =Info!$B$32 -> 0 | H120: =Info!$B$37 -> 0 | I120: =Info!$B$40 -> 0 | J120: =Info!$B$43 -> 0.5 | P120: =(D120+E120+F120+G120+H120+I120+J120)/7 -> 0.071428571 | Q120: =(O120+P120)/2 -> 0.035714286 | R120: =IF(_xlfn.BITAND(P120>0.4999, Q120>0.4999)=1,1,0) -> 0
A121: Abstract interpretation of Michelson smart-contracts | B121: https://dl.acm.org/doi/10.1145/3520313.3534660 | D121: =Info!$B$17 -> 0 | E121: =Info!$B$22 -> 0 | F121: =Info!$B$27 -> 0 | G121: =Info!$B$32 -> 0 | H121: =Info!$B$37 -> 0 | I121: =Info!$B$40 -> 0 | J121: =Info!$B$43 -> 0.5 | P121: =(D121+E121+F121+G121+H121+I121+J121)/7 -> 0.071428571 | Q121: =(O121+P121)/2 -> 0.035714286 | R121: =IF(_xlfn.BITAND(P121>0.4999, Q121>0.4999)=1,1,0) -> 0
A122: Super-optimization of Smart Contracts | B122: https://dl.acm.org/doi/10.1145/3506800 | D122: =Info!$B$17 -> 0 | E122: =Info!$B$22 -> 0 | F122: =Info!$B$27 -> 0 | G122: =Info!$B$32 -> 0 | H122: =Info!$B$37 -> 0 | I122: =Info!$B$40 -> 0 | J122: =Info!$B$43 -> 0.5 | P122: =(D122+E122+F122+G122+H122+I122+J122)/7 -> 0.071428571 | Q122: =(O122+P122)/2 -> 0.035714286 | R122: =IF(_xlfn.BITAND(P122>0.4999, Q122>0.4999)=1,1,0) -> 0
A123: Elipmoc: advanced decompilation of Ethereum smart contracts | B123: https://dl.acm.org/doi/10.1145/3527321 | D123: =Info!$B$17 -> 0 | E123: =Info!$B$22 -> 0 | F123: =Info!$B$27 -> 0 | G123: =Info!$B$32 -> 0 | H123: =Info!$B$37 -> 0 | I123: =Info!$B$40 -> 0 | J123: =Info!$B$43 -> 0.5 | P123: =(D123+E123+F123+G123+H123+I123+J123)/7 -> 0.071428571 | Q123: =(O123+P123)/2 -> 0.035714286 | R123: =IF(_xlfn.BITAND(P123>0.4999, Q123>0.4999)=1,1,0) -> 0
A124: Smart Contract Scams Detection with Topological Data Analysis on Account Interaction | B124: https://dl.acm.org/doi/10.1145/3511808.3557454 | D124: =Info!$B$17 -> 0 | E124: =Info!$B$22 -> 0 | F124: =Info!$B$27 -> 0 | G124: =Info!$B$32 -> 0 | H124: =Info!$B$37 -> 0 | I124: =Info!$B$40 -> 0 | J124: =Info!$B$43 -> 0.5 | P124: =(D124+E124+F124+G124+H124+I124+J124)/7 -> 0.071428571 | Q124: =(O124+P124)/2 -> 0.035714286 | R124: =IF(_xlfn.BITAND(P124>0.4999, Q124>0.4999)=1,1,0) -> 0
A125: Characterizing transaction-reverting statements in ethereum smart contracts | B125: https://dl.acm.org/doi/10.1109/ASE51524.2021.9678597 | D125: =Info!$B$17 -> 0 | E125: =Info!$B$22 -> 0 | F125: =Info!$B$27 -> 0 | G125: =Info!$B$32 -> 0 | H125: =Info!$B$37 -> 0 | I125: =Info!$B$40 -> 0 | J125: =Info!$B$43 -> 0.5 | P125: =(D125+E125+F125+G125+H125+I125+J125)/7 -> 0.071428571 | Q125: =(O125+P125)/2 -> 0.035714286 | R125: =IF(_xlfn.BITAND(P125>0.4999, Q125>0.4999)=1,1,0) -> 0
A126: Self-supervised learning of smart contract representations | B126: https://dl.acm.org/doi/10.1145/3524610.3527894 | D126: =Info!$B$17 -> 0 | E126: =Info!$B$22 -> 0 | F126: =Info!$B$27 -> 0 | G126: =Info!$B$32 -> 0 | H126: =Info!$B$37 -> 0 | I126: =Info!$B$40 -> 0 | J126: =Info!$B$43 -> 0.5 | P126: =(D126+E126+F126+G126+H126+I126+J126)/7 -> 0.071428571 | Q126: =(O126+P126)/2 -> 0.035714286 | R126: =IF(_xlfn.BITAND(P126>0.4999, Q126>0.4999)=1,1,0) -> 0
A127: An empirical study on implicit constraints in smart contract static analysis | B127: https://dl.acm.org/doi/10.1145/3510457.3513076 | D127: =Info!$B$17 -> 0 | E127: =Info!$B$22 -> 0 | F127: =Info!$B$27 -> 0 | G127: =Info!$B$32 -> 0 | H127: =Info!$B$37 -> 0 | I127: =Info!$B$40 -> 0 | J127: =Info!$B$43 -> 0.5 | P127: =(D127+E127+F127+G127+H127+I127+J127)/7 -> 0.071428571 | Q127: =(O127+P127)/2 -> 0.035714286 | R127: =IF(_xlfn.BITAND(P127>0.4999, Q127>0.4999)=1,1,0) -> 0
A128: Smart Contract-Based Refrigerated Container Traceability System | B128: https://dl.acm.org/doi/10.1145/3532640.3532653 | D128: =Info!$B$17 -> 0 | E128: =Info!$B$22 -> 0 | F128: =Info!$B$27 -> 0 | G128: =Info!$B$32 -> 0 | H128: =Info!$B$37 -> 0 | I128: =Info!$B$40 -> 0 | J128: =Info!$B$43 -> 0.5 | P128: =(D128+E128+F128+G128+H128+I128+J128)/7 -> 0.071428571 | Q128: =(O128+P128)/2 -> 0.035714286 | R128: =IF(_xlfn.BITAND(P128>0.4999, Q128>0.4999)=1,1,0) -> 0
A129: Provably Correct Smart Contracts: An Approach using DeepSEA | B129: https://dl.acm.org/doi/10.1145/3563768.3564116 | D129: =Info!$B$17 -> 0 | E129: =Info!$B$22 -> 0 | F129: =Info!$B$27 -> 0 | G129: =Info!$B$32 -> 0 | H129: =Info!$B$37 -> 0 | I129: =Info!$B$40 -> 0 | J129: =Info!$B$43 -> 0.5 | P129: =(D129+E129+F129+G129+H129+I129+J129)/7 -> 0.071428571 | Q129: =(O129+P129)/2 -> 0.035714286 | R129: =IF(_xlfn.BITAND(P129>0.4999, Q129>0.4999)=1,1,0) -> 0
A130: A study of inline assembly in solidity smart contracts | B130: https://dl.acm.org/doi/10.1145/3563328 | D130: =Info!$B$17 -> 0 | E130: =Info!$B$22 -> 0 | F130: =Info!$B$27 -> 0 | G130: =Info!$B$32 -> 0 | H130: =Info!$B$37 -> 0 | I130: =Info!$B$40 -> 0 | J130: =Info!$B$43 -> 0.5 | P130: =(D130+E130+F130+G130+H130+I130+J130)/7 -> 0.071428571 | Q130: =(O130+P130)/2 -> 0.035714286 | R130: =IF(_xlfn.BITAND(P130>0.4999, Q130>0.4999)=1,1,0) -> 0
A131: Deploying Transactional Smart Contracts using Multisignature Boolean Formulas | B131: https://dl.acm.org/doi/10.1145/3491003.3491014 | D131: =Info!$B$17 -> 0 | E131: =Info!$B$22 -> 0 | F131: =Info!$B$27 -> 0 | G131: =Info!$B$32 -> 0 | H131: =Info!$B$37 -> 0 | I131: =Info!$B$40 -> 0 | J131: =Info!$B$43 -> 0.5 | P131: =(D131+E131+F131+G131+H131+I131+J131)/7 -> 0.071428571 | Q131: =(O131+P131)/2 -> 0.035714286 | R131: =IF(_xlfn.BITAND(P131>0.4999, Q131>0.4999)=1,1,0) -> 0
... A150: Symboleo2SC: from legal contract specifications to smart contracts | B150: https://dl.acm.org/doi/10.1145/3550355.3552407 | D150: =Info!$B$17 -> 0 | E150: =Info!$B$22 -> 0 | F150: =Info!$B$27 -> 0 | G150: =Info!$B$32 -> 0 | H150: =Info!$B$37 -> 0 | I150: =Info!$B$40 -> 0 | J150: =Info!$B$43 -> 0.5 | P150: =(D150+E150+F150+G150+H150+I150+J150)/7 -> 0.071428571 | Q150: =(O150+P150)/2 -> 0.035714286 | R150: =IF(_xlfn.BITAND(P150>0.4999, Q150>0.4999)=1,1,0) -> 0
...

Sheet IEEE_Xplore
A1: Title | B1: Link | C1: Pubblication Class | D1: Q1 | E1: Q2 | F1: Q3 | G1: Q4 | H1: Q5 | I1: Q6 | J1: Q7 | K1: Exc.Crit | L1: Inc.Crit | M1: Pubblication Venue | N1: Vanue Name | O1: IDQ | P1: CDQ | Q1: FDQ | R1: Selected
A2: SCVD-SA: A Smart Contract Vulnerability Detection Method Based on Hybrid Deep Learning Model and Self-attention Mechanism | B2: https://ieeexplore.ieee.org/stamp/stamp.jsp?arnumber=10621722 | C2: PS | D2: 0 | E2: 1 | L2: 2, 3 | M2: Conference Proceeding or Workshops | N2: 2024 IEEE International Conference on Software Analysis Evolution and Reengineering - Companion (SANER-C) | O2: 1 | P2: 0.5 | Q2: 0.75 | R2: =IF(_xlfn.BITAND(P2>0.4999, Q2>0.4999)=1,1,0) -> 1
A3: FEMD: Feature Enhancement-aided Multimodal Feature Fusion Approach for Smart Contract Vulnerability Detection | B3: https://ieeexplore.ieee.org/stamp/stamp.jsp?arnumber=10763613 | C3: PS | D3: 0 | E3: 1 | L3: 2, 3 | M3: Conference Proceeding or Workshops | N3: 2024 IEEE 30th International Conference on Parallel and Distributed Systems (ICPADS) | O3: 1 | P3: 0.5 | Q3: 0.75 | R3: =IF(_xlfn.BITAND(P3>0.4999, Q3>0.4999)=1,1,0) -> 1
A4: FFGDetector: Vulnerability Detection in Cross-Contract Feature Flow Graph Using GCN | B4: https://ieeexplore.ieee.org/stamp/stamp.jsp?arnumber=10885121 | C4: PS | D4: 0 | E4: 1 | L4: 2, 3 | M4: Conference Proceeding or Workshops | N4: 2024 IEEE International Symposium on Parallel and Distributed Processing with Applications (ISPA) | O4: 0.8 | P4: 0.5 | Q4: 0.65 | R4: =IF(_xlfn.BITAND(P4>0.4999, Q4>0.4999)=1,1,0) -> 1
A5: HyWE: A Hybrid Word Embedding Method for Smart Contract Vulnerability Detection | B5: https://ieeexplore.ieee.org/stamp/stamp.jsp?arnumber=10771174 | C5: PS | D5: 0 | E5: 1 | L5: 2, 3 | M5: Conference Proceeding or Workshops | N5: 2024 IEEE 35th International Symposium on Software Reliability Engineering Workshops (ISSREW) | O5: 1 | P5: 0.5 | Q5: 0.75 | R5: =IF(_xlfn.BITAND(P5>0.4999, Q5>0.4999)=1,1,0) -> 1
A6: Smart Contract Vulnerability Detection Based on Automated Feature Extraction and Feature Interaction | B6: https://ieeexplore.ieee.org/stamp/stamp.jsp?arnumber=10319764 | C6: PS | D6: 0 | E6: 1 | L6: 2, 3 | M6: Journal Article | N6: IEEE Transactions on Knowledge and Data Engineering | O6: 1 | P6: 0.5 | Q6: 0.75 | R6: =IF(_xlfn.BITAND(P6>0.4999, Q6>0.4999)=1,1,0) -> 1
A7: Smart Contract: Tools and Challenges | B7: https://ieeexplore.ieee.org/stamp/stamp.jsp?arnumber=10530740 | C7: Review | D7: 0 | E7: 0.6 | F7: 0.6 | G7: 0.6 | H7: 0.6 | I7: 0 | J7: 1 | L7: 1, 2 | M7: Conference Proceeding or Workshops | N7: 2024 1st International Conference on Cognitive Green and Ubiquitous Computing (IC-CGU) | O7: 0.5 | P7: 0.56666667 | Q7: 0.53333333 | R7: =IF(_xlfn.BITAND(P7>0.4999, Q7>0.4999)=1,1,0) -> 1
A8: ParSE: Efficient Detection of Smart Contract Vulnerabilities via Parallel and Simplified Symbolic Execution | B8: https://ieeexplore.ieee.org/stamp/stamp.jsp?arnumber=10554916 | C8: PS | D8: 0 | E8: 1 | L8: 2, 3 | M8: Conference Proceeding or Workshops | N8: 2024 IEEE/ACM 46th International Conference on Software Engineering: Companion Proceedings (ICSE-Companion) | O8: 1 | P8: 0.5 | Q8: 0.75 | R8: =IF(_xlfn.BITAND(P8>0.4999, Q8>0.4999)=1,1,0) -> 1
A9: SCVHUNTER: Smart Contract Vulnerability Detection Based on Heterogeneous Graph Attention Network | B9: https://ieeexplore.ieee.org/stamp/stamp.jsp?arnumber=10549623 | C9: PS | D9: 0 | E9: 1 | L9: 2, 3 | M9: Conference Proceeding or Workshops | N9: 2024 IEEE/ACM 46th International Conference on Software Engineering (ICSE) | O9: 1 | P9: 0.5 | Q9: 0.75 | R9: =IF(_xlfn.BITAND(P9>0.4999, Q9>0.4999)=1,1,0) -> 1
A10: Smart Contract Vulnerability Detection with Self-Ensemble Pre-Trained Language Models | B10: https://ieeexplore.ieee.org/stamp/stamp.jsp?arnumber=10607982 | C10: PS | D10: 0 | E10: 1 | L10: 2, 3 | M10: Conference Proceeding or Workshops | N10: 2024 International Conference on Computer Information and Telecommunication Systems (CITS) | O10: 0.5 | P10: 0.5 | Q10: 0.5 | R10: =IF(_xlfn.BITAND(P10>0.4999, Q10>0.4999)=1,1,0) -> 1
A11: EVM-Shield: In-Contract State Access Control for Fast Vulnerability Detection and Prevention | B11: https://ieeexplore.ieee.org/stamp/stamp.jsp?arnumber=10380598 | C11: PS | D11: 0 | E11: 1 | L11: 2, 3 | M11: Journal Article | N11: IEEE Transactions on Information Forensics and Security | O11: 1 | P11: 0.5 | Q11: 0.75 | R11: =IF(_xlfn.BITAND(P11>0.4999, Q11>0.4999)=1,1,0) -> 1
A12: MuFuzz: Sequence-Aware Mutation and Seed Mask Guidance for Blockchain Smart Contract Fuzzing | B12: https://ieeexplore.ieee.org/stamp/stamp.jsp?arnumber=10597778 | C12: PS | D12: 0 | E12: 1 | K12: 2, 3 | M12: Conference Proceeding or Workshops | N12: 2024 IEEE 40th International Conference on Data Engineering (ICDE) | O12: 1 | P12: 0.5 | Q12: 0.75 | R12: =IF(_xlfn.BITAND(P12>0.4999, Q12>0.4999)=1,1,0) -> 1
A13: MindTheDApp: A Toolchain for Complex Network-Driven Structural Analysis of Ethereum-Based Decentralized Applications | B13: https://ieeexplore.ieee.org/stamp/stamp.jsp?arnumber=10436108 | C13: PS | D13: 0.3 | E13: 1 | K13: 2, 3 | M13: Journal Article | N13: IEEE Access | O13: 1 | P13: 0.65 | Q13: 0.825 | R13: =IF(_xlfn.BITAND(P13>0.4999, Q13>0.4999)=1,1,0) -> 1
A14: LLMSmartSec: Smart Contract Security Auditing with LLM and Annotated Control Flow Graph | B14: https://ieeexplore.ieee.org/stamp/stamp.jsp?arnumber=10664261 | C14: PS | D14: 0 | E14: 1 | K14: 2, 3 | M14: Conference Proceeding or Workshops | N14: 2024 IEEE International Conference on Blockchain (Blockchain) | O14: 0.5 | P14: 0.5 | Q14: 0.5 | R14: =IF(_xlfn.BITAND(P14>0.4999, Q14>0.4999)=1,1,0) -> 1
A15: A Systematic Review of the Blockchain Technology Security Challenges and Threats Classification | B15: https://ieeexplore.ieee.org/stamp/stamp.jsp?arnumber=10844455 | C15: SLR | D15: 1 | E15: 0.6 | F15: 0.6 | G15: 0.3 | H15: 0.3 | I15: 0 | J15: 1 | K15: 1, 2 | M15: Conference Proceeding or Workshops | N15: 2024 6th International Conference on Blockchain Computing and Applications (BCCA) | O15: 0.8 | P15: 0.63333333 | Q15: 0.71666667 | R15: =IF(_xlfn.BITAND(P15>0.4999, Q15>0.4999)=1,1,0) -> 1
A16: FELLMVP: An Ensemble LLM Framework for Classifying Smart Contract Vulnerabilities | B16: https://ieeexplore.ieee.org/stamp/stamp.jsp?arnumber=10664408 | C16: PS | D16: 0.3 | E16: 1 | K16: 2, 3 | M16: Conference Proceeding or Workshops | N16: 2024 IEEE International Conference on Blockchain (Blockchain) | O16: 0.5 | P16: 0.65 | Q16: 0.575 | R16: =IF(_xlfn.BITAND(P16>0.4999, Q16>0.4999)=1,1,0) -> 1
A17: Hunting DeFi Vulnerabilities via Context-Sensitive Concolic Verification | B17: https://ieeexplore.ieee.org/stamp/stamp.jsp?arnumber=10554973 | C17: PS | D17: 0 | E17: 1 | K17: 2, 3 | M17: Conference Proceeding or Workshops | N17: 2024 IEEE/ACM 46th International Conference on Software Engineering: Companion Proceedings (ICSE-Companion) | O17: 1 | P17: 0.5 | Q17: 0.75 | R17: =IF(_xlfn.BITAND(P17>0.4999, Q17>0.4999)=1,1,0) -> 1
A18: ContractCheck: Checking Ethereum Smart Contracts in Fine-Grained Level | B18: https://ieeexplore.ieee.org/stamp/stamp.jsp?arnumber=10531111 | C18: PS | D18: 0 | E18: 1 | K18: 2, 3 | M18: Journal Article | N18: IEEE Transactions on Software Engineering | O18: 1 | P18: 0.5 | Q18: 0.75 | R18: =IF(_xlfn.BITAND(P18>0.4999, Q18>0.4999)=1,1,0) -> 1
A19: SmartInv: Multimodal Learning for Smart Contract Invariant Inference | B19: https://ieeexplore.ieee.org/stamp/stamp.jsp?arnumber=10646885 | C19: PS | D19: 1 | E19: 1 | K19: 2, 3 | M19: Conference Proceeding or Workshops | N19: 2024 IEEE Symposium on Security and Privacy (SP) | O19: 1 | P19: 1 | Q19: 1 | R19: =IF(_xlfn.BITAND(P19>0.4999, Q19>0.4999)=1,1,0) -> 1
A20: Involuntary Transfer: A Vulnerability Pattern in Smart Contracts | B20: https://ieeexplore.ieee.org/stamp/stamp.jsp?arnumber=10385052 | C20: PS | D20: 0 | E20: 1 | K20: 2, 3 | M20: Journal Article | N20: IEEE Access | O20: 1 | P20: 0.5 | Q20: 0.75 | R20: =IF(_xlfn.BITAND(P20>0.4999, Q20>0.4999)=1,1,0) -> 1
A21: EvoFuzzer: An Evolutionary Fuzzer for Detecting Reentrancy Vulnerability in Smart Contracts | B21: https://ieeexplore.ieee.org/stamp/stamp.jsp?arnumber=10643322 | C21: PS | D21: 0 | E21: 1 | K21: 2, 3 | M21: Journal Article | N21: IEEE Transactions on Network Science and Engineering | O21: 1 | P21: 0.5 | Q21: 0.75 | R21: =IF(_xlfn.BITAND(P21>0.4999, Q21>0.4999)=1,1,0) -> 1
A22: The Sword of Damocles: Upgradeable Smart Contract in Ethereum | B22: https://ieeexplore.ieee.org/stamp/stamp.jsp?arnumber=10556443 | C22: Survey | D22: 0 | E22: 0.6 | F22: 0.6 | G22: 0.3 | H22: 0.6 | I22: 0 | J22: 1 | K22: 1, 2 | M22: Conference Proceeding or Workshops | N22: 2024 IEEE/ACM 32nd International Conference on Program Comprehension (ICPC) | O22: 1 | P22: 0.51666667 | Q22: 0.75833333 | R22: =IF(_xlfn.BITAND(P22>0.4999, Q22>0.4999)=1,1,0) -> 1
A23: Blockchain Programming Languages Vulnerabilities and Error Mitigation Strategies | B23: https://ieeexplore.ieee.org/stamp/stamp.jsp?arnumber=10645154 | C23: Survey | D23: 0 | E23: 1 | F23: 0.6 | G23: 0.3 | H23: 0.3 | I23: 0 | J23: 1 | K23: 1, 2 | M23: Conference Proceeding or Workshops | N23: 2024 11th International Conference on Electrical Electronic and Computing Engineering (IcETRAN) | O23: 0.5 | P23: 0.53333333 | Q23: 0.51666667 | R23: =IF(_xlfn.BITAND(P23>0.4999, Q23>0.4999)=1,1,0) -> 1
A24: DeFiRanger: Detecting DeFi Price Manipulation Attacks | B24: https://ieeexplore.ieee.org/stamp/stamp.jsp?arnumber=10373899 | C24: PS | D24: 0 | E24: 1 | K24: 1, 2 | M24: Journal Article | N24: IEEE Transactions on Dependable and Secure Computing | O24: 1 | P24: 0.5 | Q24: 0.75 | R24: =IF(_xlfn.BITAND(P24>0.4999, Q24>0.4999)=1,1,0) -> 1
A25: A Systematic Literature Review of Decentralized Applications in Web3: Identifying Challenges and Opportunities for Blockchain Developers | B25: https://ieeexplore.ieee.org/stamp/stamp.jsp?arnumber=10826066 | C25: SLR | D25: 1 | E25: 0.6 | F25: 0.6 | G25: 0.3 | H25: 0.6 | I25: 0 | J25: 1 | K25: 1, 2 | M25: Conference Proceeding or Workshops | N25: 2024 IEEE International Conference on Big Data (BigData) | O25: 0.8 | P25: 0.68333333 | Q25: 0.51666667 | R25: =IF(_xlfn.BITAND(P25>0.4999, Q25>0.4999)=1,1,0) -> 1
A26: Password-Authenticated Decentralized Identities | B26: https://ieeexplore.ieee.org/document/9551934 | K26: 1 | P26: =(D26+E26+F26+G26+H26+I26+J26)/7 -> 0 | Q26: =(O26+P26)/2 -> 0 | R26: =IF(_xlfn.BITAND(P26>0.4999, Q26>0.4999)=1,1,0) -> 0
A27: Using NFTs for Product Management, Digital Certification, Trading, and Delivery in the Healthcare Supply Chain | B27: https://ieeexplore.ieee.org/document/9935776 | D27: =Info!$B$17 -> 0 | E27: =Info!$B$22 -> 0 | F27: =Info!$B$27 -> 0 | G27: =Info!$B$32 -> 0 | H27: =Info!$B$37 -> 0 | I27: =Info!$B$40 -> 0 | J27: =Info!$B$43 -> 0.5 | P27: =(D27+E27+F27+G27+H27+I27+J27)/7 -> 0.071428571 | Q27: =(O27+P27)/2 -> 0.035714286 | R27: =IF(_xlfn.BITAND(P27>0.4999, Q27>0.4999)=1,1,0) -> 0
A28: Smart Contract Vulnerability Classification and Severity Approaches | B28: https://ieeexplore.ieee.org/stamp/stamp.jsp?arnumber=10583988 | M28: Conference Proceeding or Workshops | N28: 2024 IEEE Ural-Siberian Conference on Biomedical Engineering Radioelectronics and Information Technology (USBEREIT) | R28: =IF(_xlfn.BITAND(P28>0.4999, Q28>0.4999)=1,1,0) -> 0
A29: A C/C++ Smart Contract Vulnerability Detection Method Based on Intermediate Value Transformation | B29: https://ieeexplore.ieee.org/stamp/stamp.jsp?arnumber=10805477 | D29: 0 | M29: Conference Proceeding or Workshops | N29: 2024 4th International Conference on Blockchain Technology and Information Security (ICBCTIS) | R29: =IF(_xlfn.BITAND(P29>0.4999, Q29>0.4999)=1,1,0) -> 0
A30: A Survey of Vulnerability Detection Techniques by Smart Contract Tools | B30: https://ieeexplore.ieee.org/stamp/stamp.jsp?arnumber=10530990 | C30: Survey | D30: 0 | M30: Journal Article | N30: IEEE Access | O30: 1 | R30: =IF(_xlfn.BITAND(P30>0.4999, Q30>0.4999)=1,1,0) -> 0
A31: SELLM: An Integrated Tool Leveraging Symbolic Execution and LLMS for Smart Contract Vulnerability Detection | B31: https://ieeexplore.ieee.org/stamp/stamp.jsp?arnumber=10873603 | D31: 0 | M31: Conference Proceeding or Workshops | N31: 2024 21st International Computer Conference on Wavelet Active Media Technology and Information Processing (ICCWAMTIP) | R31: =IF(_xlfn.BITAND(P31>0.4999, Q31>0.4999)=1,1,0) -> 0
A32: Optimizing Smart Contract Security: A Cost-Sensitive Graph Neural Network Approach for Vulnerability Detection | B32: https://ieeexplore.ieee.org/stamp/stamp.jsp?arnumber=10846442 | D32: 0 | M32: Conference Proceeding or Workshops | N32: 2024 International Conference on Electronic Systems and Intelligent Computing (ICESIC) | R32: =IF(_xlfn.BITAND(P32>0.4999, Q32>0.4999)=1,1,0) -> 0
A33: A Survey on Security Analysis Methods of Smart Contracts | B33: https://ieeexplore.ieee.org/stamp/stamp.jsp?arnumber=10683998 | C33: Survey | D33: 0 | M33: Journal Article | N33: IEEE Transactions on Services Computing | O33: 1 | R33: =IF(_xlfn.BITAND(P33>0.4999, Q33>0.4999)=1,1,0) -> 0
A34: Usage of Static Taint Analysis and Auto Rule Generation for Smart Contract Vulnerability Detection | B34: https://ieeexplore.ieee.org/stamp/stamp.jsp?arnumber=10827343 | D34: 0 | M34: Conference Proceeding or Workshops | N34: 2024 15th International Conference on Information and Communication Technology Convergence (ICTC) | R34: =IF(_xlfn.BITAND(P34>0.4999, Q34>0.4999)=1,1,0) -> 0
A35: An Integrated Smart Contract Vulnerability Detection Tool Using Multi-Layer Perceptron on Real-Time Solidity Smart Contracts | B35: https://ieeexplore.ieee.org/stamp/stamp.jsp?arnumber=10430147 | D35: 0,3 | M35: Journal Article | N35: IEEE Access | O35: 1 | R35: =IF(_xlfn.BITAND(P35>0.4999, Q35>0.4999)=1,1,0) -> 0
A36: An Evaluation of Lightweight CNNs for Smart Contract Vulnerability Detection | B36: https://ieeexplore.ieee.org/stamp/stamp.jsp?arnumber=10634424 | C36: PS | D36: 0 | M36: Conference Proceeding or Workshops | N36: 2024 IEEE International Conference on Blockchain and Cryptocurrency (ICBC) | O36: 0,5 | R36: =IF(_xlfn.BITAND(P36>0.4999, Q36>0.4999)=1,1,0) -> 0
A37: Graph Attention Network with LSTM for Smart Contract Vulnerability Detection | B37: https://ieeexplore.ieee.org/stamp/stamp.jsp?arnumber=10795412 | M37: Conference Proceeding or Workshops | N37: 2024 Conference Proceeding or Workshop on Pervasive and Intelligent Computing (PICom) | R37: =IF(_xlfn.BITAND(P37>0.4999, Q37>0.4999)=1,1,0) -> 0
A38: ContractGNN: Ethereum Smart Contract Vulnerability Detection Based on Vulnerability Sub-Graphs and Graph Neural Networks | B38: https://ieeexplore.ieee.org/stamp/stamp.jsp?arnumber=10700860 | C38: PS | D38: 0 | E38: 1 | M38: Journal Article | N38: IEEE Transactions on Network Science and Engineering | O38: 1 | R38: =IF(_xlfn.BITAND(P38>0.4999, Q38>0.4999)=1,1,0) -> 0
A39: Design and Optimization of Smart Contracts for Cross-Domain Sharing of Sensitive Data | B39: https://ieeexplore.ieee.org/stamp/stamp.jsp?arnumber=10763577 | D39: 0 | M39: Conference Proceeding or Workshops | N39: 2024 IEEE 30th International Conference on Parallel and Distributed Systems (ICPADS) | R39: =IF(_xlfn.BITAND(P39>0.4999, Q39>0.4999)=1,1,0) -> 0
A40: The Security Paradox of Smart Contracts: Blind Spots and Prospects of Current Detection Strategies | B40: https://ieeexplore.ieee.org/stamp/stamp.jsp?arnumber=10580546 | M40: Conference Proceeding or Workshops | N40: 2024 27th International Conference on Computer Supported Cooperative Work in Design (CSCWD) | R40: =IF(_xlfn.BITAND(P40>0.4999, Q40>0.4999)=1,1,0) -> 0
A41: Vulnerabilities in Smart Contracts: A Detailed Survey of Detection and Mitigation Methodologies | B41: https://ieeexplore.ieee.org/stamp/stamp.jsp?arnumber=10544155 | C41: Survey | D41: 0 | M41: Conference Proceeding or Workshops | N41: 2024 International Conference on Emerging Technologies in Computer Science for Interdisciplinary Applications (ICETCS) | R41: =IF(_xlfn.BITAND(P41>0.4999, Q41>0.4999)=1,1,0) -> 0
A42: Unity is Strength: Enhancing Precision in Reentrancy Vulnerability Detection of Smart Contract Analysis Tools | B42: https://ieeexplore.ieee.org/stamp/stamp.jsp?arnumber=10596931 | D42: 0 | M42: Journal Article | N42: IEEE Transactions on Software Engineering | O42: 1 | R42: =IF(_xlfn.BITAND(P42>0.4999, Q42>0.4999)=1,1,0) -> 0
A43: SCcheck: A Novel Graph-Driven and Attention- Enabled Smart Contract Vulnerability Detection Framework for Web 3.0 Ecosystem | B43: https://ieeexplore.ieee.org/stamp/stamp.jsp?arnumber=10292506 | D43: 0 | M43: Journal Article | N43: IEEE Transactions on Network Science and Engineering | O43: 1 | R43: =IF(_xlfn.BITAND(P43>0.4999, Q43>0.4999)=1,1,0) -> 0
A44: TLSCG: Transfer Learning-Based Efficient Anomalous Smart Contract Generation to Empower Unknown Vulnerability Detection | B44: https://ieeexplore.ieee.org/stamp/stamp.jsp?arnumber=10707589 | D44: 0 | M44: Conference Proceeding or Workshops | N44: 2024 IEEE International Conference on Web Services (ICWS) | R44: =IF(_xlfn.BITAND(P44>0.4999, Q44>0.4999)=1,1,0) -> 0
A45: Smart Contract Vulnerabilities and Detection Methods: A Survey | B45: https://ieeexplore.ieee.org/stamp/stamp.jsp?arnumber=10724246 | C45: Survey | M45: Conference Proceeding or Workshops | N45: 2024 15th International Conference on Computing Communication and Networking Technologies (ICCCNT) | R45: =IF(_xlfn.BITAND(P45>0.4999, Q45>0.4999)=1,1,0) -> 0
A46: Validating Smart Contracts Using GPT Assistant | B46: https://ieeexplore.ieee.org/stamp/stamp.jsp?arnumber=10633647 | D46: 0 | M46: Conference Proceeding or Workshops | N46: 2024 IEEE 48th Annual Computers Software and Applications Conference (COMPSAC) | R46: =IF(_xlfn.BITAND(P46>0.4999, Q46>0.4999)=1,1,0) -> 0
A47: Comprehensive Evaluation of Static Analysis Tools for Their Performance in Finding Vulnerabilities in Java Code | B47: https://ieeexplore.ieee.org/stamp/stamp.jsp?arnumber=10500698 | D47: 0 | L47: 1 | M47: Journal Article | N47: IEEE Access | O47: 1 | R47: =IF(_xlfn.BITAND(P47>0.4999, Q47>0.4999)=1,1,0) -> 0
A48: Smart Contract Reentrancy Vulnerability Detection Based on CNN and LSTM-Attention | B48: https://ieeexplore.ieee.org/stamp/stamp.jsp?arnumber=10581851 | D48: 0 | M48: Conference Proceeding or Workshops | N48: 2024 5th International Seminar on Artificial Intelligence Networking and Information Technology (AINIT) | R48: =IF(_xlfn.BITAND(P48>0.4999, Q48>0.4999)=1,1,0) -> 0
A49: Smart Contract Vulnerability Detection Based on Prompt-guided ChatGPT | B49: https://ieeexplore.ieee.org/stamp/stamp.jsp?arnumber=10679877 | M49: Conference Proceeding or Workshops | N49: 2024 International Conference on Networking and Network Applications (NaNA) | R49: =IF(_xlfn.BITAND(P49>0.4999, Q49>0.4999)=1,1,0) -> 0
A50: Smart Contract Vulnerability Detection Based on Machine Learning | B50: https://ieeexplore.ieee.org/stamp/stamp.jsp?arnumber=10696331 | M50: Conference Proceeding or Workshops | N50: 2024 6th International Conference on Electronic Engineering and Informatics (EEI) | R50: =IF(_xlfn.BITAND(P50>0.4999, Q50>0.4999)=1,1,0) -> 0
A51: Advanced Smart Contract Vulnerability Detection Using Large Language Models | B51: https://ieeexplore.ieee.org/stamp/stamp.jsp?arnumber=10851734 | D51: 0 | M51: Conference Proceeding or Workshops | N51: 2024 8th Cyber Security in Networking Conference (CSNet) | R51: =IF(_xlfn.BITAND(P51>0.4999, Q51>0.4999)=1,1,0) -> 0
A52: Large-Scale Study of Vulnerability Scanners for Ethereum Smart Contracts | B52: https://ieeexplore.ieee.org/stamp/stamp.jsp?arnumber=10646883 | D52: 0 | M52: Conference Proceeding or Workshops | N52: 2024 IEEE Symposium on Security and Privacy (SP) | R52: =IF(_xlfn.BITAND(P52>0.4999, Q52>0.4999)=1,1,0) -> 0
A53: VFIX: Facilitating Software Maintenance of Smart Contracts via Automatically Fixing Vulnerabilities | B53: https://ieeexplore.ieee.org/stamp/stamp.jsp?arnumber=10795093 | C53: PS | D53: 0 | E53: 1 | M53: Conference Proceeding or Workshops | N53: 2024 IEEE International Conference on Software Maintenance and Evolution (ICSME) | R53: =IF(_xlfn.BITAND(P53>0.4999, Q53>0.4999)=1,1,0) -> 0
A54: Hypeleger Fabric Smart Contract Vulnerability Detection Technology: An Overview | B54: https://ieeexplore.ieee.org/stamp/stamp.jsp?arnumber=10605149 | M54: Conference Proceeding or Workshops | N54: 2024 IEEE 11th International Conference on Cyber Security and Cloud Computing (CSCloud) | R54: =IF(_xlfn.BITAND(P54>0.4999, Q54>0.4999)=1,1,0) -> 0
A55: Machine Learning for Cross-Vulnerability Prediction in Smart Contracts | B55: https://ieeexplore.ieee.org/stamp/stamp.jsp?arnumber=10675812 | M55: Conference Proceeding or Workshops | N55: 2024 IEEE International Conference on Software Testing Verification and Validation Workshops (ICSTW) | R55: =IF(_xlfn.BITAND(P55>0.4999, Q55>0.4999)=1,1,0) -> 0
A56: Ethereum Smart Contracts Vulnerabilities Detection Leveraging Fine-Tuning DistilBERT | B56: https://ieeexplore.ieee.org/stamp/stamp.jsp?arnumber=10830749 | C56: PS | D56: 0 | E56: 1 | M56: Conference Proceeding or Workshops | N56: 2024 International Conference on Platform Technology and Service (PlatCon) | R56: =IF(_xlfn.BITAND(P56>0.4999, Q56>0.4999)=1,1,0) -> 0
A57: Smart Contract Vulnerability Detection Based on AST-Augmented Heterogeneous Graphs | B57: https://ieeexplore.ieee.org/stamp/stamp.jsp?arnumber=10850061 | D57: 0 | M57: Conference Proceeding or Workshops | N57: 2024 IEEE International Performance Computing and Communications Conference (IPCCC) | R57: =IF(_xlfn.BITAND(P57>0.4999, Q57>0.4999)=1,1,0) -> 0
A58: Research on Smart Contract Vulnerability Detection Method of Power Equipment Based on Deep Learning Algorithm | B58: https://ieeexplore.ieee.org/stamp/stamp.jsp?arnumber=10470681 | M58: Conference Proceeding or Workshops | N58: 2024 International Conference on Optimization Computing and Wireless Communication (ICOCWC) | R58: =IF(_xlfn.BITAND(P58>0.4999, Q58>0.4999)=1,1,0) -> 0
A59: Elevating Smart Contract Defenses: A Coordinated NLP-Based Strategy for Vulnerability Detection | B59: https://ieeexplore.ieee.org/stamp/stamp.jsp?arnumber=10731796 | M59: Conference Proceeding or Workshops | N59: 2024 IEEE International Conferences on Internet of Things (iThings) and IEEE Green Computing & Communications (GreenCom) and IEEE Cyber Physical & Social Computing (CPSCom) and IEEE Smart Data (SmartData) and IEEE Congress on Cybermatics | R59: =IF(_xlfn.BITAND(P59>0.4999, Q59>0.4999)=1,1,0) -> 0
A60: Improving Smart Contract Analysis with Large Language Models: The SLLM System | B60: https://ieeexplore.ieee.org/stamp/stamp.jsp?arnumber=10846030 | D60: 0 | M60: Conference Proceeding or Workshops | N60: 2024 IEEE 17th International Conference on Signal Processing (ICSP) | R60: =IF(_xlfn.BITAND(P60>0.4999, Q60>0.4999)=1,1,0) -> 0
A61: A Universal and Efficient Multi-Modal Smart Contract Vulnerability Detection Framework for Big Data | B61: https://ieeexplore.ieee.org/stamp/stamp.jsp?arnumber=10535206 | D61: 0 | M61: Journal Article | N61: IEEE Transactions on Big Data | O61: 1 | R61: =IF(_xlfn.BITAND(P61>0.4999, Q61>0.4999)=1,1,0) -> 0
A62: Smart Contract Vulnerability Detection via Feature Fusion of Local Data Flow and Global Features | B62: https://ieeexplore.ieee.org/stamp/stamp.jsp?arnumber=10885369 | M62: Conference Proceeding or Workshops | N62: 2024 IEEE International Symposium on Parallel and Distributed Processing with Applications (ISPA) | R62: =IF(_xlfn.BITAND(P62>0.4999, Q62>0.4999)=1,1,0) -> 0
A63: Smart Contract and DeFi Security Tools: Do They Meet the Needs of Practitioners? | B63: https://ieeexplore.ieee.org/stamp/stamp.jsp?arnumber=10548356 | D63: 0,3 | M63: Conference Proceeding or Workshops | N63: 2024 IEEE/ACM 46th International Conference on Software Engineering (ICSE) | O63: 1 | R63: =IF(_xlfn.BITAND(P63>0.4999, Q63>0.4999)=1,1,0) -> 0
A64: ContractTinker: LLM-Empowered Vulnerability Repair for Real-World Smart Contracts | B64: https://ieeexplore.ieee.org/stamp/stamp.jsp?arnumber=10764925 | D64: 0 | M64: Conference Proceeding or Workshops | N64: 2024 39th IEEE/ACM International Conference on Automated Software Engineering (ASE) | O64: 1 | R64: =IF(_xlfn.BITAND(P64>0.4999, Q64>0.4999)=1,1,0) -> 0
A65: Robust Vulnerability Detection in Solidity-Based Ethereum Smart Contracts Using Fine-Tuned Transformer Encoder Models | B65: https://ieeexplore.ieee.org/stamp/stamp.jsp?arnumber=10720785 | M65: Journal Article | N65: IEEE Access | O65: 1 | R65: =IF(_xlfn.BITAND(P65>0.4999, Q65>0.4999)=1,1,0) -> 0
A66: SERNet-T: A Smart Contract Multi-label Vulnerability Detection Model Based on SE Attention and One-Dimensional Residual Network | B66: https://ieeexplore.ieee.org/stamp/stamp.jsp?arnumber=10843662 | C66: PS | D66: 0 | E66: 1 | M66: Conference Proceeding or Workshops | N66: 2024 IEEE International Conference on Cognitive Computing and Complex Data (ICCD) | R66: =IF(_xlfn.BITAND(P66>0.4999, Q66>0.4999)=1,1,0) -> 0
A67: Smart Contract Security Vulnerability Through The NIST Cybersecurity Framework 2.0 Perspective | B67: https://ieeexplore.ieee.org/stamp/stamp.jsp?arnumber=10877189 | D67: 0 | M67: Conference Proceeding or Workshops | N67: 2024 25th International Arab Conference on Information Technology (ACIT) | R67: =IF(_xlfn.BITAND(P67>0.4999, Q67>0.4999)=1,1,0) -> 0
A68: Demo: Blockchain Shield - Advanced Threat Detection & Forensic Analysis Platform | B68: https://ieeexplore.ieee.org/stamp/stamp.jsp?arnumber=10631082 | M68: Conference Proceeding or Workshops | N68: 2024 IEEE 44th International Conference on Distributed Computing Systems (ICDCS) | R68: =IF(_xlfn.BITAND(P68>0.4999, Q68>0.4999)=1,1,0) -> 0
A69: GNN-based Ethereum Smart Contract Multi-Label Vulnerability Detection | B69: https://ieeexplore.ieee.org/stamp/stamp.jsp?arnumber=10572078 | M69: Conference Proceeding or Workshops | N69: 2024 International Conference on Information Networking (ICOIN) | R69: =IF(_xlfn.BITAND(P69>0.4999, Q69>0.4999)=1,1,0) -> 0
A70: Improving Smart Contract Security with Contrastive Learning-Based Vulnerability Detection | B70: https://ieeexplore.ieee.org/stamp/stamp.jsp?arnumber=10549161 | M70: Conference Proceeding or Workshops | N70: 2024 IEEE/ACM 46th International Conference on Software Engineering (ICSE) | O70: 1 | R70: =IF(_xlfn.BITAND(P70>0.4999, Q70>0.4999)=1,1,0) -> 0
A71: Combining Deep Learning and Expert Rules for Smart Contract Vulnerability Detection | B71: https://ieeexplore.ieee.org/stamp/stamp.jsp?arnumber=10831120 | M71: Conference Proceeding or Workshops | N71: 2024 IEEE International Conference on Systems Man and Cybernetics (SMC) | R71: =IF(_xlfn.BITAND(P71>0.4999, Q71>0.4999)=1,1,0) -> 0
A72: Research on Dynamic Detection of Vulnerabilities in Smart Contracts Based on Machine Learning | B72: https://ieeexplore.ieee.org/stamp/stamp.jsp?arnumber=10485831 | M72: Conference Proceeding or Workshops | N72: 2024 IEEE 3rd International Conference on Electrical Engineering Big Data and Algorithms (EEBDA) | R72: =IF(_xlfn.BITAND(P72>0.4999, Q72>0.4999)=1,1,0) -> 0
A73: Smart Contract Vulnerability Detection Using Deep Learning Algorithms on EVM bytecode | B73: https://ieeexplore.ieee.org/stamp/stamp.jsp?arnumber=10577852 | D73: 0 | M73: Conference Proceeding or Workshops | N73: 2024 13th Mediterranean Conference on Embedded Computing (MECO) | R73: =IF(_xlfn.BITAND(P73>0.4999, Q73>0.4999)=1,1,0) -> 0
A74: On the Road to Proactive Vulnerability Analysis and Mitigation Leveraged by Software Defined Networks: A Systematic Review | B74: https://ieeexplore.ieee.org/stamp/stamp.jsp?arnumber=10599429 | C74: SLR | M74: Journal Article | N74: IEEE Access | O74: 1 | R74: =IF(_xlfn.BITAND(P74>0.4999, Q74>0.4999)=1,1,0) -> 0
A75: A method for detecting re-entry vulnerabilities in large local area network smart contracts based on eBPF | B75: https://ieeexplore.ieee.org/stamp/stamp.jsp?arnumber=10699156 | M75: Conference Proceeding or Workshops | N75: 2024 4th International Symposium on Computer Technology and Information Science (ISCTIS) | R75: =IF(_xlfn.BITAND(P75>0.4999, Q75>0.4999)=1,1,0) -> 0
A76: Blockchain Smart Contract Vulnerability Detection and Segmentation Using ML | B76: https://ieeexplore.ieee.org/stamp/stamp.jsp?arnumber=10634473 | C76: PS | M76: Conference Proceeding or Workshops | N76: 2024 IEEE International Conference on Blockchain and Cryptocurrency (ICBC) | O76: 0.5 | R76: =IF(_xlfn.BITAND(P76>0.4999, Q76>0.4999)=1,1,0) -> 0
A77: Understanding and Detecting Privacy Leakage Vulnerabilities in Hyperledger Fabric Chaincodes | B77: https://ieeexplore.ieee.org/stamp/stamp.jsp?arnumber=10771204 | L77: 1 | M77: Conference Proceeding or Workshops | N77: 2024 IEEE 35th International Symposium on Software Reliability Engineering (ISSRE) | O77: 1 | R77: =IF(_xlfn.BITAND(P77>0.4999, Q77>0.4999)=1,1,0) -> 0
A78: A Qualitative Study on Using ChatGPT for Software Security: Perception vs. Practicality | B78: https://ieeexplore.ieee.org/stamp/stamp.jsp?arnumber=10835695 | M78: Conference Proceeding or Workshops | N78: 2024 IEEE 6th International Conference on Trust Privacy and Security in Intelligent Systems and Applications (TPS-ISA) | R78: =IF(_xlfn.BITAND(P78>0.4999, Q78>0.4999)=1,1,0) -> 0
A79: Formal Verification of ERC-Based Smart Contracts: A Systematic Literature Review | B79: https://ieeexplore.ieee.org/stamp/stamp.jsp?arnumber=10833642 | M79: Journal Article | N79: IEEE Access | O79: 1 | R79: =IF(_xlfn.BITAND(P79>0.4999, Q79>0.4999)=1,1,0) -> 0
A80: Smart Contract Vulnerability Detection Under Digital Assets | B80: https://ieeexplore.ieee.org/stamp/stamp.jsp?arnumber=10735475 | M80: Conference Proceeding or Workshops | N80: 2024 4th International Conference on Computer Science and Blockchain (CCSB) | R80: =IF(_xlfn.BITAND(P80>0.4999, Q80>0.4999)=1,1,0) -> 0
A81: AdvSCanner: Generating Adversarial Smart Contracts to Exploit Reentrancy Vulnerabilities Using LLM and Static Analysis | B81: https://ieeexplore.ieee.org/stamp/stamp.jsp?arnumber=10764830 | M81: Conference Proceeding or Workshops | N81: 2024 39th IEEE/ACM International Conference on Automated Software Engineering (ASE) | O81: 1 | R81: =IF(_xlfn.BITAND(P81>0.4999, Q81>0.4999)=1,1,0) -> 0
A82: QuadraCode AI: Smart Contract Vulnerability Detection with Multimodal Representation | B82: https://ieeexplore.ieee.org/stamp/stamp.jsp?arnumber=10637655 | M82: Conference Proceeding or Workshops | N82: 2024 33rd International Conference on Computer Communications and Networks (ICCCN) | R82: =IF(_xlfn.BITAND(P82>0.4999, Q82>0.4999)=1,1,0) -> 0
A83: GPTScan: Detecting Logic Vulnerabilities in Smart Contracts by Combining GPT with Program Analysis | B83: https://ieeexplore.ieee.org/stamp/stamp.jsp?arnumber=10549149 | D83: 1 | M83: Conference Proceeding or Workshops | N83: 2024 IEEE/ACM 46th International Conference on Software Engineering (ICSE) | O83: 1 | R83: =IF(_xlfn.BITAND(P83>0.4999, Q83>0.4999)=1,1,0) -> 0
A84: Oracle-Guided Vulnerability Diversity and Exploit Synthesis of Smart Contracts Using LLMs | B84: https://ieeexplore.ieee.org/stamp/stamp.jsp?arnumber=10765027 | D84: 0 | M84: Conference Proceeding or Workshops | N84: 2024 39th IEEE/ACM International Conference on Automated Software Engineering (ASE) | O84: 1 | R84: =IF(_xlfn.BITAND(P84>0.4999, Q84>0.4999)=1,1,0) -> 0
A85: Enhancing Smart Contract Vulnerability Detection using Graph-Based Deep Learning Approaches | B85: https://ieeexplore.ieee.org/stamp/stamp.jsp?arnumber=10860016 | M85: Conference Proceeding or Workshops | N85: 2024 International Conference on Integrated Intelligence and Communication Systems (ICIICS) | R85: =IF(_xlfn.BITAND(P85>0.4999, Q85>0.4999)=1,1,0) -> 0
A86: Deep Learning-Based Vulnerability Detection Solutions in Smart Contracts: A Comparative and Meta-Analysis of Existing Approaches | B86: https://ieeexplore.ieee.org/stamp/stamp.jsp?arnumber=10848097 | D86: 0 | M86: Journal Article | N86: IEEE Access | O86: 1 | R86: =IF(_xlfn.BITAND(P86>0.4999, Q86>0.4999)=1,1,0) -> 0
A87: Enhancing Transparency in the Peer-to-Peer Transactive Energy Market: Smart Contract Monitoring in Bilateral Negotiations with the Ethereum Platform | B87: https://ieeexplore.ieee.org/stamp/stamp.jsp?arnumber=10631949 | K87: 1 | M87: Conference Proceeding or Workshops | N87: 2024 9th International Conference on Technology and Energy Management (ICTEM) | R87: =IF(_xlfn.BITAND(P87>0.4999, Q87>0.4999)=1,1,0) -> 0
A88: Exploring Smart Contracts based on Web 3.0 Applications with respect to Vulnerability Detection Mechanisms | B88: https://ieeexplore.ieee.org/stamp/stamp.jsp?arnumber=10560371 | D88: 0 | M88: Conference Proceeding or Workshops | N88: 2024 International Conference on Computing and Data Science (ICCDS) | R88: =IF(_xlfn.BITAND(P88>0.4999, Q88>0.4999)=1,1,0) -> 0
A89: Smart Contract Upgradability: A Structured and Natural Approach | B89: https://ieeexplore.ieee.org/stamp/stamp.jsp?arnumber=10844407 | M89: Conference Proceeding or Workshops | N89: 2024 6th International Conference on Blockchain Computing and Applications (BCCA) | R89: =IF(_xlfn.BITAND(P89>0.4999, Q89>0.4999)=1,1,0) -> 0
A90: A Methodology for Vulnerability Assessment and Threat Modelling of an e-Voting Platform Based on Ethereum Blockchain | B90: https://ieeexplore.ieee.org/stamp/stamp.jsp?arnumber=10750196 | M90: Journal Article | N90: IEEE Access | O90: 1 | R90: =IF(_xlfn.BITAND(P90>0.4999, Q90>0.4999)=1,1,0) -> 0
A91: Research on link layer vulnerability of master-slave scheduling in industrial control network based on stochastic Petri net | B91: https://ieeexplore.ieee.org/stamp/stamp.jsp?arnumber=10624735 | K91: 1 | M91: Conference Proceeding or Workshops | N91: 2024 3rd International Conference on Energy and Power Engineering Control Engineering (EPECE) | R91: =IF(_xlfn.BITAND(P91>0.4999, Q91>0.4999)=1,1,0) -> 0
A92: Static Detection of Missing Validations in Solidity Smart Contracts | B92: https://ieeexplore.ieee.org/stamp/stamp.jsp?arnumber=10679381 | D92: 0 | M92: Conference Proceeding or Workshops | N92: 2024 IEEE International Conference on Cyber Security and Resilience (CSR) | R92: =IF(_xlfn.BITAND(P92>0.4999, Q92>0.4999)=1,1,0) -> 0
A93: Detecting Reentrancy Vulnerability in Smart Contracts using Graph Convolution Networks | B93: https://ieeexplore.ieee.org/stamp/stamp.jsp?arnumber=10454763 | M93: Conference Proceeding or Workshops | N93: 2024 IEEE 21st Consumer Communications & Networking Conference (CCNC) | R93: =IF(_xlfn.BITAND(P93>0.4999, Q93>0.4999)=1,1,0) -> 0
A94: Data Breaches: Financial and Reputational Impacts of Vulnerabilities on Organizations to Enhance Cybersecurity Strategies | B94: https://ieeexplore.ieee.org/stamp/stamp.jsp?arnumber=10841577 | M94: Conference Proceeding or Workshops | N94: 2024 3rd International Conference on Automation Computing and Renewable Systems (ICACRS) | R94: =IF(_xlfn.BITAND(P94>0.4999, Q94>0.4999)=1,1,0) -> 0
A95: Blockchain and Smart Contracts: Evolution | B95: 10.1109/ICKECS61492.2024.10616652 | K95: 1 | M95: Conference Proceeding or Workshop | N95: 2024 International Conference on Knowledge Engineering and Communication Systems (ICKECS) | R95: =IF(_xlfn.BITAND(P95>0.4999, Q95>0.4999)=1,1,0) -> 0
A96: An Approach to Optimize Symbolic Execution in Ethereum Smart Contracts | B96: https://ieeexplore.ieee.org/stamp/stamp.jsp?arnumber=10727001 | M96: Conference Proceeding or Workshops | N96: 2024 IEEE 24th International Conference on Software Quality Reliability and Security Companion (QRS-C) | O96: 1 | R96: =IF(_xlfn.BITAND(P96>0.4999, Q96>0.4999)=1,1,0) -> 0
A97: VulnFusion: Exploiting Multimodal Representations for Advanced Smart Contract Vulnerability Detection | B97: https://ieeexplore.ieee.org/stamp/stamp.jsp?arnumber=10844483 | M97: Conference Proceeding or Workshops | N97: 2024 6th International Conference on Blockchain Computing and Applications (BCCA) | R97: =IF(_xlfn.BITAND(P97>0.4999, Q97>0.4999)=1,1,0) -> 0
A98: Systematic Study of Compilers and Vulnerability Scanners Using the Example of Integer Bugs | B98: https://ieeexplore.ieee.org/stamp/stamp.jsp?arnumber=10664359 | D98: 0 | M98: Conference Proceeding or Workshops | N98: 2024 IEEE International Conference on Blockchain (Blockchain) | O98: 0,5 | R98: =IF(_xlfn.BITAND(P98>0.4999, Q98>0.4999)=1,1,0) -> 0
A99: Verifying Declarative Smart Contracts | B99: https://ieeexplore.ieee.org/stamp/stamp.jsp?arnumber=10548754 | D99: 0 | M99: Conference Proceeding or Workshops | N99: 2024 IEEE/ACM 46th International Conference on Software Engineering (ICSE) | O99: 1 | R99: =IF(_xlfn.BITAND(P99>0.4999, Q99>0.4999)=1,1,0) -> 0
A100: Cyber Risks and Blockchain Security for Digital Forensics | B100: https://ieeexplore.ieee.org/stamp/stamp.jsp?arnumber=10576471 | M100: Conference Proceeding or Workshops | N100: 2024 IEEE 14th Symposium on Computer Applications & Industrial Electronics (ISCAIE) | R100: =IF(_xlfn.BITAND(P100>0.4999, Q100>0.4999)=1,1,0) -> 0
...

Sheet Science_Direct
A1: Title | B1: Link | C1: Pubblication Class | D1: Q1 | E1: Q2 | F1: Q3 | G1: Q4 | H1: Q5 | I1: Q6 | J1: Q7 | K1: Exc.Crit | L1: Inc.Crit | M1: Pubblication Venue | N1: Vanue Name | O1: IDQ | P1: CDQ | Q1: FDQ | R1: Selected
A2: A security framework for Ethereum smart contracts | C2: PS | D2: =Info!$B$48 -> 1 | E2: =Info!$B$53 -> 1 | L2: 2 | M2: Journal Article | N2: Computer Communications | O2: 1 | P2: =(D2+E2)/2 -> 1 | Q2: =(O2+P2)/2 -> 1 | R2: =IF(_xlfn.BITAND(P2>0.4999, Q2>0.4999)=1,1,0) -> 1
A3: A systematic literature review of blockchain and smart contract development: Techniques, tools, and open challenges | B3: https://www.sciencedirect.com/science/article/pii/S0164121220302818 | C3: SLR | D3: =Info!$B$16 -> 1 | E3: =Info!$B$21 -> 0.3 | F3: =Info!$B$27 -> 0 | G3: =Info!$B$29 -> 1 | H3: =Info!$B$36 -> 0.3 | I3: =Info!$B$39 -> 1 | J3: =Info!$B$44 -> 0 | L3: 1.2 | M3: Journal Article | N3: Journal of Systems and Software | O3: 1 | P3: =(D3+E3+F3+G3+H3+I3+J3)/7 -> 0.51428571 | Q3: =(O3+P3)/2 -> 0.75714286 | R3: =IF(_xlfn.BITAND(P3>0.4999, Q3>0.4999)=1,1,0) -> 1
A4: Block-gram: Mining Knowledgeable Features for Smart Contract Vulnerability Detection | B4: https://www.sciencedirect.com/science/article/pii/S2352864823001347 | C4: PS | D4: =Info!$B$51 -> 0 | E4: =Info!$B$53 -> 1 | L4: 2,3 | M4: Journal Article | N4: Digital Communications and Networks | O4: 1 | P4: =(D4+E4)/2 -> 0.5 | Q4: =(O4+P4)/2 -> 0.75 | R4: =IF(_xlfn.BITAND(P4>0.4999, Q4>0.4999)=1,1,0) -> 1
A5: Combine sliced joint graph with graph neural networks for smart contract vulnerability detection | C5: PS | D5: =Info!$B$48 -> 1 | E5: =Info!$B$53 -> 1 | L5: 2,3 | M5: Journal Article | N5: Journal of Systems and Software | O5: 1 | P5: =(D5+E5)/2 -> 1 | Q5: =(O5+P5)/2 -> 1 | R5: =IF(_xlfn.BITAND(P5>0.4999, Q5>0.4999)=1,1,0) -> 1
A6: CrossFuzz: Cross-contract fuzzing for smart contract vulnerability detection | B6: https://www.sciencedirect.com/science/article/pii/S0167642323001582 | C6: PS | D6: =Info!$B$51 -> 0 | E6: =Info!$B$53 -> 1 | L6: 2,3 | M6: Journal Article | N6: Science of Computer Programming | O6: 0.5 | P6: =(D6+E6)/2 -> 0.5 | Q6: =(O6+P6)/2 -> 0.5 | R6: =IF(_xlfn.BITAND(P6>0.4999, Q6>0.4999)=1,1,0) -> 1
A7: Effuzz: Efficient fuzzing by directed search for smart contracts | B7: https://www.sciencedirect.com/science/article/pii/S0950584923000678 | C7: PS | D7: =Info!$B$51 -> 0 | E7: =Info!$B$53 -> 1 | L7: 2,3 | M7: Journal Article | N7: Information and Software Technology | O7: 1 | P7: =(D7+E7)/2 -> 0.5 | Q7: =(O7+P7)/2 -> 0.75 | R7: =IF(_xlfn.BITAND(P7>0.4999, Q7>0.4999)=1,1,0) -> 1
A8: Enhancing Ethereum smart-contracts static analysis by computing a precise Control-Flow Graph of Ethereum bytecode | B8: https://www.sciencedirect.com/science/article/pii/S0164121223000481 | C8: PS | D8: =Info!$B$51 -> 0 | E8: =Info!$B$53 -> 1 | L8: 1 | M8: Journal Article | N8: Journal of Systems and Software | O8: 1 | P8: =(D8+E8)/2 -> 0.5 | Q8: =(O8+P8)/2 -> 0.75 | R8: =IF(_xlfn.BITAND(P8>0.4999, Q8>0.4999)=1,1,0) -> 1
A9: Smart contract vulnerability detection combined with multi-objective detection | B9: https://www.sciencedirect.com/science/article/abs/pii/S1389128622003437 | C9: PS | D9: =Info!$B$48 -> 1 | E9: =Info!$B$53 -> 1 | L9: 2 | M9: Journal Article | N9: Computer Networks | O9: 1 | P9: =(D9+E9)/2 -> 1 | Q9: =(O9+P9)/2 -> 1 | R9: =IF(_xlfn.BITAND(P9>0.4999, Q9>0.4999)=1,1,0) -> 1
A10: SolGuard: Preventing external call issues in smart contract-based multi-agent robotic systems | B10: https://www.sciencedirect.com/science/article/pii/S0020025521007994 | C10: PS | D10: =Info!$B$17 -> 0 | E10: 1 | L10: 2 | M10: Journal Article | N10: Information Sciences | O10: 1 | P10: =(D10+E10)/2 -> 0.5 | Q10: =(O10+P10)/2 -> 0.75 | R10: =IF(_xlfn.BITAND(P10>0.4999, Q10>0.4999)=1,1,0) -> 1
A11: SVScanner: Detecting smart contract vulnerabilities via deep semantic extraction | B11: https://www.sciencedirect.com/science/article/abs/pii/S2214212623000686 | C11: PS | D11: =Info!$B$50 -> 0.3 | E11: =Info!$B$53 -> 1 | L11: 2,3 | M11: Journal Article | N11: Journal of Information Security and Applications | O11: 1 | P11: =(D11+E11)/2 -> 0.65 | Q11: =(O11+P11)/2 -> 0.825 | R11: =IF(_xlfn.BITAND(P11>0.4999, Q11>0.4999)=1,1,0) -> 1
A12: Unveiling Vulnerable Smart Contracts: Toward Profiling Vulnerable Smart Contracts using Genetic Algorithm and Generating Benchmark Dataset | B12: https://www.sciencedirect.com/science/article/pii/S2096720923000465 | C12: PS | D12: =Info!$B$51 -> 0 | E12: =Info!$B$53 -> 1 | L12: 2 | M12: Arxiv Paper or Preprint | N12: Blockchain: Research and Applications | O12: 1 | P12: =(D12+E12)/2 -> 0.5 | Q12: 0.8 | R12: =IF(_xlfn.BITAND(P12>0.4999, Q12>0.4999)=1,1,0) -> 1
A13: Vulpedia: Detecting vulnerable ethereum smart contracts via abstracted vulnerability signatures | C13: PS | D13: =Info!$B$49 -> 0.6 | E13: =Info!$B$53 -> 1 | L13: 2,3 | M13: Journal Article | N13: Journal of Systems and Software | O13: 1 | P13: =(D13+E13)/2 -> 0.8 | Q13: =(O13+P13)/2 -> 0.9 | R13: =IF(_xlfn.BITAND(P13>0.4999, Q13>0.4999)=1,1,0) -> 1
A14: Unveiling Smart Contracts Vulnerabilities: Toward Profiling Smart Contracts Vulnerabilities using Enhanced Genetic Algorithm and Generating Benchmark Dataset | B14: https://www.sciencedirect.com/science/article/pii/S2096720924000666 | C14: PS | D14: 0 | E14: 1 | M14: Journal Article | N14: Blockchain: Research and Applications | O14: 1 | P14: =(D14+E14+F14+G14+H14+I14+J14)/2 -> 0.5 | Q14: =(O14+P14)/2 -> 0.75 | R14: =IF(_xlfn.BITAND(P14>0.4999, Q14>0.4999)=1,1,0) -> 1
A15: A comprehensive survey of smart contracts vulnerability detection tools: Techniques and methodologies | B15: https://www.sciencedirect.com/science/article/pii/S1084804525000396 | C15: SLR | D15: 1 | E15: 0.6 | F15: 0.6 | G15: 1 | H15: 1 | I15: 0 | J15: 1 | M15: Journal Article | N15: Journal of Network and Computer Applications | O15: 1 | P15: =(D15+E15+F15+G15+H15+I15+J15)/7 -> 0.74285714 | Q15: =(O15+P15)/2 -> 0.87142857 | R15: =IF(_xlfn.BITAND(P15>0.4999, Q15>0.4999)=1,1,0) -> 1
A16: Smart contracts vulnerability detection model based on adversarial multi-task learning | B16: https://www.sciencedirect.com/science/article/pii/S2214212623001394 | C16: PS | D16: =Info!$B$51 -> 0 | E16: =Info!$B$54 -> 0 | L16: 2 | M16: Journal Article | N16: Journal of Information Security and Applications | O16: 1 | P16: =(D16+E16)/2 -> 0 | Q16: =(O16+P16)/2 -> 0.5 | R16: =IF(_xlfn.BITAND(P16>0.4999, Q16>0.4999)=1,1,0) -> 0
A17: Vulnerable smart contract function locating based on Multi-Relational Nested Graph Convolutional Network | B17: https://www.sciencedirect.com/science/article/abs/pii/S016412122300170X | C17: PS | D17: =Info!$B$51 -> 0 | E17: =Info!$B$54 -> 0 | L17: 1 | M17: Journal Article | N17: Journal of Information Security and Applications | O17: 1 | P17: =(D17+E17)/2 -> 0 | Q17: =(O17+P17)/2 -> 0.5 | R17: =IF(_xlfn.BITAND(P17>0.4999, Q17>0.4999)=1,1,0) -> 0
A18: A formal verification approach for composite smart contracts security using FSM | B18: https://www.sciencedirect.com/science/article/pii/S1319157822003111 | C18: PS | D18: =Info!$B$50 -> 0.3 | E18: =Info!$B$54 -> 0 | L18: 1 | M18: Journal Article | N18: Journal of King Saud University - Computer and Information Sciences | O18: 1 | P18: =(D18+E18+F18+G18+H18+I18+J18)/6 -> 0.05 | Q18: =(O18+P18)/2 -> 0.525 | R18: =IF(_xlfn.BITAND(P18>0.4999, Q18>0.4999)=1,1,0) -> 0
A19: A survey of DeFi security: Challenges and opportunities | B19: https://www.sciencedirect.com/science/article/pii/S1319157822003792 | C19: Survey | D19: =Info!$B$16 -> 1 | E19: =Info!$B$20 -> 0.6 | F19: =Info!$B$25 -> 0.6 | G19: =Info!$B$32 -> 0 | H19: =Info!$B$37 -> 0 | I19: =Info!$B$40 -> 0 | J19: =Info!$B$43 -> 0.5 | L19: 1 | M19: Journal Article | N19: Journal of King Saud University - Computer and Information Sciences | O19: 1 | P19: =(D19+E19+F19+G19+H19+I19+J19)/6 -> 0.45 | Q19: =(O19+P19)/2 -> 0.725 | R19: =IF(_xlfn.BITAND(P19>0.4999, Q19>0.4999)=1,1,0) -> 0
A20: A survey on blockchain technology and its security | B20: https://www.sciencedirect.com/science/article/pii/S2096720922000070 | C20: Survey | D20: =Info!$B$17 -> 0 | E20: =Info!$B$20 -> 0.6 | F20: =Info!$B$26 -> 0.3 | G20: =Info!$B$31 -> 0.3 | H20: =Info!$B$36 -> 0.3 | I20: =Info!$B$40 -> 0 | J20: =Info!$B$43 -> 0.5 | L20: 1 | M20: Journal Article | N20: Blockchain: Research and Applications | O20: 1 | P20: =(D20+E20+F20+G20+H20+I20+J20)/6 -> 0.33333333 | Q20: =(O20+P20)/2 -> 0.66666667 | R20: =IF(_xlfn.BITAND(P20>0.4999, Q20>0.4999)=1,1,0) -> 0
A21: An empirical study on real bug fixes from solidity smart contract projects | B21: https://www.sciencedirect.com/science/article/pii/S0164121223001826 | C21: Survey | D21: =Info!$B$17 -> 0 | E21: =Info!$B$21 -> 0.3 | F21: =Info!$B$26 -> 0.3 | G21: =Info!$B$32 -> 0 | H21: =Info!$B$37 -> 0 | I21: =Info!$B$40 -> 0 | J21: =Info!$B$42 -> 1 | L21: 1 | M21: Journal Article | N21: Journal of Systems and Software | O21: 1 | P21: =(D21+E21+F21+G21+H21+I21+J21)/7 -> 0.22857143 | Q21: =(O21+P21)/2 -> 0.61428571 | R21: =IF(_xlfn.BITAND(P21>0.4999, Q21>0.4999)=1,1,0) -> 0
A22: Security challenges and defense approaches for blockchain-based services from a full-stack architecture perspective | B22: https://www.sciencedirect.com/science/article/pii/S2096720923000106 | D22: =Info!$B$17 -> 0 | E22: =Info!$B$21 -> 0.3 | F22: =Info!$B$26 -> 0.3 | G22: =Info!$B$32 -> 0 | H22: =Info!$B$37 -> 0 | I22: =Info!$B$40 -> 0 | J22: =Info!$B$42 -> 1 | P22: =(D22+E22+F22+G22+H22+I22+J22)/7 -> 0.22857143 | Q22: =(O22+P22)/2 -> 0.11428571 | R22: =IF(_xlfn.BITAND(P22>0.4999, Q22>0.4999)=1,1,0) -> 0
A23: ContractArmor: Attack Surface Generator for Smart Contracts | B23: https://www.sciencedirect.com/science/article/pii/S1877050923021634 | D23: =Info!$B$17 -> 0 | E23: =Info!$B$21 -> 0.3 | F23: =Info!$B$27 -> 0 | G23: =Info!$B$32 -> 0 | H23: =Info!$B$37 -> 0 | I23: =Info!$B$40 -> 0 | J23: =Info!$B$42 -> 1 | P23: =(D23+E23+F23+G23+H23+I23+J23)/7 -> 0.18571429 | Q23: =(O23+P23)/2 -> 0.092857143 | R23: =IF(_xlfn.BITAND(P23>0.4999, Q23>0.4999)=1,1,0) -> 0
A24: SRP: An Efficient Runtime Protection Framework for Blockchain-based Smart Contracts | B24: https://www.sciencedirect.com/science/article/pii/S1084804523000772 | D24: =Info!$B$17 -> 0 | E24: =Info!$B$21 -> 0.3 | F24: =Info!$B$27 -> 0 | G24: =Info!$B$32 -> 0 | H24: =Info!$B$37 -> 0 | I24: =Info!$B$40 -> 0 | J24: =Info!$B$42 -> 1 | P24: =(D24+E24+F24+G24+H24+I24+J24)/7 -> 0.18571429 | Q24: =(O24+P24)/2 -> 0.092857143 | R24: =IF(_xlfn.BITAND(P24>0.4999, Q24>0.4999)=1,1,0) -> 0
A25: AI and Blockchain-based source code vulnerability detection and prevention system for multiparty software development | B25: https://www.sciencedirect.com/science/article/pii/S0045790623000320 | D25: =Info!$B$17 -> 0 | E25: =Info!$B$21 -> 0.3 | F25: =Info!$B$27 -> 0 | G25: =Info!$B$32 -> 0 | H25: =Info!$B$37 -> 0 | I25: =Info!$B$40 -> 0 | J25: =Info!$B$42 -> 1 | P25: =(D25+E25+F25+G25+H25+I25+J25)/7 -> 0.18571429 | Q25: =(O25+P25)/2 -> 0.092857143 | R25: =IF(_xlfn.BITAND(P25>0.4999, Q25>0.4999)=1,1,0) -> 0
A26: Blockchain-based trusted accountability in the maintenance of medical imaging equipment | B26: https://www.sciencedirect.com/science/article/pii/S0957417423032207 | D26: =Info!$B$17 -> 0 | E26: =Info!$B$22 -> 0 | F26: =Info!$B$27 -> 0 | G26: =Info!$B$32 -> 0 | H26: =Info!$B$37 -> 0 | I26: =Info!$B$40 -> 0 | J26: =Info!$B$42 -> 1 | P26: =(D26+E26+F26+G26+H26+I26+J26)/7 -> 0.14285714 | Q26: =(O26+P26)/2 -> 0.071428571 | R26: =IF(_xlfn.BITAND(P26>0.4999, Q26>0.4999)=1,1,0) -> 0
A27: GAIN: Decentralized Privacy-Preserving Federated Learning | B27: https://www.sciencedirect.com/science/article/pii/S2214212623001990 | D27: =Info!$B$17 -> 0 | E27: =Info!$B$22 -> 0 | F27: =Info!$B$27 -> 0 | G27: =Info!$B$32 -> 0 | H27: =Info!$B$37 -> 0 | I27: =Info!$B$40 -> 0 | J27: =Info!$B$42 -> 1 | P27: =(D27+E27+F27+G27+H27+I27+J27)/7 -> 0.14285714 | Q27: =(O27+P27)/2 -> 0.071428571 | R27: =IF(_xlfn.BITAND(P27>0.4999, Q27>0.4999)=1,1,0) -> 0
A28: A smart contract and IPFS-based framework for secure electric vehicles synchronization at charging station | B28: https://www.sciencedirect.com/science/article/pii/S2352467724000018 | D28: =Info!$B$17 -> 0 | E28: =Info!$B$22 -> 0 | F28: =Info!$B$27 -> 0 | G28: =Info!$B$32 -> 0 | H28: =Info!$B$37 -> 0 | I28: =Info!$B$40 -> 0 | J28: =Info!$B$42 -> 1 | P28: =(D28+E28+F28+G28+H28+I28+J28)/7 -> 0.14285714 | Q28: =(O28+P28)/2 -> 0.071428571 | R28: =IF(_xlfn.BITAND(P28>0.4999, Q28>0.4999)=1,1,0) -> 0
A29: Applying Ethereum blockchain and IPFS to construct a multi-party used-car trading and management system | B29: https://www.sciencedirect.com/science/article/pii/S2405959523001650 | D29: =Info!$B$17 -> 0 | E29: =Info!$B$22 -> 0 | F29: =Info!$B$27 -> 0 | G29: =Info!$B$32 -> 0 | H29: =Info!$B$37 -> 0 | I29: =Info!$B$40 -> 0 | J29: =Info!$B$42 -> 1 | P29: =(D29+E29+F29+G29+H29+I29+J29)/7 -> 0.14285714 | Q29: =(O29+P29)/2 -> 0.071428571 | R29: =IF(_xlfn.BITAND(P29>0.4999, Q29>0.4999)=1,1,0) -> 0
A30: Mobile-Chain: Secure blockchain based decentralized authentication system for global roaming in mobility networks | B30: https://www.sciencedirect.com/science/article/pii/S0140366422004820 | D30: =Info!$B$17 -> 0 | E30: =Info!$B$22 -> 0 | F30: =Info!$B$27 -> 0 | G30: =Info!$B$32 -> 0 | H30: =Info!$B$37 -> 0 | I30: =Info!$B$40 -> 0 | J30: =Info!$B$42 -> 1 | P30: =(D30+E30+F30+G30+H30+I30+J30)/7 -> 0.14285714 | Q30: =(O30+P30)/2 -> 0.071428571 | R30: =IF(_xlfn.BITAND(P30>0.4999, Q30>0.4999)=1,1,0) -> 0
A31: Cryptographic evidence-based cybersecurity for smart healthcare systems | B31: https://www.sciencedirect.com/science/article/pii/S0020025523012185 | D31: =Info!$B$17 -> 0 | E31: =Info!$B$22 -> 0 | F31: =Info!$B$27 -> 0 | G31: =Info!$B$32 -> 0 | H31: =Info!$B$37 -> 0 | I31: =Info!$B$40 -> 0 | J31: =Info!$B$42 -> 1 | P31: =(D31+E31+F31+G31+H31+I31+J31)/7 -> 0.14285714 | Q31: =(O31+P31)/2 -> 0.071428571 | R31: =IF(_xlfn.BITAND(P31>0.4999, Q31>0.4999)=1,1,0) -> 0
A32: d-EMR: Secure and distributed Electronic Medical Record management | B32: https://www.sciencedirect.com/science/article/pii/S2667295222000538 | D32: =Info!$B$17 -> 0 | E32: =Info!$B$22 -> 0 | F32: =Info!$B$27 -> 0 | G32: =Info!$B$32 -> 0 | H32: =Info!$B$37 -> 0 | I32: =Info!$B$40 -> 0 | J32: =Info!$B$42 -> 1 | P32: =(D32+E32+F32+G32+H32+I32+J32)/7 -> 0.14285714 | Q32: =(O32+P32)/2 -> 0.071428571 | R32: =IF(_xlfn.BITAND(P32>0.4999, Q32>0.4999)=1,1,0) -> 0
A33: A smart contract-based robotic surgery authentication system for healthcare using 6G-Tactile Internet | B33: https://www.sciencedirect.com/science/article/pii/S1389128623005789 | D33: =Info!$B$17 -> 0 | E33: =Info!$B$22 -> 0 | F33: =Info!$B$27 -> 0 | G33: =Info!$B$32 -> 0 | H33: =Info!$B$37 -> 0 | I33: =Info!$B$40 -> 0 | J33: =Info!$B$42 -> 1 | P33: =(D33+E33+F33+G33+H33+I33+J33)/7 -> 0.14285714 | Q33: =(O33+P33)/2 -> 0.071428571 | R33: =IF(_xlfn.BITAND(P33>0.4999, Q33>0.4999)=1,1,0) -> 0
A34: GDPR compliance verification through a user-centric blockchain approach in multi-cloud environment | B34: https://www.sciencedirect.com/science/article/pii/S0045790623001714 | D34: =Info!$B$17 -> 0 | E34: =Info!$B$22 -> 0 | F34: =Info!$B$27 -> 0 | G34: =Info!$B$32 -> 0 | H34: =Info!$B$37 -> 0 | I34: =Info!$B$40 -> 0 | J34: =Info!$B$42 -> 1 | P34: =(D34+E34+F34+G34+H34+I34+J34)/7 -> 0.14285714 | Q34: =(O34+P34)/2 -> 0.071428571 | R34: =IF(_xlfn.BITAND(P34>0.4999, Q34>0.4999)=1,1,0) -> 0
A35: ChainSure: Agent free insurance system using blockchain for healthcare 4.0 | B35: https://www.sciencedirect.com/science/article/pii/S2667305323000029 | D35: =Info!$B$17 -> 0 | E35: =Info!$B$22 -> 0 | F35: =Info!$B$27 -> 0 | G35: =Info!$B$32 -> 0 | H35: =Info!$B$37 -> 0 | I35: =Info!$B$40 -> 0 | J35: =Info!$B$42 -> 1 | P35: =(D35+E35+F35+G35+H35+I35+J35)/7 -> 0.14285714 | Q35: =(O35+P35)/2 -> 0.071428571 | R35: =IF(_xlfn.BITAND(P35>0.4999, Q35>0.4999)=1,1,0) -> 0
A36: The Decentralized Smart Contract Certificate System Utilizing Ethereum Blockchain Technology | B36: https://www.sciencedirect.com/science/article/pii/S1877050923020252 | D36: =Info!$B$17 -> 0 | E36: =Info!$B$22 -> 0 | F36: =Info!$B$27 -> 0 | G36: =Info!$B$32 -> 0 | H36: =Info!$B$37 -> 0 | I36: =Info!$B$40 -> 0 | J36: =Info!$B$42 -> 1 | P36: =(D36+E36+F36+G36+H36+I36+J36)/7 -> 0.14285714 | Q36: =(O36+P36)/2 -> 0.071428571 | R36: =IF(_xlfn.BITAND(P36>0.4999, Q36>0.4999)=1,1,0) -> 0
A37: The real estate time-stamping and registration system based on Ethereum blockchain | B37: https://www.sciencedirect.com/science/article/pii/S2096720923000507 | D37: =Info!$B$17 -> 0 | E37: =Info!$B$22 -> 0 | F37: =Info!$B$27 -> 0 | G37: =Info!$B$32 -> 0 | H37: =Info!$B$37 -> 0 | I37: =Info!$B$40 -> 0 | J37: =Info!$B$42 -> 1 | P37: =(D37+E37+F37+G37+H37+I37+J37)/7 -> 0.14285714 | Q37: =(O37+P37)/2 -> 0.071428571 | R37: =IF(_xlfn.BITAND(P37>0.4999, Q37>0.4999)=1,1,0) -> 0
... A64: Blockchain technology in the AEC industry: Scientometric analysis of research activities | B64: https://www.sciencedirect.com/science/article/pii/S235271022300788X | D64: =Info!$B$17 -> 0 | E64: =Info!$B$22 -> 0 | F64: =Info!$B$27 -> 0 | G64: =Info!$B$32 -> 0 | H64: =Info!$B$37 -> 0 | I64: =Info!$B$40 -> 0 | J64: =Info!$B$42 -> 1 | P64: =(D64+E64+F64+G64+H64+I64+J64)/7 -> 0.14285714 | Q64: =(O64+P64)/2 -> 0.071428571 | R64: =IF(_xlfn.BITAND(P64>0.4999, Q64>0.4999)=1,1,0) -> 0
A65: Smart contract vulnerability detection based on a semantic code structure and a self-designed neural network | B65: https://www.sciencedirect.com/science/article/pii/S0045790623001908 | J65: =Info!$B$42 -> 1 | P65: =(D65+E65+F65+G65+H65+I65+J65)/7 -> 0.14285714 | Q65: =(O65+P65)/2 -> 0.071428571 | R65: =IF(_xlfn.BITAND(P65>0.4999, Q65>0.4999)=1,1,0) -> 0
A66: A novel extended multimodal AI framework towards vulnerability detection in smart contracts | B66: https://www.sciencedirect.com/science/article/pii/S0020025523004565 | J66: =Info!$B$42 -> 1 | P66: =(D66+E66+F66+G66+H66+I66+J66)/7 -> 0.14285714 | Q66: =(O66+P66)/2 -> 0.071428571 | R66: =IF(_xlfn.BITAND(P66>0.4999, Q66>0.4999)=1,1,0) -> 0
A67: Automation and smart materials in detecting smart contracts vulnerabilities in Blockchain using deep learning | B67: https://www.sciencedirect.com/science/article/pii/S2214785321030273 | J67: =Info!$B$42 -> 1 | P67: =(D67+E67+F67+G67+H67+I67+J67)/7 -> 0.14285714 | Q67: =(O67+P67)/2 -> 0.071428571 | R67: =IF(_xlfn.BITAND(P67>0.4999, Q67>0.4999)=1,1,0) -> 0
A68: ASSBert: Active and semi-supervised bert for smart contract vulnerability detection | B68: https://www.sciencedirect.com/science/article/pii/S221421262300008X | J68: =Info!$B$42 -> 1 | P68: =(D68+E68+F68+G68+H68+I68+J68)/7 -> 0.14285714 | Q68: =(O68+P68)/2 -> 0.071428571 | R68: =IF(_xlfn.BITAND(P68>0.4999, Q68>0.4999)=1,1,0) -> 0
A69: EDIT: A data inspection tool for smart contracts temporal behavior modeling and prediction | B69: https://www.sciencedirect.com/science/article/pii/S0167739X24000013 | J69: =Info!$B$42 -> 1 | P69: =(D69+E69+F69+G69+H69+I69+J69)/7 -> 0.14285714 | Q69: =(O69+P69)/2 -> 0.071428571 | R69: =IF(_xlfn.BITAND(P69>0.4999, Q69>0.4999)=1,1,0) -> 0
A70: TaintGuard: Preventing implicit privilege leakage in smart contract based on taint tracking at abstract syntax tree level | B70: https://www.sciencedirect.com/science/article/pii/S1383762123001042 | J70: =Info!$B$42 -> 1 | K70: 4 | P70: =(D70+E70+F70+G70+H70+I70+J70)/7 -> 0.14285714 | Q70: =(O70+P70)/2 -> 0.071428571 | R70: =IF(_xlfn.BITAND(P70>0.4999, Q70>0.4999)=1,1,0) -> 0
A71: An empirical study on the complexity, security and maintainability of Ethereum-based decentralized applications (DApps) | B71: https://www.sciencedirect.com/science/article/pii/S2096720922000616 | J71: =Info!$B$42 -> 1 | P71: =(D71+E71+F71+G71+H71+I71+J71)/7 -> 0.14285714 | Q71: =(O71+P71)/2 -> 0.071428571 | R71: =IF(_xlfn.BITAND(P71>0.4999, Q71>0.4999)=1,1,0) -> 0
A72: Chapter 8 - Formal verification and code generation for solidity smart contracts | B72: https://www.sciencedirect.com/science/article/pii/B9780323961462000280 | J72: =Info!$B$42 -> 1 | K72: 4 | P72: =(D72+E72+F72+G72+H72+I72+J72)/7 -> 0.14285714 | Q72: =(O72+P72)/2 -> 0.071428571 | R72: =IF(_xlfn.BITAND(P72>0.4999, Q72>0.4999)=1,1,0) -> 0
A73: MedUAV: Drone-based Emergency Medical Supply System using Decentralized Autonomous Organization (DAO) | B73: https://www.sciencedirect.com/science/article/pii/S1877050923021336 | J73: =Info!$B$42 -> 1 | P73: =(D73+E73+F73+G73+H73+I73+J73)/7 -> 0.14285714 | Q73: =(O73+P73)/2 -> 0.071428571 | R73: =IF(_xlfn.BITAND(P73>0.4999, Q73>0.4999)=1,1,0) -> 0
A74: Smart contract-based integrity audit method for IoT | B74: https://www.sciencedirect.com/science/article/pii/S0020025523009982 | J74: =Info!$B$42 -> 1 | P74: =(D74+E74+F74+G74+H74+I74+J74)/7 -> 0.14285714 | Q74: =(O74+P74)/2 -> 0.071428571 | R74: =IF(_xlfn.BITAND(P74>0.4999, Q74>0.4999)=1,1,0) -> 0
A75: A blockchain-based approach to the challenges of EU’s environmental policy compliance in aquaculture: From traceability to fraud prevention | B75: https://www.sciencedirect.com/science/article/pii/S0308597X23004256 | J75: =Info!$B$42 -> 1 | P75: =(D75+E75+F75+G75+H75+I75+J75)/7 -> 0.14285714 | Q75: =(O75+P75)/2 -> 0.071428571 | R75: =IF(_xlfn.BITAND(P75>0.4999, Q75>0.4999)=1,1,0) -> 0
A76: An efficient chain code for access control in hyper ledger fabric healthcare system | B76: https://www.sciencedirect.com/science/article/pii/S2772671123000992 | J76: =Info!$B$42 -> 1 | P76: =(D76+E76+F76+G76+H76+I76+J76)/7 -> 0.14285714 | Q76: =(O76+P76)/2 -> 0.071428571 | R76: =IF(_xlfn.BITAND(P76>0.4999, Q76>0.4999)=1,1,0) -> 0
A77: Chapter 17 - An in-depth look at blockchain technology: Architecture and security concerns | B77: https://www.sciencedirect.com/science/article/pii/B9780323961462000231 | J77: =Info!$B$42 -> 1 | P77: =(D77+E77+F77+G77+H77+I77+J77)/7 -> 0.14285714 | Q77: =(O77+P77)/2 -> 0.071428571 | R77: =IF(_xlfn.BITAND(P77>0.4999, Q77>0.4999)=1,1,0) -> 0
A78: Optimal and secure peer-to-peer carbon emission trading: A game theory informed framework on blockchain | B78: https://www.sciencedirect.com/science/article/pii/S0098135423003484 | J78: =Info!$B$42 -> 1 | P78: =(D78+E78+F78+G78+H78+I78+J78)/7 -> 0.14285714 | Q78: =(O78+P78)/2 -> 0.071428571 | R78: =IF(_xlfn.BITAND(P78>0.4999, Q78>0.4999)=1,1,0) -> 0
A79: Chapter Six - Bayesian network-based quality assessment of blockchain smart contracts | B79: https://www.sciencedirect.com/science/article/pii/S0065245823000517 | J79: =Info!$B$42 -> 1 | P79: =(D79+E79+F79+G79+H79+I79+J79)/7 -> 0.14285714 | Q79: =(O79+P79)/2 -> 0.071428571 | R79: =IF(_xlfn.BITAND(P79>0.4999, Q79>0.4999)=1,1,0) -> 0
A80: Increasing the security and traceability of biological samples in biobanks by blockchain technology | B80: https://www.sciencedirect.com/science/article/pii/S0169260723000469 | J80: =Info!$B$42 -> 1 | P80: =(D80+E80+F80+G80+H80+I80+J80)/7 -> 0.14285714 | Q80: =(O80+P80)/2 -> 0.071428571 | R80: =IF(_xlfn.BITAND(P80>0.4999, Q80>0.4999)=1,1,0) -> 0
A81: Health chain-block chain based electronic healthcare record system with access and permission management | B81: https://www.sciencedirect.com/science/article/pii/S2665917423002398 | J81: =Info!$B$42 -> 1 | P81: =(D81+E81+F81+G81+H81+I81+J81)/7 -> 0.14285714 | Q81: =(O81+P81)/2 -> 0.071428571 | R81: =IF(_xlfn.BITAND(P81>0.4999, Q81>0.4999)=1,1,0) -> 0
A82: METAseen: Analyzing network traffic and privacy policies in Web 3.0 based Metaverse | B82: https://www.sciencedirect.com/science/article/pii/S2352864823001694 | J82: =Info!$B$42 -> 1 | P82: =(D82+E82+F82+G82+H82+I82+J82)/7 -> 0.14285714 | Q82: =(O82+P82)/2 -> 0.071428571 | R82: =IF(_xlfn.BITAND(P82>0.4999, Q82>0.4999)=1,1,0) -> 0
A83: PharmaChain: Blockchain-based drug supply chain provenance verification system | B83: https://www.sciencedirect.com/science/article/pii/S2405844023051654 | J83: =Info!$B$42 -> 1 | P83: =(D83+E83+F83+G83+H83+I83+J83)/7 -> 0.14285714 | Q83: =(O83+P83)/2 -> 0.071428571 | R83: =IF(_xlfn.BITAND(P83>0.4999, Q83>0.4999)=1,1,0) -> 0
A84: Using NFTs for ownership management of digital twins and for proof of delivery of their physical assets | B84: https://www.sciencedirect.com/science/article/pii/S0167739X23001280 | J84: =Info!$B$42 -> 1 | P84: =(D84+E84+F84+G84+H84+I84+J84)/7 -> 0.14285714 | Q84: =(O84+P84)/2 -> 0.071428571 | R84: =IF(_xlfn.BITAND(P84>0.4999, Q84>0.4999)=1,1,0) -> 0
... A309: Study on the new implementation mode of cross-docking based on blockchain technology | B309: https://www.sciencedirect.com/science/article/pii/S0360835223002735 | J309: =Info!$B$42 -> 1 | P309: =(D309+E309+F309+G309+H309+I309+J309)/7 -> 0.14285714 | Q309: =(O309+P309)/2 -> 0.071428571 | R309: =IF(_xlfn.BITAND(P309>0.4999, Q309>0.4999)=1,1,0) -> 0
A310: Deep learning-based malicious smart contract detection scheme for internet of things environment | B310: https://www.sciencedirect.com/science/article/pii/S004579062100519X | D310: =Info!$B$17 -> 0 | E310: =Info!$B$22 -> 0 | F310: =Info!$B$27 -> 0 | G310: =Info!$B$32 -> 0 | H310: =Info!$B$37 -> 0 | I310: =Info!$B$40 -> 0 | J310: =Info!$B$43 -> 0.5 | P310: =(D310+E310+F310+G310+H310+I310+J310)/7 -> 0.071428571 | Q310: =(O310+P310)/2 -> 0.035714286 | R310: =IF(_xlfn.BITAND(P310>0.4999, Q310>0.4999)=1,1,0) -> 0
A311: A secure double spectrum auction scheme | B311: https://www.sciencedirect.com/science/article/pii/S2352864822002759 | D311: =Info!$B$17 -> 0 | E311: =Info!$B$22 -> 0 | F311: =Info!$B$27 -> 0 | G311: =Info!$B$32 -> 0 | H311: =Info!$B$37 -> 0 | I311: =Info!$B$40 -> 0 | J311: =Info!$B$43 -> 0.5 | P311: =(D311+E311+F311+G311+H311+I311+J311)/7 -> 0.071428571 | Q311: =(O311+P311)/2 -> 0.035714286 | R311: =IF(_xlfn.BITAND(P311>0.4999, Q311>0.4999)=1,1,0) -> 0
A312: Blockchain-based Supply Chain Traceability for COVID-19 personal protective equipment | B312: https://www.sciencedirect.com/science/article/pii/S0360835222000651 | D312: =Info!$B$17 -> 0 | E312: =Info!$B$22 -> 0 | F312: =Info!$B$27 -> 0 | G312: =Info!$B$32 -> 0 | H312: =Info!$B$37 -> 0 | I312: =Info!$B$40 -> 0 | J312: =Info!$B$43 -> 0.5 | P312: =(D312+E312+F312+G312+H312+I312+J312)/7 -> 0.071428571 | Q312: =(O312+P312)/2 -> 0.035714286 | R312: =IF(_xlfn.BITAND(P312>0.4999, Q312>0.4999)=1,1,0) -> 0
A313: A user-centric privacy-preserving authentication protocol for IoT-AmI environments | B313: https://www.sciencedirect.com/science/article/pii/S014036642200370X | D313: =Info!$B$17 -> 0 | E313: =Info!$B$22 -> 0 | F313: =Info!$B$27 -> 0 | G313: =Info!$B$32 -> 0 | H313: =Info!$B$37 -> 0 | I313: =Info!$B$40 -> 0 | J313: =Info!$B$43 -> 0.5 | P313: =(D313+E313+F313+G313+H313+I313+J313)/7 -> 0.071428571 | Q313: =(O313+P313)/2 -> 0.035714286 | R313: =IF(_xlfn.BITAND(P313>0.4999, Q313>0.4999)=1,1,0) -> 0
A314: CCGIR: Information retrieval-based code comment generation method for smart contracts | B314: https://www.sciencedirect.com/science/article/pii/S0950705121010406 | D314: =Info!$B$17 -> 0 | E314: =Info!$B$22 -> 0 | F314: =Info!$B$27 -> 0 | G314: =Info!$B$32 -> 0 | H314: =Info!$B$37 -> 0 | I314: =Info!$B$40 -> 0 | J314: =Info!$B$43 -> 0.5 | P314: =(D314+E314+F314+G314+H314+I314+J314)/7 -> 0.071428571 | Q314: =(O314+P314)/2 -> 0.035714286 | R314: =IF(_xlfn.BITAND(P314>0.4999, Q314>0.4999)=1,1,0) -> 0
A315: Blockchain-based secure delivery of medical supplies using drones | B315: https://www.sciencedirect.com/science/article/pii/S1389128621005661 | D315: =Info!$B$17 -> 0 | E315: =Info!$B$22 -> 0 | F315: =Info!$B$27 -> 0 | G315: =Info!$B$32 -> 0 | H315: =Info!$B$37 -> 0 | I315: =Info!$B$40 -> 0 | J315: =Info!$B$43 -> 0.5 | P315: =(D315+E315+F315+G315+H315+I315+J315)/7 -> 0.071428571 | Q315: =(O315+P315)/2 -> 0.035714286 | R315: =IF(_xlfn.BITAND(P315>0.4999, Q315>0.4999)=1,1,0) -> 0
A316: Design and implementation of a New Blockchain-based digital health passport: A Moroccan case study | B316: https://www.sciencedirect.com/science/article/pii/S2352914822002623 | D316: =Info!$B$17 -> 0 | E316: =Info!$B$22 -> 0 | F316: =Info!$B$27 -> 0 | G316: =Info!$B$32 -> 0 | H316: =Info!$B$37 -> 0 | I316: =Info!$B$40 -> 0 | J316: =Info!$B$43 -> 0.5 | P316: =(D316+E316+F316+G316+H316+I316+J316)/7 -> 0.071428571 | Q316: =(O316+P316)/2 -> 0.035714286 | R316: =IF(_xlfn.BITAND(P316>0.4999, Q316>0.4999)=1,1,0) -> 0
A317: Blockchain-enabled fraud discovery through abnormal smart contract detection on Ethereum | B317: https://www.sciencedirect.com/science/article/pii/S0167739X21003319 | D317: =Info!$B$17 -> 0 | E317: =Info!$B$22 -> 0 | F317: =Info!$B$27 -> 0 | G317: =Info!$B$32 -> 0 | H317: =Info!$B$37 -> 0 | I317: =Info!$B$40 -> 0 | J317: =Info!$B$43 -> 0.5 | P317: =(D317+E317+F317+G317+H317+I317+J317)/7 -> 0.071428571 | Q317: =(O317+P317)/2 -> 0.035714286 | R317: =IF(_xlfn.BITAND(P317>0.4999, Q317>0.4999)=1,1,0) -> 0
A318: K-nearest neighbour-based smart contract for internet of medical things security using blockchain | B318: https://www.sciencedirect.com/science/article/pii/S0045790622003792 | D318: =Info!$B$17 -> 0 | E318: =Info!$B$22 -> 0 | F318: =Info!$B$27 -> 0 | G318: =Info!$B$32 -> 0 | H318: =Info!$B$37 -> 0 | I318: =Info!$B$40 -> 0 | J318: =Info!$B$43 -> 0.5 | P318: =(D318+E318+F318+G318+H318+I318+J318)/7 -> 0.071428571 | Q318: =(O318+P318)/2 -> 0.035714286 | R318: =IF(_xlfn.BITAND(P318>0.4999, Q318>0.4999)=1,1,0) -> 0
A319: DVTChain: A blockchain-based decentralized mechanism to ensure the security of digital voting system voting system | B319: https://www.sciencedirect.com/science/article/pii/S1319157822002221 | D319: =Info!$B$17 -> 0 | E319: =Info!$B$22 -> 0 | F319: =Info!$B$27 -> 0 | G319: =Info!$B$32 -> 0 | H319: =Info!$B$37 -> 0 | I319: =Info!$B$40 -> 0 | J319: =Info!$B$43 -> 0.5 | P319: =(D319+E319+F319+G319+H319+I319+J319)/7 -> 0.071428571 | Q319: =(O319+P319)/2 -> 0.035714286 | R319: =IF(_xlfn.BITAND(P319>0.4999, Q319>0.4999)=1,1,0) -> 0
A320: Smart contracts in energy systems: A systematic review of fundamental approaches and implementations | B320: https://www.sciencedirect.com/science/article/pii/S1364032121012764 | D320: =Info!$B$17 -> 0 | E320: =Info!$B$22 -> 0 | F320: =Info!$B$27 -> 0 | G320: =Info!$B$32 -> 0 | H320: =Info!$B$37 -> 0 | I320: =Info!$B$40 -> 0 | J320: =Info!$B$43 -> 0.5 | P320: =(D320+E320+F320+G320+H320+I320+J320)/7 -> 0.071428571 | Q320: =(O320+P320)/2 -> 0.035714286 | R320: =IF(_xlfn.BITAND(P320>0.4999, Q320>0.4999)=1,1,0) -> 0
A321: Blockchain in oil and gas industry: Applications, challenges, and future trends | B321: https://www.sciencedirect.com/science/article/pii/S0160791X22000823 | D321: =Info!$B$17 -> 0 | E321: =Info!$B$22 -> 0 | F321: =Info!$B$27 -> 0 | G321: =Info!$B$32 -> 0 | H321: =Info!$B$37 -> 0 | I321: =Info!$B$40 -> 0 | J321: =Info!$B$43 -> 0.5 | P321: =(D321+E321+F321+G321+H321+I321+J321)/7 -> 0.071428571 | Q321: =(O321+P321)/2 -> 0.035714286 | R321: =IF(_xlfn.BITAND(P321>0.4999, Q321>0.4999)=1,1,0) -> 0
A322: A lightweight approach to smart contracts supporting safety, security, and privacy | B322: https://www.sciencedirect.com/science/article/pii/S2352220822000256 | J322: =Info!$B$43 -> 0.5 | P322: =(D322+E322+F322+G322+H322+I322+J322)/7 -> 0.071428571 | Q322: =(O322+P322)/2 -> 0.035714286 | R322: =IF(_xlfn.BITAND(P322>0.4999, Q322>0.4999)=1,1,0) -> 0
A323: HBFL: A hierarchical blockchain-based federated learning framework for collaborative IoT intrusion detection | B323: https://www.sciencedirect.com/science/article/pii/S0045790622005961 | J323: =Info!$B$43 -> 0.5 | P323: =(D323+E323+F323+G323+H323+I323+J323)/7 -> 0.071428571 | Q323: =(O323+P323)/2 -> 0.035714286 | R323: =IF(_xlfn.BITAND(P323>0.4999, Q323>0.4999)=1,1,0) -> 0
A324: Blockchain-based AMI framework for data security and privacy protection | B324: https://www.sciencedirect.com/science/article/pii/S2352467722001060 | J324: =Info!$B$43 -> 0.5 | P324: =(D324+E324+F324+G324+H324+I324+J324)/7 -> 0.071428571 | Q324: =(O324+P324)/2 -> 0.035714286 | R324: =IF(_xlfn.BITAND(P324>0.4999, Q324>0.4999)=1,1,0) -> 0
A325: A patent registration and trading system based on blockchain | B325: https://www.sciencedirect.com/science/article/pii/S0957417422005000 | J325: =Info!$B$43 -> 0.5 | P325: =(D325+E325+F325+G325+H325+I325+J325)/7 -> 0.071428571 | Q325: =(O325+P325)/2 -> 0.035714286 | R325: =IF(_xlfn.BITAND(P325>0.4999, Q325>0.4999)=1,1,0) -> 0
A326: Applying blockchain-based method to smart contract classification for CPS applications | B326: https://www.sciencedirect.com/science/article/pii/S2352864822001742 | J326: =Info!$B$43 -> 0.5 | P326: =(D326+E326+F326+G326+H326+I326+J326)/7 -> 0.071428571 | Q326: =(O326+P326)/2 -> 0.035714286 | R326: =IF(_xlfn.BITAND(P326>0.4999, Q326>0.4999)=1,1,0) -> 0
A327: The Role of Smart Contract Blockchain in 6G Wireless Communication System | B327: https://www.sciencedirect.com/science/article/pii/S1877050922020762 | J327: =Info!$B$43 -> 0.5 | P327: =(D327+E327+F327+G327+H327+I327+J327)/7 -> 0.071428571 | Q327: =(O327+P327)/2 -> 0.035714286 | R327: =IF(_xlfn.BITAND(P327>0.4999, Q327>0.4999)=1,1,0) -> 0
A328: Secure and privacy-preserving crowdsensing using smart contracts: Issues and solutions | B328: https://www.sciencedirect.com/science/article/pii/S1574013721000873 | J328: =Info!$B$43 -> 0.5 | P328: =(D328+E328+F328+G328+H328+I328+J328)/7 -> 0.071428571 | Q328: =(O328+P328)/2 -> 0.035714286 | R328: =IF(_xlfn.BITAND(P328>0.4999, Q328>0.4999)=1,1,0) -> 0
A329: Providing scalability and privacy for smart contract in the healthcare system | B329: https://www.sciencedirect.com/science/article/pii/S0030402622013353 | J329: =Info!$B$43 -> 0.5 | P329: =(D329+E329+F329+G329+H329+I329+J329)/7 -> 0.071428571 | Q329: =(O329+P329)/2 -> 0.035714286 | R329: =IF(_xlfn.BITAND(P329>0.4999, Q329>0.4999)=1,1,0) -> 0
A330: Chapter 29 - A comparative study on IoT-aided smart grids using blockchain platform | B330: https://www.sciencedirect.com/science/article/pii/B978012824054000006X | J330: =Info!$B$43 -> 0.5 | P330: =(D330+E330+F330+G330+H330+I330+J330)/7 -> 0.071428571 | Q330: =(O330+P330)/2 -> 0.035714286 | R330: =IF(_xlfn.BITAND(P330>0.4999, Q330>0.4999)=1,1,0) -> 0
A331: Blockchain verification and validation: Techniques, challenges, and research directions | B331: https://www.sciencedirect.com/science/article/pii/S1574013722000314 | J331: =Info!$B$43 -> 0.5 | P331: =(D331+E331+F331+G331+H331+I331+J331)/7 -> 0.071428571 | Q331: =(O331+P331)/2 -> 0.035714286 | R331: =IF(_xlfn.BITAND(P331>0.4999, Q331>0.4999)=1,1,0) -> 0
A332: Elliptic curve threshold signature scheme for blockchain | B332: https://www.sciencedirect.com/science/article/pii/S2214212622001909 | J332: =Info!$B$43 -> 0.5 | P332: =(D332+E332+F332+G332+H332+I332+J332)/7 -> 0.071428571 | Q332: =(O332+P332)/2 -> 0.035714286 | R332: =IF(_xlfn.BITAND(P332>0.4999, Q332>0.4999)=1,1,0) -> 0
A333: Chatbot for construction firms using scalable blockchain network | B333: https://www.sciencedirect.com/science/article/pii/S0926580522002631 | J333: =Info!$B$43 -> 0.5 | P333: =(D333+E333+F333+G333+H333+I333+J333)/7 -> 0.071428571 | Q333: =(O333+P333)/2 -> 0.035714286 | R333: =IF(_xlfn.BITAND(P333>0.4999, Q333>0.4999)=1,1,0) -> 0
... A491: A peer-to-peer market for utility exchanges in Eco-Industrial Parks using automated negotiations | B491: https://www.sciencedirect.com/science/article/pii/S0957417421015256 | J491: =Info!$B$43 -> 0.5 | P491: =(D491+E491+F491+G491+H491+I491+J491)/7 -> 0.071428571 | Q491: =(O491+P491)/2 -> 0.035714286 | R491: =IF(_xlfn.BITAND(P491>0.4999, Q491>0.4999)=1,1,0) -> 0
A492: A security type verifier for smart contracts | B492: https://www.sciencedirect.com/science/article/pii/S016740482100167X | D492: =Info!$B$17 -> 0 | E492: =Info!$B$21 -> 0.3 | F492: =Info!$B$27 -> 0 | G492: =Info!$B$32 -> 0 | H492: =Info!$B$37 -> 0 | I492: =Info!$B$40 -> 0 | J492: =Info!$B$44 -> 0 | P492: =(D492+E492+F492+G492+H492+I492+J492)/7 -> 0.042857143 | Q492: =(O492+P492)/2 -> 0.021428571 | R492: =IF(_xlfn.BITAND(P492>0.4999, Q492>0.4999)=1,1,0) -> 0
A493: EtherClue: Digital investigation of attacks on Ethereum smart contracts | B493: https://www.sciencedirect.com/science/article/pii/S2096720921000233 | D493: =Info!$B$17 -> 0 | E493: =Info!$B$21 -> 0.3 | F493: =Info!$B$27 -> 0 | G493: =Info!$B$32 -> 0 | H493: =Info!$B$37 -> 0 | I493: =Info!$B$40 -> 0 | J493: =Info!$B$44 -> 0 | P493: =(D493+E493+F493+G493+H493+I493+J493)/7 -> 0.042857143 | Q493: =(O493+P493)/2 -> 0.021428571 | R493: =IF(_xlfn.BITAND(P493>0.4999, Q493>0.4999)=1,1,0) -> 0
A494: A blockchain-based access control and intrusion detection framework for satellite communication systems | B494: https://www.sciencedirect.com/science/article/pii/S0140366421001250 | D494: =Info!$B$17 -> 0 | E494: =Info!$B$22 -> 0 | F494: =Info!$B$27 -> 0 | G494: =Info!$B$32 -> 0 | H494: =Info!$B$37 -> 0 | I494: =Info!$B$40 -> 0 | J494: =Info!$B$44 -> 0 | P494: =(D494+E494+F494+G494+H494+I494+J494)/7 -> 0 | Q494: =(O494+P494)/2 -> 0 | R494: =IF(_xlfn.BITAND(P494>0.4999, Q494>0.4999)=1,1,0) -> 0
A495: ConGradetect: Blockchain-based detection of code and identity privacy vulnerabilities in crowdsourcing | B495: https://www.sciencedirect.com/science/article/pii/S1383762120301752 | D495: =Info!$B$17 -> 0 | E495: =Info!$B$22 -> 0 | F495: =Info!$B$27 -> 0 | G495: =Info!$B$32 -> 0 | H495: =Info!$B$37 -> 0 | I495: =Info!$B$40 -> 0 | J495: =Info!$B$44 -> 0 | P495: =(D495+E495+F495+G495+H495+I495+J495)/7 -> 0 | Q495: =(O495+P495)/2 -> 0 | R495: =IF(_xlfn.BITAND(P495>0.4999, Q495>0.4999)=1,1,0) -> 0
A496: Privacy-preserving in smart contracts using blockchain and artificial intelligence for cyber risk measurements | B496: https://www.sciencedirect.com/science/article/pii/S2214212621000028 | D496: =Info!$B$17 -> 0 | E496: =Info!$B$22 -> 0 | F496: =Info!$B$27 -> 0 | G496: =Info!$B$32 -> 0 | H496: =Info!$B$37 -> 0 | I496: =Info!$B$40 -> 0 | J496: =Info!$B$44 -> 0 | P496: =(D496+E496+F496+G496+H496+I496+J496)/7 -> 0 | Q496: =(O496+P496)/2 -> 0 | R496: =IF(_xlfn.BITAND(P496>0.4999, Q496>0.4999)=1,1,0) -> 0
A497: Blockchain based solutions to secure IoT: Background, integration trends and a way forward | B497: https://www.sciencedirect.com/science/article/pii/S1084804521000758 | D497: =Info!$B$17 -> 0 | E497: =Info!$B$22 -> 0 | F497: =Info!$B$27 -> 0 | G497: =Info!$B$32 -> 0 | H497: =Info!$B$37 -> 0 | I497: =Info!$B$40 -> 0 | J497: =Info!$B$44 -> 0 | P497: =(D497+E497+F497+G497+H497+I497+J497)/7 -> 0 | Q497: =(O497+P497)/2 -> 0 | R497: =IF(_xlfn.BITAND(P497>0.4999, Q497>0.4999)=1,1,0) -> 0
A498: The Challenges of IoT Addressing Security, Ethics, Privacy, and Laws | B498: https://www.sciencedirect.com/science/article/pii/S2542660521000640 | D498: =Info!$B$17 -> 0 | E498: =Info!$B$22 -> 0 | F498: =Info!$B$27 -> 0 | G498: =Info!$B$32 -> 0 | H498: =Info!$B$37 -> 0 | I498: =Info!$B$40 -> 0 | J498: =Info!$B$44 -> 0 | P498: =(D498+E498+F498+G498+H498+I498+J498)/7 -> 0 | Q498: =(O498+P498)/2 -> 0 | R498: =IF(_xlfn.BITAND(P498>0.4999, Q498>0.4999)=1,1,0) -> 0
A499: A secure spectrum auction scheme without the trusted party based on the smart contract | B499: https://www.sciencedirect.com/science/article/pii/S235286481930330X | D499: =Info!$B$17 -> 0 | E499: =Info!$B$22 -> 0 | F499: =Info!$B$27 -> 0 | G499: =Info!$B$32 -> 0 | H499: =Info!$B$37 -> 0 | I499: =Info!$B$40 -> 0 | J499: =Info!$B$44 -> 0 | P499: =(D499+E499+F499+G499+H499+I499+J499)/7 -> 0 | Q499: =(O499+P499)/2 -> 0 | R499: =IF(_xlfn.BITAND(P499>0.4999, Q499>0.4999)=1,1,0) -> 0
A500: Applications of distributed ledger technology (DLT) and Blockchain-enabled smart contracts in construction | B500: https://www.sciencedirect.com/science/article/pii/S0926580521004064 | D500: =Info!$B$17 -> 0 | E500: =Info!$B$22 -> 0 | F500: =Info!$B$27 -> 0 | G500: =Info!$B$32 -> 0 | H500: =Info!$B$37 -> 0 | I500: =Info!$B$40 -> 0 | J500: =Info!$B$44 -> 0 | P500: =(D500+E500+F500+G500+H500+I500+J500)/7 -> 0 | Q500: =(O500+P500)/2 -> 0 | R500: =IF(_xlfn.BITAND(P500>0.4999, Q500>0.4999)=1,1,0) -> 0
A501: A survey on smart contract vulnerabilities: Data sources, detection and repair | B501: https://www.sciencedirect.com/science/article/abs/pii/S0950584923000757 | P501: =(D501+E501+F501+G501+H501+I501+J501)/7 -> 0 | Q501: =(O501+P501)/2 -> 0 | R501: =IF(_xlfn.BITAND(P501>0.4999, Q501>0.4999)=1,1,0) -> 0
A502: Optimizing smart contract vulnerability detection via multi-modality code and entropy embedding | P502: =(D502+E502+F502+G502+H502+I502+J502)/7 -> 0 | Q502: =(O502+P502)/2 -> 0 | R502: =IF(_xlfn.BITAND(P502>0.4999, Q502>0.4999)=1,1,0) -> 0
A503: Fine-grained smart contract vulnerability detection by heterogeneous code feature learning and automated dataset construction | P503: =(D503+E503+F503+G503+H503+I503+J503)/7 -> 0 | Q503: =(O503+P503)/2 -> 0 | R503: =IF(_xlfn.BITAND(P503>0.4999, Q503>0.4999)=1,1,0) -> 0
A504: Eth2Vec: Learning contract-wide code representations for vulnerability detection on Ethereum smart contracts | P504: =(D504+E504+F504+G504+H504+I504+J504)/7 -> 0 | Q504: =(O504+P504)/2 -> 0 | R504: =IF(_xlfn.BITAND(P504>0.4999, Q504>0.4999)=1,1,0) -> 0
A505: Smart contract vulnerability detection based on semantic graph and residual graph convolutional networks with edge attention | P505: =(D505+E505+F505+G505+H505+I505+J505)/7 -> 0 | Q505: =(O505+P505)/2 -> 0 | R505: =IF(_xlfn.BITAND(P505>0.4999, Q505>0.4999)=1,1,0) -> 0
A506: Modeling and Security Verification of State-Based Smart Contracts | B506: https://www.sciencedirect.com/science/article/pii/S240589632202303X | P506: =(D506+E506+F506+G506+H506+I506+J506)/7 -> 0 | Q506: =(O506+P506)/2 -> 0 | R506: =IF(_xlfn.BITAND(P506>0.4999, Q506>0.4999)=1,1,0) -> 0
A507: Security reinforcement for Ethereum virtual machine | B507: https://www.sciencedirect.com/science/article/pii/S0306457321000674 | J507: =Info!$B$44 -> 0 | P507: =(D507+E507+F507+G507+H507+I507+J507)/7 -> 0 | Q507: =(O507+P507)/2 -> 0 | R507: =IF(_xlfn.BITAND(P507>0.4999, Q507>0.4999)=1,1,0) -> 0
...

Sheet TU_Wien_CatalogPlus
A1: Title | B1: Link | C1: Pubblication Class | D1: Q1 | E1: Q2 | F1: Q3 | G1: Q4 | H1: Q5 | I1: Q6 | J1: Q7 | K1: Exc.Crit | L1: Inc.Crit | M1: Pubblication Venue | N1: Vanue Name | O1: IDQ | P1: CDQ | Q1: FDQ | R1: Selected
A2: A Novel Machine Learning-Based Analysis Model for Smart Contract Vulnerability | B2: https://catalogplus.tuwien.at/permalink/f/1m011kq/TN_cdi_webofscience_primary_000687462200004CitationCount | C2: PS | D2: =Info!$B$48 -> 1 | E2: =Info!$B$53 -> 1 | L2: 1 | M2: Journal Article | N2: Security and Communication Networks | O2: 0.8 | P2: =(D2+E2)/2 -> 1 | Q2: =(O2+P2)/2 -> 0.9 | R2: =IF(_xlfn.BITAND(P2>0.4999, Q2>0.4999)=1,1,0) -> 1
A3: Aroc: An Automatic Repair Framework for On-Chain Smart Contracts | B3: https://catalogplus.tuwien.at/permalink/f/1m011kq/TN_cdi_crossref_primary_10_1109_TSE_=Info!$A$43_3123170 | C3: PS | D3: =Info!$B$49 -> 0.6 | E3: =Info!$B$53 -> 1 | L3: 2,3 | M3: Journal Article | N3: IEEE Transactions on Software Engineering | O3: 1 | P3: =(D3+E3)/2 -> 0.8 | Q3: =(O3+P3)/2 -> 0.9 | R3: =IF(_xlfn.BITAND(P3>0.4999, Q3>0.4999)=1,1,0) -> 1
A4: CBGRU: A Detection Method of Smart Contract Vulnerability Based on a Hybrid Model | B4: https://catalogplus.tuwien.at/permalink/f/1m011kq/TN_cdi_doaj_primary_oai_doaj_org_article_040ca2e2762c4fed9f705272910ece1d | C4: PS | D4: =Info!$B$48 -> 1 | E4: =Info!$B$54 -> 0 | L4: 2 | M4: Journal Article | N4: Sensors | O4: 0.8 | P4: =(D4+E4)/2 -> 0.5 | Q4: =(O4+P4)/2 -> 0.65 | R4: =IF(_xlfn.BITAND(P4>0.4999, Q4>0.4999)=1,1,0) -> 1
A5: CodeNet: Code-Targeted Convolutional Neural Network Architecture for Smart Contract Vulnerability Detection | B5: https://catalogplus.tuwien.at/permalink/f/1m011kq/TN_cdi_ieee_primary_9740682 | C5: PS | D5: =Info!$B$48 -> 1 | E5: =Info!$B$52 -> 0 | L5: 2,3 | M5: Journal Article | N5: IEEE Access | O5: 1 | P5: =(D5+E5)/2 -> 0.5 | Q5: =(O5+P5)/2 -> 0.75 | R5: =IF(_xlfn.BITAND(P5>0.4999, Q5>0.4999)=1,1,0) -> 1
A6: Combining Graph Neural Networks With Expert Knowledge for Smart Contract Vulnerability Detection | B6: https://catalogplus.tuwien.at/permalink/f/1m011kq/TN_cdi_crossref_primary_10_1109_TKDE_=Info!$A$43_3095196 | C6: PS | D6: =Info!$B$48 -> 1 | E6: =Info!$B$52 -> 0 | L6: 2 | M6: Journal Article | N6: IEEE Transactions on Knowledge and Data Engineering | O6: 1 | P6: =(D6+E6)/2 -> 0.5 | Q6: =(O6+P6)/2 -> 0.75 | R6: =IF(_xlfn.BITAND(P6>0.4999, Q6>0.4999)=1,1,0) -> 1
A7: DeeSCVHunter: A Deep Learning-Based Framework for Smart Contract Vulnerability Detection | B7: https://catalogplus.tuwien.at/permalink/f/1m011kq/TN_cdi_ieee_primary_9534324 | C7: PS | D7: =Info!$B$48 -> 1 | E7: =Info!$B$53 -> 1 | L7: 2 | M7: Conference Proceeding or Workshop | N7: International Joint Conference on Neural Networks | O7: 1 | P7: =(D7+E7)/2 -> 1 | Q7: =(O7+P7)/2 -> 1 | R7: =IF(_xlfn.BITAND(P7>0.4999, Q7>0.4999)=1,1,0) -> 1
A8: DefectChecker: Automated Smart Contract Defect Detection by Analyzing EVM Bytecode | B8: https://catalogplus.tuwien.at/permalink/f/1m011kq/TN_cdi_crossref_primary_10_1109_TSE_=Info!$A$43_3054928 | C8: PS | D8: =Info!$B$48 -> 1 | E8: =Info!$B$53 -> 1 | L8: 2,3 | M8: Journal Article | N8: IEEE Transactions on Software Engineering | O8: 1 | P8: =(D8+E8)/2 -> 1 | Q8: =(O8+P8)/2 -> 1 | R8: =IF(_xlfn.BITAND(P8>0.4999, Q8>0.4999)=1,1,0) -> 1
A9: Defining Smart Contract Defects on Ethereum | B9: https://catalogplus.tuwien.at/permalink/f/1m011kq/TN_cdi_ieee_primary_9072659 | C9: Survey | D9: =Info!$B$16 -> 1 | E9: =Info!$B$19 -> 1 | F9: =Info!$B$24 -> 1 | G9: =Info!$B$31 -> 0.3 | H9: =Info!$B$37 -> 0 | I9: =Info!$B$40 -> 0 | J9: =Info!$B$43 -> 0.5 | L9: 1 | M9: Journal Article | N9: IEEE Transactions on software engineering | O9: 1 | P9: =(D9+E9+F9+G9+H9+I9+J9)/6 -> 0.63333333 | Q9: =(O9+P9)/2 -> 0.81666667 | R9: =IF(_xlfn.BITAND(P9>0.4999, Q9>0.4999)=1,1,0) -> 1
A10: Detect Defects of Solidity Smart Contract Based on the Knowledge Graph | B10: https://catalogplus.tuwien.at/permalink/f/1m011kq/TN_cdi_ieee_primary_10025570 | C10: PS | D10: =Info!$B$51 -> 0 | E10: =Info!$B$53 -> 1 | L10: 2,3 | M10: Journal Article | N10: IEEE transactions on reliability | O10: 1 | P10: =(D10+E10)/2 -> 0.5 | Q10: =(O10+P10)/2 -> 0.75 | R10: =IF(_xlfn.BITAND(P10>0.4999, Q10>0.4999)=1,1,0) -> 1
A11: Detection of Vulnerabilities of Blockchain Smart Contracts | B11: https://catalogplus.tuwien.at/permalink/f/1m011kq/TN_cdi_crossref_primary_10_1109_JIOT_2023_3241544 | C11: Survey | D11: =Info!$B$17 -> 0 | E11: =Info!$B$20 -> 0.6 | F11: =Info!$B$25 -> 0.6 | G11: =Info!$B$29 -> 1 | H11: =Info!$B$36 -> 0.3 | I11: =Info!$B$40 -> 0 | J11: =Info!$B$42 -> 1 | L11: 2 | M11: Journal Article | N11: IEEE internet of things journal | O11: 1 | P11: =(D11+E11+F11+G11+H11+I11+J11)/6 -> 0.58333333 | Q11: =(O11+P11)/2 -> 0.79166667 | R11: =IF(_xlfn.BITAND(P11>0.4999, Q11>0.4999)=1,1,0) -> 1
A12: Ethereum Smart Contract Analysis Tools: A Systematic Review | B12: https://catalogplus.tuwien.at/permalink/f/1m011kq/TN_cdi_crossref_primary_10_1109_ACCESS_2022_3169902 | C12: SLR | D12: =Info!$B$16 -> 1 | E12: =Info!$B$19 -> 1 | F12: =Info!$B$25 -> 0.6 | G12: =Info!$B$31 -> 0.3 | H12: =Info!$B$37 -> 0 | I12: =Info!$B$40 -> 0 | J12: =Info!$B$43 -> 0.5 | L12: 2 | M12: Journal Article | N12: IEEE Access | O12: 1 | P12: =(D12+E12+F12+G12+H12+I12+J12)/6 -> 0.56666667 | Q12: =(O12+P12)/2 -> 0.78333333 | R12: =IF(_xlfn.BITAND(P12>0.4999, Q12>0.4999)=1,1,0) -> 1
A13: EtherFuzz: Mutation Fuzzing Smart Contracts for TOD Vulnerability Detection | B13: https://catalogplus.tuwien.at/permalink/f/1m011kq/TN_cdi_unpaywall_primary_10_1155_2022_1565007 | C13: PS | D13: =Info!$B$50 -> 0.3 | E13: =Info!$B$53 -> 1 | L13: 2,3 | M13: Journal Article | N13: Wireless communications and mobile computing | O13: 0.5 | P13: =(D13+E13)/2 -> 0.65 | Q13: =(O13+P13)/2 -> 0.575 | R13: =IF(_xlfn.BITAND(P13>0.4999, Q13>0.4999)=1,1,0) -> 1
A14: EthVer: Formal Verification of Randomized Ethereum Smart Contracts | B14: https://catalogplus.tuwien.at/permalink/f/1m011kq/TN_cdi_openaire_primary_doi_9db40bfca1380b1075be1223128ea8e9 | C14: PS | D14: =Info!$B$51 -> 0 | E14: =Info!$B$53 -> 1 | J14: =Info!$B$44 -> 0 | L14: 2 | M14: Conference Proceeding or Workshop | N14: Financial Cryptography and Data Security | O14: 1 | P14: =(D14+E14)/2 -> 0.5 | Q14: =(O14+P14)/2 -> 0.75 | R14: =IF(_xlfn.BITAND(P14>0.4999, Q14>0.4999)=1,1,0) -> 1
A15: GraBit: A Sequential Model-Based Framework for Smart Contract Vulnerability Detection | B15: https://catalogplus.tuwien.at/permalink/f/1m011kq/TN_cdi_ieee_primary_10301241 | C15: PS | D15: =Info!$B$51 -> 0 | E15: =Info!$B$53 -> 1 | L15: 2,3 | M15: Conference Proceeding or Workshop | N15: 2023 IEEE 34th International Symposium on Software Reliability Engineering (ISSRE) | O15: 1 | P15: =(D15+E15)/2 -> 0.5 | Q15: =(O15+P15)/2 -> 0.75 | R15: =IF(_xlfn.BITAND(P15>0.4999, Q15>0.4999)=1,1,0) -> 1
A16: HGAT: smart contract vulnerability detection method based on hierarchical graph attention network | B16: https://catalogplus.tuwien.at/permalink/f/1m011kq/TN_cdi_doaj_primary_oai_doaj_org_article_8d0de5bbfe0640e6b2b896cb364dca35 | C16: PS | D16: =Info!$B$51 -> 0 | E16: =Info!$B$53 -> 1 | L16: 2,3 | M16: Journal Article | N16: Journal of Cloud Computing | O16: 0.8 | P16: =(D16+E16)/2 -> 0.5 | Q16: =(O16+P16)/2 -> 0.65 | R16: =IF(_xlfn.BITAND(P16>0.4999, Q16>0.4999)=1,1,0) -> 1
A17: Hunting Vulnerable Smart Contracts via Graph Embedding Based Bytecode Matching | B17: https://catalogplus.tuwien.at/permalink/f/1m011kq/TN_cdi_webofscience_primary_000616307600013 | C17: PS | D17: =Info!$B$48 -> 1 | E17: =Info!$B$54 -> 0 | L17: 2 | M17: Journal Article | N17: IEEE transactions on information forensics and security | O17: 1 | P17: =(D17+E17)/2 -> 0.5 | Q17: =(O17+P17)/2 -> 0.75 | R17: =IF(_xlfn.BITAND(P17>0.4999, Q17>0.4999)=1,1,0) -> 1
A18: MANDO-HGT: Heterogeneous Graph Transformers for Smart Contract Vulnerability Detection | B18: https://catalogplus.tuwien.at/permalink/f/1m011kq/TN_cdi_ieee_primary_10174104 | C18: PS | D18: =Info!$B$51 -> 0 | E18: =Info!$B$53 -> 1 | L18: 2,3 | M18: Conference Proceeding or Workshop | N18: IEEE/ACM 20th International Conference on Mining Software Repositories (MSR) | O18: 1 | P18: =(D18+E18)/2 -> 0.5 | Q18: =(O18+P18)/2 -> 0.75 | R18: =IF(_xlfn.BITAND(P18>0.4999, Q18>0.4999)=1,1,0) -> 1
A19: M-A-R: a Dynamic Symbol Execution Detection Method for Smart Contract Reentry Vulnerability | B19: https://catalogplus.tuwien.at/permalink/f/1m011kq/TN_cdi_openaire_primary_doi_16749d61a881ccfd7e0041b3de04ea79 | C19: PS | D19: =Info!$B$51 -> 0 | E19: =Info!$B$53 -> 1 | L19: 2,3 | M19: Journal Article | N19: Blockchain and Trustworthy Systems | O19: 0.5 | P19: =(D19+E19)/2 -> 0.5 | Q19: =(O19+P19)/2 -> 0.5 | R19: =IF(_xlfn.BITAND(P19>0.4999, Q19>0.4999)=1,1,0) -> 1
A20: Mutation testing for integer overflow in ethereum smart contracts | B20: https://catalogplus.tuwien.at/permalink/f/1m011kq/TN_cdi_openaire_primary_doi_68a8d6db1eef5feb5fa2632cb54f82ee | C20: PS | D20: =Info!$B$48 -> 1 | E20: =Info!$B$54 -> 0 | L20: 1 | M20: Journal Article | N20: Tsinghua science and technology | O20: 1 | P20: =(D20+E20)/2 -> 0.5 | Q20: =(O20+P20)/2 -> 0.75 | R20: =IF(_xlfn.BITAND(P20>0.4999, Q20>0.4999)=1,1,0) -> 1
A21: PSCVFinder: A Prompt-Tuning Based Framework for Smart Contract Vulnerability Detection | B21: https://catalogplus.tuwien.at/permalink/f/1m011kq/TN_cdi_ieee_primary_10301244 | C21: PS | D21: =Info!$B$51 -> 0 | E21: =Info!$B$53 -> 1 | L21: 2,3 | M21: Conference Proceeding or Workshop | N21: 2023 IEEE 34th International Symposium on Software Reliability Engineering (ISSRE) | O21: 1 | P21: =(D21+E21)/2 -> 0.5 | Q21: =(O21+P21)/2 -> 0.75 | R21: =IF(_xlfn.BITAND(P21>0.4999, Q21>0.4999)=1,1,0) -> 1
A22: Rethinking Smart Contract Fuzzing: Fuzzing With Invocation Ordering and Important Branch Revisiting | B22: https://catalogplus.tuwien.at/permalink/f/1m011kq/TN_cdi_unpaywall_primary_10_1109_tifs_2023_3237370 | C22: PS | D22: =Info!$B$48 -> 1 | E22: =Info!$B$53 -> 1 | L22: 1 | M22: Journal Article | N22: IEEE transactions on information forensics and security | O22: 1 | P22: =(D22+E22)/2 -> 1 | Q22: =(O22+P22)/2 -> 1 | R22: =IF(_xlfn.BITAND(P22>0.4999, Q22>0.4999)=1,1,0) -> 1
A23: SAILFISH: Vetting Smart Contract State-Inconsistency Bugs in Seconds | B23: https://catalogplus.tuwien.at/permalink/f/1m011kq/TN_cdi_ieee_primary_9833721 | C23: PS | D23: =Info!$B$48 -> 1 | E23: =Info!$B$53 -> 1 | L23: 1 | M23: Conference Proceeding or Workshop | N23: IEEE Symposium on Security and Privacy | O23: 1 | P23: =(D23+E23)/2 -> 1 | Q23: =(O23+P23)/2 -> 1 | R23: =IF(_xlfn.BITAND(P23>0.4999, Q23>0.4999)=1,1,0) -> 1
A24: SCcheck: A Novel Graph-driven and Attention-enabled Smart Contract Vulnerability Detection Framework for Web 3.0 Ecosystem | B24: https://catalogplus.tuwien.at/permalink/f/1m011kq/TN_cdi_crossref_primary_10_1109_TNSE_2023_3324942 | C24: PS | D24: =Info!$B$51 -> 0 | E24: =Info!$B$53 -> 1 | L24: 2,3 | M24: Journal Article | N24: IEEE transactions on network science and engineering | O24: 1 | P24: =(D24+E24)/2 -> 0.5 | Q24: =(O24+P24)/2 -> 0.75 | R24: =IF(_xlfn.BITAND(P24>0.4999, Q24>0.4999)=1,1,0) -> 1
A25: SESCon: Secure Ethereum Smart Contracts by Vulnerable Patterns’ Detection | B25: https://catalogplus.tuwien.at/permalink/f/1m011kq/TN_cdi_openaire_primary_doi_dedup_98e75c49e07c5a0eab2b3183f1647f16 | C25: PS | D25: =Info!$B$51 -> 0 | E25: =Info!$B$53 -> 1 | L25: 1,2,3 | M25: Journal Article | N25: Security and communication networks | O25: 0.8 | P25: =(D25+E25)/2 -> 0.5 | Q25: =(O25+P25)/2 -> 0.65 | R25: =IF(_xlfn.BITAND(P25>0.4999, Q25>0.4999)=1,1,0) -> 1
A26: sFuzz2.0: Storage‐access pattern guided smart contract fuzzing | B26: https://catalogplus.tuwien.at/permalink/f/1m011kq/TN_cdi_openaire_primary_doi_16ead8da3425bccb9531a128177db014 | C26: PS | D26: =Info!$B$51 -> 0 | E26: =Info!$B$53 -> 1 | L26: 2,3 | M26: Journal Article | N26: Journal of software : evolution and process | O26: 0.8 | P26: =(D26+E26)/2 -> 0.5 | Q26: =(O26+P26)/2 -> 0.65 | R26: =IF(_xlfn.BITAND(P26>0.4999, Q26>0.4999)=1,1,0) -> 1
A27: SGUARD: Towards Fixing Vulnerable Smart Contracts Automatically | B27: https://catalogplus.tuwien.at/permalink/f/1m011kq/TN_cdi_ieee_primary_9519444 | C27: PS | D27: =Info!$B$48 -> 1 | E27: =Info!$B$53 -> 1 | L27: 2,3 | M27: Conference Proceeding or Workshop | N27: IEEE Symposium on Security and Privacy | O27: 1 | P27: =(D27+E27)/2 -> 1 | Q27: =(O27+P27)/2 -> 1 | R27: =IF(_xlfn.BITAND(P27>0.4999, Q27>0.4999)=1,1,0) -> 1
A28: Smart Contract Vulnerability Detection Model Based on Multi-Task Learning | B28: https://catalogplus.tuwien.at/permalink/f/1m011kq/TN_cdi_doaj_primary_oai_doaj_org_article_d7855428d30e48bf8bd7c088c2028f08 | C28: PS | D28: =Info!$B$48 -> 1 | E28: =Info!$B$52 -> 0 | L28: 2 | M28: Journal Article | N28: Sensors | O28: 0.8 | P28: =(D28+E28)/2 -> 0.5 | Q28: =(O28+P28)/2 -> 0.65 | R28: =IF(_xlfn.BITAND(P28>0.4999, Q28>0.4999)=1,1,0) -> 1
A29: SmartBugs 2.0: An Execution Framework for Weakness Detection in Ethereum Smart Contracts | B29: https://catalogplus.tuwien.at/permalink/f/1m011kq/TN_cdi_ieee_primary_10298326 | C29: PS | D29: =Info!$B$51 -> 0 | E29: =Info!$B$53 -> 1 | L29: 2,3 | M29: Conference Proceeding or Workshop | N29: 2023 38th IEEE/ACM International Conference on Automated Software Engineering (ASE) | O29: 1 | P29: =(D29+E29)/2 -> 0.5 | Q29: =(O29+P29)/2 -> 0.75 | R29: =IF(_xlfn.BITAND(P29>0.4999, Q29>0.4999)=1,1,0) -> 1
A30: SoliTester: Detecting exploitable external‐risky vulnerability in smart contracts using contract account triggering method | B30: https://catalogplus.tuwien.at/permalink/f/1m011kq/TN_cdi_crossref_primary_10_1002_smr_2633 | C30: PS | D30: =Info!$B$51 -> 0 | E30: =Info!$B$53 -> 1 | L30: 2,3 | M30: Journal Article | N30: Journal of software : evolution and process | O30: 0.8 | P30: =(D30+E30)/2 -> 0.5 | Q30: =(O30+P30)/2 -> 0.65 | R30: =IF(_xlfn.BITAND(P30>0.4999, Q30>0.4999)=1,1,0) -> 1
A31: SPCBIG-EC: A Robust Serial Hybrid Model for Smart Contract Vulnerability Detection | B31: https://catalogplus.tuwien.at/permalink/f/1m011kq/TN_cdi_doaj_primary_oai_doaj_org_article_674a4b27177045848022dc9387fb8a5f | C31: PS | D31: =Info!$B$48 -> 1 | E31: =Info!$B$54 -> 0 | L31: 2 | M31: Journal Article | N31: Sensors | O31: 0.8 | P31: =(D31+E31)/2 -> 0.5 | Q31: =(O31+P31)/2 -> 0.65 | R31: =IF(_xlfn.BITAND(P31>0.4999, Q31>0.4999)=1,1,0) -> 1
A32: SuperDetector: A Framework for Performance Detection on Vulnerabilities of Smart Contracts | B32: https://catalogplus.tuwien.at/permalink/f/1m011kq/TN_cdi_iop_journals_10_1088_1742_6596_2289_1_012010 | C32: PS | D32: =Info!$B$51 -> 0 | E32: =Info!$B$53 -> 1 | L32: 2,3 | M32: Conference Proceeding or Workshop | N32: Journal of physics. Conference series, 2022 | O32: 0.5 | P32: =(D32+E32)/2 -> 0.5 | Q32: =(O32+P32)/2 -> 0.5 | R32: =IF(_xlfn.BITAND(P32>0.4999, Q32>0.4999)=1,1,0) -> 1
A33: Systematic Review of Security Vulnerabilities in Ethereum Blockchain Smart Contract | B33: https://catalogplus.tuwien.at/permalink/f/1m011kq/TN_cdi_openaire_primary_doi_dedup_bc169163780df3ad5ed32cb890de6924 | C33: SLR | D33: =Info!$B$16 -> 1 | E33: =Info!$B$20 -> 0.6 | F33: =Info!$B$25 -> 0.6 | G33: =Info!$B$29 -> 1 | H33: =Info!$B$36 -> 0.3 | I33: =Info!$B$40 -> 0 | J33: =Info!$B$44 -> 0 | L33: 1 | M33: Journal Article | N33: IEEE Access | O33: 1 | P33: =(D33+E33+F33+G33+H33+I33+J33)/6 -> 0.58333333 | Q33: =(O33+P33)/2 -> 0.79166667 | R33: =IF(_xlfn.BITAND(P33>0.4999, Q33>0.4999)=1,1,0) -> 1
A34: Tips: towards automating patch suggestion for vulnerable smart contracts | B34: https://catalogplus.tuwien.at/permalink/f/1m011kq/TN_cdi_proquest_journals_2864595129 | C34: PS | D34: =Info!$B$51 -> 0 | E34: =Info!$B$53 -> 1 | L34: 3 | M34: Journal Article | N34: Automated Software Engineering | O34: 0.8 | P34: =(D34+E34)/2 -> 0.5 | Q34: =(O34+P34)/2 -> 0.65 | R34: =IF(_xlfn.BITAND(P34>0.4999, Q34>0.4999)=1,1,0) -> 1
A35: Toward Vulnerability Detection for Ethereum Smart Contracts Using Graph-Matching Network | B35: https://catalogplus.tuwien.at/permalink/f/1m011kq/TN_cdi_doaj_primary_oai_doaj_org_article_55d238d42ccb48bfb33eadc5a3a04f1c | C35: PS | D35: =Info!$B$50 -> 0.3 | E35: =Info!$B$53 -> 1 | L35: 1 | M35: Journal Article | N35: Future Internet | O35: 0.8 | P35: =(D35+E35)/2 -> 0.65 | Q35: =(O35+P35)/2 -> 0.725 | R35: =IF(_xlfn.BITAND(P35>0.4999, Q35>0.4999)=1,1,0) -> 1
A36: TxMirror: When the Dynamic EVM Stack Meets Transactions for Smart Contract Vulnerability Detection | B36: https://catalogplus.tuwien.at/permalink/f/1m011kq/TN_cdi_doaj_primary_oai_doaj_org_article_83944d1895ad427784acedab4ef8136e | C36: PS | D36: =Info!$B$51 -> 0 | E36: =Info!$B$53 -> 1 | L36: 2 | M36: Journal Article | N36: Symmetry | O36: 0.8 | P36: =(D36+E36)/2 -> 0.5 | Q36: =(O36+P36)/2 -> 0.65 | R36: =IF(_xlfn.BITAND(P36>0.4999, Q36>0.4999)=1,1,0) -> 1
A37: Unknown Threats Detection Methods of Smart Contracts | B37: https://catalogplus.tuwien.at/permalink/f/1m011kq/TN_cdi_proquest_journals_2918030176 | C37: PS | D37: =Info!$B$16 -> 1 | E37: =Info!$B$20 -> 0.6 | F37: =Info!$B$24 -> 1 | G37: =Info!$B$31 -> 0.3 | H37: =Info!$B$37 -> 0 | I37: =Info!$B$40 -> 0 | J37: =Info!$B$42 -> 1 | L37: 1.2 | M37: Journal Article | N37: IEEE Internet of Things Journal | O37: 1 | P37: =(D37+E37+F37+G37+H37+I37+J37)/6 -> 0.65 | Q37: =(O37+P37)/2 -> 0.825 | R37: =IF(_xlfn.BITAND(P37>0.4999, Q37>0.4999)=1,1,0) -> 1
A38: VulHunter: Hunting Vulnerable Smart Contracts at EVM Bytecode-Level via Multiple Instance Learning | B38: https://catalogplus.tuwien.at/permalink/f/1m011kq/TN_cdi_ieee_primary_10261219 | C38: PS | D38: =Info!$B$51 -> 0 | E38: =Info!$B$53 -> 1 | L38: 1.2 | M38: Journal Article | N38: IEEE Transactions on Software Engineering | O38: 1 | P38: =(D38+E38)/2 -> 0.5 | Q38: =(O38+P38)/2 -> 0.75 | R38: =IF(_xlfn.BITAND(P38>0.4999, Q38>0.4999)=1,1,0) -> 1
A39: OpenSCV: an open hierarchical taxonomy for smart contract vulnerabilities | B39: https://catalogplus.tuwien.at/permalink/f/1m011kq/TN_cdi_proquest_journals_3069403316 | C39: Survey | D39: 0 | E39: 1 | F39: 1 | G39: 1 | H39: 0 | I39: 0 | J39: 1 | L39: 3 | M39: Journal Article | N39: EMSE | O39: 1 | P39: =(D39+E39)/2 -> 0.5 | Q39: =(O39+P39)/2 -> 0.75 | R39: =IF(_xlfn.BITAND(P39>0.4999, Q39>0.4999)=1,1,0) -> 1
A40: ContractArmor: Attack Surface Generator for Smart Contracts | B40: https://catalogplus.tuwien.at/permalink/f/1m011kq/TN_cdi_crossref_primary_10_1016_j_procs_2023_12_151 | C40: PS | D40: 0.3 | E40: 1 | M40: Conference Proceeding or Workshops | N40: Procedia computer science, 2024, Vol.231, p.8-15 | O40: 0.8 | P40: 0.5 | Q40: 0.725 | R40: =IF(_xlfn.BITAND(P40>0.4999, Q40>0.4999)=1,1,0) -> 1
A41: DeepFusion: Smart Contract Vulnerability Detection Via Deep Learning and Data Fusion | B41: https://catalogplus.tuwien.at/permalink/f/1m011kq/TN_cdi_crossref_primary_10_1109_TR_2024_3480010 | C41: PS | D41: 0 | E41: 1 | N41: IEEE transactions on reliability, 2024-10, p.1-15 | O41: 1 | P41: 0.5 | Q41: 0.75 | R41: =IF(_xlfn.BITAND(P41>0.4999, Q41>0.4999)=1,1,0) -> 1
A42: ReenSAT: Reentrancy Vulnerability Detection in Smart Contracts Using Semantic-Enhanced SAT Evaluation | B42: https://catalogplus.tuwien.at/permalink/f/1m011kq/TN_cdi_ieee_primary_10752786 | C42: PS | D42: 0 | E42: 1 | N42: IEEE transactions on reliability, 2024-11, p.1-15 | O42: 1 | P42: 0.5 | Q42: 0.75 | R42: =IF(_xlfn.BITAND(P42>0.4999, Q42>0.4999)=1,1,0) -> 1
A43: A comprehensive survey of smart contract security: State of the art and research directions | B43: https://catalogplus.tuwien.at/permalink/f/1m011kq/TN_cdi_crossref_primary_10_1016_j_jnca_2024_103882 | C43: Survey | D43: 0 | E43: 0.6 | F43: 0.6 | G43: 1 | H43: 1 | I43: 0 | J43: 1 | M43: Journal Article | N43: Journal of network and computer applications, 2024-06, Vol.226, p.103882, Article 103882 | O43: 1 | P43: 0.6 | Q43: 0.8 | R43: =IF(_xlfn.BITAND(P43>0.4999, Q43>0.4999)=1,1,0) -> 1
A44: An integrated deep learning model for Ethereum smart contract vulnerability detection | B44: https://catalogplus.tuwien.at/permalink/f/1m011kq/TN_cdi_proquest_journals_2917414619 | C44: PS | D44: 1 | E44: 0 | M44: Journal Article | N44: International journal of information security, 2024-02, Vol.23 (1), p.557-575 | O44: 0.8 | P44: 0.5 | Q44: 0.65 | R44: =IF(_xlfn.BITAND(P44>0.4999, Q44>0.4999)=1,1,0) -> 1
A45: Ethereum Smart Contract Vulnerability Detection and Machine Learning-Driven Solutions: A Systematic Literature Review | B45: https://catalogplus.tuwien.at/permalink/f/1m011kq/TN_cdi_proquest_journals_3072317710 | C45: SLR | D45: 1 | E45: 1 | F45: 0.6 | G45: 0.6 | H45: 0.6 | I45: 0 | J45: 1 | M45: Journal Article | N45: Electronics (Basel), 2024-06, Vol.13 (12), p.2295 | O45: 0.8 | P45: =SUM(D45:J45)/7 -> 0.68571429 | Q45: =SUM(O45:P45)/2 -> 0.74285714 | R45: =IF(_xlfn.BITAND(P45>0.4999, Q45>0.4999)=1,1,0) -> 1
A46: SafeCheck: Detecting smart contract vulnerabilities based on static program analysis methods | B46: https://catalogplus.tuwien.at/permalink/f/1m011kq/TN_cdi_crossref_primary_10_1002_spy2_393 | C46: PS | D46: 0 | E46: 1 | M46: Journal Article | N46: Security and privacy, 2024-09, Vol.7 (5), p.n/a | O46: 0.8 | P46: 0.5 | Q46: 0.65 | R46: =IF(_xlfn.BITAND(P46>0.4999, Q46>0.4999)=1,1,0) -> 1
A47: SolGPT: A GPT-Based Static Vulnerability Detection Model for Enhancing Smart Contract Security | B47: https://catalogplus.tuwien.at/permalink/f/1m011kq/TN_cdi_springer_books_10_1007_978_981_97_0859_8_3 | C47: PS | D47: 0.3 | E47: 1 | N47: Algorithms and Architectures for Parallel Processing, 2024, Vol.14490, p.42-62 | O47: 0.8 | P47: 0.65 | Q47: 0.725 | R47: =IF(_xlfn.BITAND(P47>0.4999, Q47>0.4999)=1,1,0) -> 1
A48: ContractGNN: Ethereum Smart Contract Vulnerability Detection Based on Vulnerability Sub-Graphs and Graph Neural Networks | B48: https://catalogplus.tuwien.at/permalink/f/1m011kq/TN_cdi_ieee_primary_10700860 | C48: PS | D48: 0 | E48: 1 | N48: IEEE transactions on network science and engineering, 2024-11, Vol.11 (6), p.6382-6395 | O48: 1 | P48: 0.5 | Q48: 0.75 | R48: =IF(_xlfn.BITAND(P48>0.4999, Q48>0.4999)=1,1,0) -> 1
A49: SCcheck: A Novel Graph-Driven and Attention- Enabled Smart Contract Vulnerability Detection Framework for Web 3.0 Ecosystem | B49: https://catalogplus.tuwien.at/permalink/f/1m011kq/TN_cdi_proquest_journals_3094516749 | C49: PS | D49: 0.6 | E49: 1 | N49: IEEE transactions on network science and engineering, 2024-09, Vol.11 (5), p.4007-4019 | O49: 1 | P49: 0.8 | Q49: 0.9 | R49: =IF(_xlfn.BITAND(P49>0.4999, Q49>0.4999)=1,1,0) -> 1
A50: Erinys: Efficient fuzzing by function invoke sequence generation for smart contracts | B50: https://catalogplus.tuwien.at/permalink/f/1m011kq/TN_cdi_acm_books_10_1145_3697355_3697394_brief | C50: PS | D50: 0 | E50: 1 | M50: Conference Proceeding or Workshops | N50: Proceedings of the 2024 8th International Conference on Big Data and Internet of Things, 2024, p.236-241 | O50: 0.5 | P50: 0.5 | Q50: 0.5 | R50: =IF(_xlfn.BITAND(P50>0.4999, Q50>0.4999)=1,1,0) -> 1
A51: ContractWard: Automated Vulnerability Detection Models for Ethereum Smart Contracts | B51: https://catalogplus.tuwien.at/permalink/f/1m011kq/TN_cdi_unpaywall_primary_10_1109_tnse_2020_2968505 | C51: PS | K51: 5 | L51: 2 | M51: Journal Article | N51: IEEE transactions on network science and engineering | O51: 1 | P51: =(D51+E51)/2 -> 0 | Q51: =(O51+P51)/2 -> 0.5 | R51: =IF(_xlfn.BITAND(P51>0.4999, Q51>0.4999)=1,1,0) -> 0
A52: A Distributed framework for detecting DDoS attacks in smart contract‐based Blockchain‐IoT Systems by leveraging Fog computing | B52: https://catalogplus.tuwien.at/permalink/f/1m011kq/TN_cdi_crossref_primary_10_1002_ett_4112 | C52: PS | K52: 5 | L52: 2 | M52: Journal Article | N52: Transactions on emerging telecommunications technologies | O52: 0.8 | P52: =(D52+E52)/2 -> 0 | Q52: =(O52+P52)/2 -> 0.4 | R52: =IF(_xlfn.BITAND(P52>0.4999, Q52>0.4999)=1,1,0) -> 0
A53: NeuCheck: A more practical Ethereum smart contract security analysis tool | B53: https://catalogplus.tuwien.at/permalink/f/1m011kq/TN_cdi_webofscience_primary_000484100100001CitationCount | C53: PS | K53: 5 | M53: Journal Article | N53: Software, practice & experience | O53: 0.8 | P53: =(D53+E53)/2 -> 0 | Q53: =(O53+P53)/2 -> 0.4 | R53: =IF(_xlfn.BITAND(P53>0.4999, Q53>0.4999)=1,1,0) -> 0
A54: TP-Detect: trigram-pixel based vulnerability detection for Ethereum smart contracts | B54: https://catalogplus.tuwien.at/permalink/f/1m011kq/TN_cdi_openaire_primary_doi_906ad9d7b2920dce9e57a18d055112a4 | C54: PS | D54: =Info!$B$51 -> 0 | E54: =Info!$B$54 -> 0 | L54: 2 | M54: Journal Article | N54: Multimedia tools and applications | O54: 0.8 | P54: =(D54+E54)/2 -> 0 | Q54: =(O54+P54)/2 -> 0.4 | R54: =IF(_xlfn.BITAND(P54>0.4999, Q54>0.4999)=1,1,0) -> 0
A55: An integrated deep learning model for Ethereum smart contract vulnerability detection | B55: https://catalogplus.tuwien.at/permalink/f/1m011kq/TN_cdi_proquest_journals_2917414619 | C55: PS | D55: =Info!$B$51 -> 0 | E55: =Info!$B$54 -> 0 | L55: 2 | M55: Journal Article | N55: International journal of information security | O55: 0.8 | P55: =(D55+E55)/2 -> 0 | Q55: =(O55+P55)/2 -> 0.4 | R55: =IF(_xlfn.BITAND(P55>0.4999, Q55>0.4999)=1,1,0) -> 0
A56: A Novel Smart Contract Reentrancy Vulnerability Detection Model based on BiGAS | B56: https://catalogplus.tuwien.at/permalink/f/1m011kq/TN_cdi_openaire_primary_doi_d3de720fdfede7f356c7e8d4704a54d8 | C56: PS | D56: =Info!$B$51 -> 0 | E56: =Info!$B$54 -> 0 | L56: 2 | M56: Journal Article | N56: Journal of signal processing systems | O56: 0.5 | P56: =(D56+E56)/2 -> 0 | Q56: =(O56+P56)/2 -> 0.25 | R56: =IF(_xlfn.BITAND(P56>0.4999, Q56>0.4999)=1,1,0) -> 0
